Workbook
Name MobileInternet: data!$B$15:$B$16
Name HouseholdAccessories: data!$B$12:$B$14
Name Subcategory: data!$B$2:$B$30
Name Savings: data!$B$22:$B$25
Name Account: data!$E$2:$E$10
Name RentAndPaybill: data!$B$2:$B$7
Name Bazar: data!$B$8:$B$11
Name Donation: data!$B$27:$B$28
Name ExtraExpenses: data!$B$17:$B$21
Name SavingsAcc: data!$G$2:$G$6
Name DATESTATUS: LAMBDA(startdate, enddate, IF(TODAY()<startdate, "Start in "&(startdate-TODAY()), IF(TODAY()<=enddate, "Expire in "&(enddate-TODAY()), "Expired")))

Sheet January 25
B2: TOTAL | C2: =sum(C4:C34) -> 46600 | D2: =sum(D4:D34) -> 43050 | E2: GROUP | F2: IN-HAND | G2: =C2-D2-G5 -> 1855 | I2: =49500-J3 -> 8500 | J2: Estimated | K2: Cost | L2: Remaining
B3: Date | C3: Withdraw | D3: Cost | F3: In-Acc | G3: =49500 - C2 -> 2900 | I3: BUDGET | J3: =sum(J4:J17) -> 41000 | K3: =sum(K4:K17) -> 42730 | L3: =sum(L4:L17) -> 1850
B4: 45651 | C4: 11000 | D4: 10500 | E4: =sum(D4:D10) -> 28265 | F4: Mob. Bank | I4: Prev. Due | J4: =6000+2000+2000 -> 10000 | K4: =6000+4000 -> 10000 | L4: =J4-K4 -> 0
B5: 45652 | D5: =20+30+220 -> 270 | F5: bKash | G5: =500+2000-635-1510-200-250+2000-210 -> 1695 | I5: Home | J5: 12000 | K5: 10000 | L5: =J5-K5 -> 2000
B6: 45653 | C6: 6500 | D6: 6000 | I6: H. Rent | J6: 7000 | K6: 7000 | L6: =J6-K6 -> 0
B7: 45654 | C7: 10000 | D7: =60+110+250+50+130+7000+180+20+20 -> 7820 | I7: ext. exp | J7: 5000 | K7: =4100+180+100+450+50+500 -> 5380 | L7: =J7-K7 -> -380
B8: 45655 | D8: =35 -> 35 | I8: Internet & MS | J8: 2000 | K8: =200+250+635 -> 1085 | L8: =J8-K8 -> 915
B9: 45656 | C9: 2000 | D9: =15+200+20+10+635+1510 -> 2390 | I9: SAV_2.5 | J9: 0 | L9: =J9-K9 -> 0
B10: 45657 | D10: =1000+20+30+200 -> 1250 | I10: SAV_5 | J10: 0 | L10: =J10-K10 -> 0
B11: 45658 | D11: =20+10+15+200 -> 245 | E11: =sum(D11:D20) -> 13410 | F11: LEND FROM | G11: =sum(G12:G20) -> 0 | I11: EXT(DN&Med) | J11: 1000 | K11: =130+220+200+20+935+75+20+20 -> 1620 | L11: =J11-K11 -> -620
B12: 45659 | D12: =10+15 -> 25 | F12: Mess | I12: Food_Meal | J12: 2000 | K12: =260+180+200+100+245+290+20+550+200+35+20+20+50+80+240+40 -> 2530 | L12: =J12-K12 -> -530
B13: 45660 | D13: =100+20+15+15+245 -> 395 | I13: Travel | J13: 1000 | K13: =300+20+60+10+20+30+10+20+10+30+50+20+20+20+20+20+20+10+20 -> 710 | L13: =J13-K13 -> 290
B14: 45661 | C14: 10000 | D14: =290+15+20+20+2200 -> 2545 | I14: Tea & Others | J14: 1000 | K14: =30+110+40+40+35+15+30+15+15+30+15+20+15+30+15+15+50+75+15+55+15+15+15+50+35+30 -> 825 | L14: =J14-K14 -> 175
B15: 45662 | D15: =20+15+4000+250 -> 4285 | I15: Lend Given | K15: =290+1510+1000-2000+200 -> 1000
B16: 45663 | D16: =30+935 -> 965 | I16: Donation | K16: =200+20+110+50 -> 380
B17: 45664 | D17: 0 | I17: FixedCost | K17: 2200
B18: 45665 | D18: =10+15 -> 25
B19: 45666 | D19: =(250+300)+15+30 -> 595
B20: 45667 | C20: 4100 | D20: =4100+180+(15*3+5) -> 4330
B21: 45668 | D21: =200+50+450+15*5+75 -> 850 | E21: =sum(D21:D34) -> 1375 | F21: LEND TO | G21: =sum(G22:G34) -> 2560
B22: 45669 | D22: =100+20 -> 120 | F22: sakib | G22: 50
B23: 45670 | D23: =20+15 -> 35 | F23: Monir | G23: =1510+1000 -> 2510
B24: 45671 | D24: =20+55 -> 75
B25: 45672 | D25: =20+15 -> 35
B26: 45673 | D26: =20+15+35 -> 70
B27: 45674 | D27: =0-2000+200+290-235 -> -1745
B28: 45675 | D28: =20+15+20 -> 55
B29: 45676 | D29: =50+20+20+50 -> 140
B30: 45677 | D30: =20+100+10 -> 130
B31: 45678 | D31: =50+20+20+10+60 -> 160
B32: 45679 | C32: 3000 | D32: =30+15+180+35+50+210 -> 520
B33: 45680 | D33: =20+15 -> 35
B34: 45681 | D34: =(220+35+50)+(20+30+20+20+500) -> 895

Sheet Feb 25
B3: Transaction | D3: DAY | E3: Date | F3: TotalCost | G3: =Sum(F5:F40)+sum(G5:G40) -> 51393 | I3: FINANCIAL STATUS | K3: =J5+J6+J7+J8-J9 -> 4848 | M3: BUDGET | N3: =sum(N5:N18) -> 50485 | O3: =sum(O5:O18) -> 51393 | P3: =sum(P5:P18) -> -908
B4: Amount | C4: From--To | F4: From Cash | G4: From bKash | I4: Type | J4: Current Status | K4: Start with | M4: Field | N4: Budget | O4: Cost | P4: Remaining
C5: None | D5: sunday | E5: 45683 | F5: =10+10 -> 20 | I5: S_A/C | J5: {=K5 - sum(IF((C5:C40="S_A/C-->bKash")+(C5:C40="S_A/C-->Cash")+(C5:C40="S_A/C-->SonaliBU"), B5:B40, 0))} -> 621 | K5: =680+49500-14-15-15-15 -> 50121 | M5: prevDue | N5: 685 | O5: 685 | P5: =N5-O5 -> 0
C6: None | D6: monday | E6: 45684 | F6: =15+20+50 -> 85 | I6: bKash | J6: {=K6 - sum(G5:G40) + sum(IF((C5:C40="S_A/C-->bKash")+(C5:C40="givenLend-->bKash")+(C5:C40="Cash-->bKash")+(C5:C40="takenLend-->bKash"), B5:B40, 0)) - sum(IF((C5:C40="bKash-->givenLend")+(C5:C40="bKash-->Cash")+(C5:C40="bKash-->takenLend"), B5:B40, 0))} -> 162 | K6: =3723-9+20-19+35+10 -> 3760 | M6: home | N6: 30000 | O6: =5900+4800+1500+1300+400+1200+750+7000 -> 22850 | P6: =N6-O6 -> 7150
C7: None | D7: tuesday | E7: 45685 | F7: =20+30+15 -> 65 | I7: Cash | J7: {=K7 - sum(F5:F40) + sum(IF((C5:C40="S_A/C-->Cash")+(C5:C40="givenLend-->Cash")+(C5:C40="bKash-->Cash")+(C5:C40="takenLend-->Cash"), B5:B40, 0)) - sum(IF((C5:C40="Cash-->takenLend")+(C5:C40="Cash-->givenLend")+(C5:C40="Cash-->bKash"), B5:B40, 0))} -> 1650 | K7: 1860 | M7: hRent | N7: 7000 | O7: 7000 | P7: =N7-O7 -> 0
B8: 500 | C8: S_A/C-->SonaliBU | D8: wednesday | E8: 45686 | F8: =20 -> 20 | I8: givenLend | J8: {=K8 + sum(IF((C5:C40="bKash-->givenLend")+(C5:C40="Cash-->givenLend"), B5:B40, 0)) - sum(IF((C5:C40="givenLend-->bKash")+(C5:C40="givenLend-->Cash"), B5:B40, 0))} -> 2415 | K8: 1000 | M8: extExp | N8: 4500 | O8: =250+250+225+140+1890+350+1490+5250 -> 9845 | P8: =N8-O8 -> -5345
C9: None | D9: thursday | E9: 45687 | F9: =20+(30+125)+250 -> 425 | G9: 1500 | I9: takenLend | J9: {=K9 + sum(IF((C5:C40="takenLend-->Cash")+(C5:C40="takenLend-->bKash"), B5:B40, 0)) - sum(IF((C5:C40="Cash-->takenLend")+(C5:C40="bKash-->takenLend"), B5:B40, 0))} -> 0 | K9: 0 | M9: internet | N9: 1500 | O9: =150+150+250+30+298+30 -> 908 | P9: =N9-O9 -> 592
C10: None | D10: friday | E10: 45688 | F10: =30+40+35 -> 105 | I10: SonaliBank | J10: {=K10 + sum(IF((C5:C40="S_A/C-->SonaliBU"), B5:B40, 0))} -> 300 | K10: -200 | M10: sav_2.5 | N10: 2500 | O10: 2500 | P10: =N10-O10 -> 0
B11: 2000 | C11: bKash-->givenLend | D11: saturday | E11: 45689 | F11: =(15+20)+250+(410+20+10+20)+65+685+110 -> 1605 | H11: 2 | I11: Nagad | M11: sav_5 | N11: 0 | P11: =N11-O11 -> 0
B12: 585 | C12: givenLend-->Cash | D12: sunday | E12: 45690 | F12: =(15+20) -> 35 | M12: dailyNec | N12: 1000 | O12: =65+260+100+150+70+35+170+105+85 -> 1040 | P12: =N12-O12 -> -40
B13: 12000 | C13: S_A/C-->Cash | D13: monday | E13: 45691 | F13: =20 -> 20 | G13: =50+100 -> 150 | M13: food | N13: 1000 | O13: =10+70+30+35+20+90+50+20+20+40+80+20+70+30+20+40+30 -> 675 | P13: =N13-O13 -> 325
B14: 2500 | C14: S_A/C-->bKash | D14: tuesday | E14: 45692 | F14: =30+225 -> 255 | G14: 2500 | I14: LEND GIVEN TO | K14: =sum(K16:K21) -> 2415 | M14: travel | N14: 500 | O14: =10+20+20+20+40+10+700+375+700 -> 1895 | P14: =N14-O14 -> -1395
B15: 1000 | C15: S_A/C-->bKash | D15: wednesday | E15: 45693 | F15: =7000+15+90 -> 7105 | I15: Date | J15: Given To | K15: Amount | M15: tea | N15: 500 | O15: =15+15+155+30+35+35+30+15+15+45+45+30+15+15+15+50+45+30+15+30+35+45+60+15+15+15+30 -> 895 | P15: =N15-O15 -> -395
B16: 500 | C16: bKash-->Cash | D16: thursday | E16: 45694 | F16: =15+(75+120+65)+(30+20)+190 -> 515 | I16: prev | J16: Monir | K16: =1000-585 -> 415 | M16: lendGiven | N16: 0 | P16: =N16-O16 -> 0
B17: 10000 | C17: S_A/C-->Cash | D17: friday | E17: 45695 | F17: =(15*3)+20+(150+90)+(5900+4800+1500+1300+400) -> 14205 | H17: 2 | I17: 45689 | J17: Ayon | K17: 1000 | M17: donation | N17: 300 | O17: =1500+110+300+260+10 -> 2180 | P17: =N17-O17 -> -1880
B18: 1000 | C18: givenLend-->bKash | D18: saturday | E18: 45696 | F18: =(15*3)+20+30+100 -> 195 | H18: 2 | I18: 45712 | J18: Razib Shekh vai | K18: 1000 | M18: mess | N18: 1000 | O18: =460+190+240+30+540-540 -> 920 | P18: =N18-O18 -> 80
C19: None | D19: sunday | E19: 45697 | F19: =30+10 -> 40
C20: None | D20: monday | E20: 45698 | F20: =15+40 -> 55
B21: 10000 | C21: S_A/C-->Cash | D21: tuesday | E21: 45699 | F21: =80+20+50+15+70 -> 235
C22: None | D22: wednesday | E22: 45700 | F22: =300+15 -> 315 | G22: =700 -> 700
C23: None | D23: thursday | E23: 45701 | F23: =750+(15+80+80+200)+(30+20)+1200 -> 2375 | I23: LEND TAKEN FROM | K23: =sum(K25:K30) -> 0
B24: 1000 | C24: S_A/C-->bKash | D24: friday | E24: 45702 | F24: =7000 -> 7000 | G24: 150 | H24: 0 | I24: Date | J24: Taken From | K24: Amount
B25: 1000 | C25: bKash-->Cash | D25: saturday | E25: 45703 | F25: =(50+650)+(20+20+20+10+10)+(15*3)+(10+5+20) -> 860 | G25: 250 | H25: 0
C26: None | D26: sunday | E26: 45704 | F26: =15+15+20 -> 50
C27: None | D27: monday | E27: 45705 | F27: =15 -> 15 | G27: 30
C28: None | D28: tuesday | E28: 45706 | F28: =30+70 -> 100
C29: None | D29: wednesday | E29: 45707 | F29: 0
B30: 2000 | C30: S_A/C-->Cash | D30: thursday | E30: 45708 | F30: =140+(20+15) -> 175
B31: 1000 | C31: Cash-->givenLend | D31: friday | E31: 45709 | F31: =(30+15)+(30)+(180+360)-(540) -> 75 | H31: 0 | I31: done
B32: 1500 | C32: S_A/C-->bKash | D32: saturday | E32: 45710 | F32: =20+(15*4)+(70+30+70)+(260) -> 510 | G32: =298+30 -> 328 | H32: 0
B33: 5000 | C33: S_A/C-->Cash | D33: sunday | E33: 45711 | F33: =15+40+(1890+350)+105 -> 2400 | G33: =1490 -> 1490
B34: 4000 | C34: S_A/C-->Cash | D34: monday | E34: 45712 | F34: =5250+15+30+85+10 -> 5390
C35: None | D35: tuesday | E35: 45713 | F35: =15 -> 15
C36: None | D36: wednesday | E36: 45714 | F36: =30 -> 30
C37: None
C38: None
C39: None
C40: None

Sheet March 25
B3: T r a n s a c t i o n | F3: DAY | G3: Date | H3: TotalCost | I3: =Sum(H5:H40)+sum(I5:I40) -> 49467 | K3: FINANCIAL STATUS | M3: =L5+L6+L7 -> 4388 | O3: BUDGET | P3: =sum(P5:P18) -> 30000 | Q3: =sum(Q5:Q18) -> 49235 | R3: =sum(R5:R18) -> -19235
B4: Date | C4: Amount | D4: From--To | H4: From Cash | I4: From bKash | K4: Type | L4: Current Status | M4: Start with | O4: Field | P4: Budget | Q4: Cost | R4: Remaining
B5: 45714 | C5: 12000 | D5: S_A/C-->bKash | K5: S_A/C | L5: {=M5 - sum(IF((D5:D40="S_A/C-->bKash")+(D5:D40="S_A/C-->Cash")+(D5:D40="S_A/C-->SonaliBU"), C5:C40, 0))} -> 46 | M5: =621+49500-(15*5) -> 50046 | O5: prevDue | P5: 0 | R5: =P5-Q5 -> 0
B6: 45716 | C6: 2500 | D6: S_A/C-->bKash | K6: bKash | L6: {=M6 - sum(I5:I40) + sum(IF((D5:D40="S_A/C-->bKash")+(D5:D40="SonaliBU-->bKash")+(D5:D40="givenLend-->bKash")+(D5:D40="Cash-->bKash")+(D5:D40="takenLend-->bKash"), C5:C40, 0)) - sum(IF((D5:D40="bKash-->givenLend")+(D5:D40="bKash-->Cash")+(D5:D40="bKash-->takenLend"), C5:C40, 0))} -> 4952 | M6: =162-18 -> 144 | O6: home | P6: 10000 | Q6: =10200+10100 -> 20300 | R6: =P6-Q6 -> -10300
B7: 45716 | C7: 2500 | D7: S_A/C-->bKash | K7: Cash | L7: {=M7 - sum(H5:H40) + sum(IF((D5:D40="S_A/C-->Cash")+(D5:D40="givenLend-->Cash")+(D5:D40="bKash-->Cash")+(D5:D40="takenLend-->Cash"), C5:C40, 0)) - sum(IF((D5:D40="Cash-->takenLend")+(D5:D40="Cash-->givenLend")+(D5:D40="Cash-->bKash"), C5:C40, 0))} -> -610 | M7: =1630+520 -> 2150 | O7: hRent | P7: 7000 | Q7: 7000 | R7: =P7-Q7 -> 0
B8: 45717 | C8: 20000 | D8: S_A/C-->SonaliBU | K8: givenLend | L8: {=M8 + sum(IF((D5:D40="bKash-->givenLend")+(D5:D40="Cash-->givenLend")+(D5:D40="SonaliBU-->givenLend"), C5:C40, 0)) - sum(IF((D5:D40="givenLend-->bKash")+(D5:D40="givenLend-->Cash")+(D5:D40="givenLend-->SonaliBU"), C5:C40, 0))} -> 1000 | M8: =2415+75 -> 2490 | O8: extExp | P8: 5000 | Q8: =2440+180+160+1480+2190+4147 -> 10597 | R8: =P8-Q8 -> -5597
B9: 45720 | C9: 10000 | D9: S_A/C-->Cash | F9: thursday | G9: 45715 | H9: =30 -> 30 | I9: =10200+208 -> 10408 | K9: takenLend | L9: {=M9 + sum(IF((D5:D40="takenLend-->Cash")+(D5:D40="takenLend-->bKash"), C5:C40, 0)) - sum(IF((D5:D40="Cash-->takenLend")+(D5:D40="bKash-->takenLend"), C5:C40, 0))} -> 0 | M9: -15 | O9: internet | P9: 1200 | Q9: =208+297+300+225 -> 1030 | R9: =P9-Q9 -> 170
B10: 45722 | C10: 1000 | D10: givenLend-->bKash | F10: friday | G10: 45716 | H10: =(15*3+5) + 80 + 180 + 75 -> 385 | I10: =2500+2440 -> 4940 | J10: 1 | K10: SonaliBU | L10: {=M10 + sum(IF((D5:D40="S_A/C-->SonaliBU")+(D5:D40="givenLend-->SonaliBU"), C5:C40, 0)) - sum(IF((D5:D40="SonaliBU-->givenLend")+(D5:D40="SonaliBU-->bKash"), C5:C40, 0))} -> 290 | M10: =300 -> 300 | O10: sav_2.5 | P10: 2500 | Q10: 2500 | R10: =P10-Q10 -> 0
B11: 45724 | C11: 10010 | D11: SonaliBU-->givenLend | F11: saturday | G11: 45717 | H11: =30+(15*3+5)+(500+275+25)+(50) -> 930 | J11: 3 | K11: EximBank | L11: =M11 -> 507 | M11: 507 | O11: sav_5 | P11: 0 | R11: =P11-Q11 -> 0
B12: 45729 | C12: 3000 | D12: S_A/C-->Cash | F12: sunday | G12: 45718 | H12: =200+15 -> 215 | I12: =297 -> 297 | J12: 1 | K12: Nagad | L12: =M12 | O12: dailyNec | P12: 800 | Q12: =75+280+70+70 -> 495 | R12: =P12-Q12 -> 305
B13: 45730 | C13: 10000 | D13: SonaliBU-->bKash | F13: monday | G13: 45719 | H13: =15 -> 15 | J13: 1 | O13: food | P13: 700 | Q13: =80+30+50+30+80+140+35 -> 445 | R13: =P13-Q13 -> 255
B14: 45732 | C14: 1030 | D14: takenLend-->bKash | F14: tuesday | G14: 45720 | H14: =(180+240)+(280)+15+30 -> 745 | J14: 1 | O14: travel | P14: 300 | Q14: =90+30+1600+30 -> 1750 | R14: =P14-Q14 -> -1450
B15: 45732 | C15: 400 | D15: givenLend-->bKash | F15: wednesday | G15: 45721 | H15: =15 -> 15 | J15: 1 | K15: LEND GIVEN TO | M15: =sum(M17:M22) -> 1000 | O15: tea | P15: 500 | Q15: =30+50+50+15+15+15+15+15+15+5+17+15+17+15+52+50+15+40+15+15+15 -> 491 | R15: =P15-Q15 -> 9
B16: 45732 | C16: 1000 | D16: bKash-->Cash | F16: thursday | G16: 45722 | H16: =(10+50+30) -> 90 | J16: 1 | K16: Date | L16: Given To | M16: Amount | O16: lendGiven | P16: 0 | R16: =P16-Q16 -> 0
B17: 45735 | C17: 10000 | D17: givenLend-->bKash | F17: friday | G17: 45723 | H17: =(110+20)+15 -> 145 | J17: 1 | O17: donation | P17: 500 | Q17: =100+100 -> 200 | R17: =P17-Q17 -> 300
B18: 45736 | C18: 5100 | D18: bKash-->givenLend | F18: saturday | G18: 45724 | H18: =7000+(750+260)+15 -> 8025 | J18: 1 | O18: mess | P18: 1500 | Q18: =(180+220)+800+200+130+240+750+260+22+20+570+155+250+350-50+175+155 -> 4427 | R18: =P18-Q18 -> -2927
B19: 45740 | C19: 5200 | D19: givenLend-->bKash | F19: sunday | G19: 45725 | H19: =220+160+(22+20) -> 422 | J19: 1 | K19: 45712 | L19: Razib Shekh vai | M19: 1000
B20: 45740 | C20: 1015 | D20: bKash-->takenLend | F20: monday | G20: 45726 | H20: =30 -> 30 | J20: 1
D21: None | F21: tuesday | G21: 45727 | H21: =70+5 -> 75 | J21: 1
D22: None | F22: wednesday | G22: 45728 | H22: =(200+280+40+50)+15+2 -> 587 | J22: 1
D23: None | F23: thursday | G23: 45729 | H23: =(500+580+400) +15 +80 -> 1575 | J23: 1
D24: None | F24: friday | G24: 45730 | H24: =15+2 -> 17 | I24: 10100 | J24: 1 | K24: LEND TAKEN FROM | M24: =sum(M26:M31) -> 0
D25: None | F25: saturday | G25: 45731 | H25: 15 | J25: 1 | K25: Date | L25: Taken From | M25: Amount
D26: None | F26: sunday | G26: 45732 | H26: =1600+(35+15+2) -> 1652 | I26: =2190 -> 2190 | J26: 1
D27: None | F27: monday | G27: 45733 | H27: =15+2 -> 17 | J27: 1
D28: None | F28: tuesday | G28: 45734 | H28: =15+10 -> 25 | J28: 1
D29: None | F29: wednesday | G29: 45735 | H29: =15+(195+30+125)+100+35 -> 500 | J29: 2
D30: None | F30: thursday | G30: 45736 | H30: =(15+25)+(30+180+40-50) -> 240 | J30: 3
D31: None | F31: friday | G31: 45737 | H31: =(60+80) -> 140 | J31: 2
D32: None | F32: saturday | G32: 45738 | H32: =30+15 -> 45 | I32: =300+4147 -> 4447 | J32: 2
D33: None | F33: sunday | G33: 45739 | H33: =100+30+25+(35+15) -> 205 | J33: 2
D34: None | F34: monday | G34: 45740 | H34: =15+70 -> 85 | I34: =225+100 -> 325 | J34: 2
D35: None | F35: tuesday | G35: 45741 | H35: =15+(35+140) -> 190 | J35: 2
D36: None | F36: wednesday | G36: 45742 | H36: =60+15+70+200 -> 345 | J36: 1
D37: None
D38: None
D39: None
D40: None

Sheet Apr 25
B2: T r a n s a c t i o n | G2: DAY | H2: Date | I2: TotalCost | J2: =Sum(I4:I39)+sum(J4:J39) -> 52938 | L2: FINANCIAL STATUS | N2: =M4+M5+M6-M8 -> 4894 | P2: BUDGET | Q2: =sum(Q4:Q17) -> 40000 | R2: =sum(R4:R17) -> 52938 | S2: =sum(S4:S17) -> -12938 | U2: Total | W2: Date | X2: mess | Z2: tea | AB2: food | AD2: dailyNec | AF2: internet | AH2: extExp | AJ2: travel | AL2: home | AN2: hRent | AP2: sav_2.5 | AR2: donation | AT2: prevDue
B3: Date | C3: Cost | D3: Amount | E3: From--To | I3: Cash | J3: bKash | L3: Type | M3: Current Status | N3: Start with | P3: Field | Q3: Budget | R3: Cost | S3: Remaining | U3: Cash | V3: bKash | X3: Cash | Y3: bKash | Z3: Cash | AA3: bKash | AB3: Cash | AC3: bKash | AD3: Cash | AE3: bKash | AF3: Cash | AG3: bKash | AH3: Cash | AI3: bKash | AJ3: Cash | AK3: bKash | AL3: Cash | AM3: bKash | AN3: Cash | AO3: bKash | AP3: Cash | AQ3: bKash | AR3: Cash | AS3: bKash | AT3: Cash | AU3: bKash
B4: 45740 | D4: 49500 | E4: add-->S_A/C | G4: wednesday | H4: 45742 | I4: =X4+Z4+AB4+AD4+AF4+AH4+AJ4+AL4+AN4+AP4+AR4+AT4 -> 1500 | J4: =Y4+AA4+AC4+AE4+AG4+AI4+AK4+AM4+AO4+AQ4+AS4+AU4 -> 2500 | L4: S_A/C | M4: {=N4 - sum(IF((E4:E39="S_A/C-->bKash")+(E4:E39="S_A/C-->Cash")+(E4:E39="S_A/C-->SonaliBU"), D4:D39, 0)) + sum(IF((E4:E39="add-->S_A/C"), D4:D39, 0)) - sum(IF((E4:E39="S_A/C-->Cash"), C4:C39, 0))} -> 822 | N4: ='March 25'!L5 -> 46 | P4: prevDue | Q4: 0 | R4: =sum(AT4:AT39)+sum(AU4:AU39) -> 0 | S4: =Q4-R4 -> 0 | U4: =X4+Z4+AB4+AD4+AF4+AH4+AJ4+AL4+AN4+AP4+AR4+AT4 -> 1500 | V4: =Y4+AA4+AC4+AE4+AG4+AI4+AK4+AM4+AO4+AQ4+AS4+AU4 -> 2500 | W4: =IF(H4<>"", TEXT(H4, "DD/MM/YY"), "") -> 26/03/25 | AN4: 1500 | AQ4: 2500
B5: 45740 | C5: 15 | D5: 10000 | E5: S_A/C-->Cash | G5: thursday | H5: 45743 | I5: =X5+Z5+AB5+AD5+AF5+AH5+AJ5+AL5+AN5+AP5+AR5+AT5 -> 1200 | J5: =Y5+AA5+AC5+AE5+AG5+AI5+AK5+AM5+AO5+AQ5+AS5+AU5 -> 0 | L5: bKash | M5: {=N5 - sum(J4:J39) + sum(IF((E4:E39="S_A/C-->bKash")+(E4:E39="givenLend-->bKash")+(E4:E39="Cash-->bKash")+(E4:E39="takenLend-->bKash")+(E4:E39="add-->bKash"), D4:D39, 0)) - sum(IF((E4:E39="bKash-->givenLend")+(E4:E39="bKash-->Cash")+(E4:E39="bKash-->takenLend"), D4:D39, 0))} -> 314 | N5: ='March 25'!L6 -> 4952 | P5: home | Q5: 10000 | R5: =sum(AL4:AL39)+sum(AM4:AM39) -> 17190 | S5: =Q5-R5 -> -7190 | U5: =X5+Z5+AB5+AD5+AF5+AH5+AJ5+AL5+AN5+AP5+AR5+AT5 -> 1200 | V5: =Y5+AA5+AC5+AE5+AG5+AI5+AK5+AM5+AO5+AQ5+AS5+AU5 -> 0 | W5: =IF(H5<>"", TEXT(H5, "DD/MM/YY"), "") -> 27/03/25 | Z5: =15+15+15 -> 45 | AB5: =300+45 -> 345 | AD5: 10 | AJ5: =200+120+120 -> 440 | AL5: =300 -> 300 | AR5: =20+40 -> 60
B6: 45741 | D6: 129 | E6: add-->bKash | G6: friday | H6: 45744 | I6: =X6+Z6+AB6+AD6+AF6+AH6+AJ6+AL6+AN6+AP6+AR6+AT6 -> 9145 | J6: =Y6+AA6+AC6+AE6+AG6+AI6+AK6+AM6+AO6+AQ6+AS6+AU6 -> 200 | L6: Cash | M6: {=N6 - sum(I4:I39) + sum(IF((E4:E39="S_A/C-->Cash")+(E4:E39="givenLend-->Cash")+(E4:E39="bKash-->Cash")+(E4:E39="takenLend-->Cash")+(E4:E39="add-->Cash")+(E4:E39="Nagad-->Cash"), D4:D39, 0)) - sum(IF((E4:E39="Cash-->takenLend")+(E4:E39="Cash-->givenLend")+(E4:E39="Cash-->bKash")+(E4:E39="Cash-->SonaliBU"), D4:D39, 0))} -> 3758 | N6: ='March 25'!L7 -> -610 | P6: hRent | Q6: =7000+1500 -> 8500 | R6: =sum(AN4:AN39)+sum(AO4:AO39) -> 8500 | S6: =Q6-R6 -> 0 | U6: =X6+Z6+AB6+AD6+AF6+AH6+AJ6+AL6+AN6+AP6+AR6+AT6 -> 9145 | V6: =Y6+AA6+AC6+AE6+AG6+AI6+AK6+AM6+AO6+AQ6+AS6+AU6 -> 200 | W6: =IF(H6<>"", TEXT(H6, "DD/MM/YY"), "") -> 28/03/25 | Z6: =160+35 -> 195 | AG6: 200 | AH6: 20 | AL6: =140+400+7000 -> 7540 | AR6: =90+100+200+1000 -> 1390
B7: 45741 | D7: 2500 | E7: S_A/C-->bKash | G7: saturday | H7: 45745 | I7: =X7+Z7+AB7+AD7+AF7+AH7+AJ7+AL7+AN7+AP7+AR7+AT7 -> 1000 | J7: =Y7+AA7+AC7+AE7+AG7+AI7+AK7+AM7+AO7+AQ7+AS7+AU7 -> 1400 | L7: givenLend | M7: {=N7 + sum(IF((E4:E39="bKash-->givenLend")+(E4:E39="Cash-->givenLend")+(E4:E39="SonaliBU-->givenLend"), D4:D39, 0)) - sum(IF((E4:E39="givenLend-->bKash")+(E4:E39="givenLend-->Cash")+(E4:E39="givenLend-->SonaliBU")+(E4:E39="givenLend-->Nagad"), D4:D39, 0))} -> 2500 | N7: ='March 25'!L8 -> 1000 | P7: extExp | Q7: 10000 | R7: =sum(AH4:AH39)+sum(AI4:AI39) -> 4984 | S7: =Q7-R7 -> 5016 | U7: =X7+Z7+AB7+AD7+AF7+AH7+AJ7+AL7+AN7+AP7+AR7+AT7 -> 1000 | V7: =Y7+AA7+AC7+AE7+AG7+AI7+AK7+AM7+AO7+AQ7+AS7+AU7 -> 1400 | W7: =IF(H7<>"", TEXT(H7, "DD/MM/YY"), "") -> 29/03/25 | AK7: 1400 | AL7: 1000
B8: 45742 | D8: 1000 | E8: add-->Cash | G8: sunday | H8: 45746 | I8: =X8+Z8+AB8+AD8+AF8+AH8+AJ8+AL8+AN8+AP8+AR8+AT8 -> 0 | J8: =Y8+AA8+AC8+AE8+AG8+AI8+AK8+AM8+AO8+AQ8+AS8+AU8 -> 208 | L8: takenLend | M8: {=N8 + sum(IF((E4:E39="takenLend-->Cash")+(E4:E39="takenLend-->bKash"), D4:D39, 0)) - sum(IF((E4:E39="Cash-->takenLend")+(E4:E39="bKash-->takenLend"), D4:D39, 0))} -> 0 | N8: ='March 25'!L9 -> 0 | P8: internet | Q8: 1200 | R8: =sum(AF4:AF39)+sum(AG4:AG39) -> 1597 | S8: =Q8-R8 -> -397 | U8: =X8+Z8+AB8+AD8+AF8+AH8+AJ8+AL8+AN8+AP8+AR8+AT8 -> 0 | V8: =Y8+AA8+AC8+AE8+AG8+AI8+AK8+AM8+AO8+AQ8+AS8+AU8 -> 208 | W8: =IF(H8<>"", TEXT(H8, "DD/MM/YY"), "") -> 30/03/25 | AG8: 208
B9: 45742 | D9: 1120 | E9: add-->bKash | G9: monday | H9: 45747 | I9: =X9+Z9+AB9+AD9+AF9+AH9+AJ9+AL9+AN9+AP9+AR9+AT9 -> 0 | J9: =Y9+AA9+AC9+AE9+AG9+AI9+AK9+AM9+AO9+AQ9+AS9+AU9 -> 100 | L9: SonaliBU | M9: {=N9 + sum(IF((E4:E39="S_A/C-->SonaliBU")+(E4:E39="givenLend-->SonaliBU")+(E4:E39="Cash-->SonaliBU"), D4:D39, 0)) - sum(IF((E4:E39="SonaliBU-->givenLend"), D4:D39, 0))} -> 5290 | N9: ='March 25'!L10 -> 290 | P9: sav_2.5 | Q9: 2500 | R9: =sum(AP4:AP39)+sum(AQ4:AQ39) -> 2500 | S9: =Q9-R9 -> 0 | U9: =X9+Z9+AB9+AD9+AF9+AH9+AJ9+AL9+AN9+AP9+AR9+AT9 -> 0 | V9: =Y9+AA9+AC9+AE9+AG9+AI9+AK9+AM9+AO9+AQ9+AS9+AU9 -> 100 | W9: =IF(H9<>"", TEXT(H9, "DD/MM/YY"), "") -> 31/03/25 | AI9: 100
B10: 45742 | D10: 5000 | E10: Cash-->SonaliBU | G10: tuesday | H10: 45748 | I10: =X10+Z10+AB10+AD10+AF10+AH10+AJ10+AL10+AN10+AP10+AR10+AT10 -> 8385 | J10: =Y10+AA10+AC10+AE10+AG10+AI10+AK10+AM10+AO10+AQ10+AS10+AU10 -> 0 | L10: EximBank | M10: =N10 -> 507 | N10: ='March 25'!L11 -> 507 | P10: sav_5 | Q10: 0 | S10: =Q10-R10 -> 0 | U10: =X10+Z10+AB10+AD10+AF10+AH10+AJ10+AL10+AN10+AP10+AR10+AT10 -> 8385 | V10: =Y10+AA10+AC10+AE10+AG10+AI10+AK10+AM10+AO10+AQ10+AS10+AU10 -> 0 | W10: =IF(H10<>"", TEXT(H10, "DD/MM/YY"), "") -> 01/04/25 | Z10: 35 | AL10: =5000+3350 -> 8350
B11: 28-03-25 | C11: 15 | D11: 10000 | E11: S_A/C-->Cash | G11: wednesday | H11: 45749 | I11: =X11+Z11+AB11+AD11+AF11+AH11+AJ11+AL11+AN11+AP11+AR11+AT11 -> 0 | J11: =Y11+AA11+AC11+AE11+AG11+AI11+AK11+AM11+AO11+AQ11+AS11+AU11 -> 0 | L11: Nagad | M11: {=N11 + sum(IF((E4:E39="givenLend-->Nagad"), D4:D39, 0)) - sum(IF((E4:E39="Nagad-->Cash"), D4:D39, 0)) - - sum(IF((E4:E39="Nagad-->Cash"), C4:C39, 0))} -> 800 | N11: ='March 25'!L12 | P11: dailyNec | Q11: 1000 | R11: =sum(AD4:AD39)+sum(AE4:AE39) -> 355 | S11: =Q11-R11 -> 645 | U11: =X11+Z11+AB11+AD11+AF11+AH11+AJ11+AL11+AN11+AP11+AR11+AT11 -> 0 | V11: =Y11+AA11+AC11+AE11+AG11+AI11+AK11+AM11+AO11+AQ11+AS11+AU11 -> 0 | W11: =IF(H11<>"", TEXT(H11, "DD/MM/YY"), "") -> 02/04/25
C12: 15 | D12: 3000 | E12: S_A/C-->Cash | G12: thursday | H12: 45750 | I12: =X12+Z12+AB12+AD12+AF12+AH12+AJ12+AL12+AN12+AP12+AR12+AT12 -> 0 | J12: =Y12+AA12+AC12+AE12+AG12+AI12+AK12+AM12+AO12+AQ12+AS12+AU12 -> 0 | N12: ='March 25'!L13 | P12: food | Q12: 800 | R12: =sum(AB4:AB39)+sum(AC4:AC39) -> 2020 | S12: =Q12-R12 -> -1220 | U12: =X12+Z12+AB12+AD12+AF12+AH12+AJ12+AL12+AN12+AP12+AR12+AT12 -> 0 | V12: =Y12+AA12+AC12+AE12+AG12+AI12+AK12+AM12+AO12+AQ12+AS12+AU12 -> 0 | W12: =IF(H12<>"", TEXT(H12, "DD/MM/YY"), "") -> 03/04/25
C13: 15 | D13: 3000 | E13: S_A/C-->Cash | G13: friday | H13: 45751 | I13: =X13+Z13+AB13+AD13+AF13+AH13+AJ13+AL13+AN13+AP13+AR13+AT13 -> 0 | J13: =Y13+AA13+AC13+AE13+AG13+AI13+AK13+AM13+AO13+AQ13+AS13+AU13 -> 0 | P13: travel | Q13: 2000 | R13: =sum(AJ4:AJ39)+sum(AK4:AK39) -> 10420 | S13: =Q13-R13 -> -8420 | U13: =X13+Z13+AB13+AD13+AF13+AH13+AJ13+AL13+AN13+AP13+AR13+AT13 -> 0 | V13: =Y13+AA13+AC13+AE13+AG13+AI13+AK13+AM13+AO13+AQ13+AS13+AU13 -> 0 | W13: =IF(H13<>"", TEXT(H13, "DD/MM/YY"), "") -> 04/04/25
C14: 15 | D14: 10000 | E14: S_A/C-->Cash | G14: saturday | H14: 45752 | I14: =X14+Z14+AB14+AD14+AF14+AH14+AJ14+AL14+AN14+AP14+AR14+AT14 -> 0 | J14: =Y14+AA14+AC14+AE14+AG14+AI14+AK14+AM14+AO14+AQ14+AS14+AU14 -> 1030 | L14: LEND GIVEN TO | N14: =sum(N16:N21) -> 2500 | P14: tea | Q14: 1000 | R14: =sum(Z4:Z39)+sum(AA4:AA39) -> 2252 | S14: =Q14-R14 -> -1252 | U14: =X14+Z14+AB14+AD14+AF14+AH14+AJ14+AL14+AN14+AP14+AR14+AT14 -> 0 | V14: =Y14+AA14+AC14+AE14+AG14+AI14+AK14+AM14+AO14+AQ14+AS14+AU14 -> 1030 | W14: =IF(H14<>"", TEXT(H14, "DD/MM/YY"), "") -> 05/04/25 | AI14: =460+560+5+5 -> 1030
C15: 0 | D15: 2500 | E15: S_A/C-->Cash | G15: sunday | H15: 45753 | I15: =X15+Z15+AB15+AD15+AF15+AH15+AJ15+AL15+AN15+AP15+AR15+AT15 -> 115 | J15: =Y15+AA15+AC15+AE15+AG15+AI15+AK15+AM15+AO15+AQ15+AS15+AU15 -> 0 | L15: Date | M15: Given To | N15: Amount | P15: lendGiven | Q15: 0 | S15: =Q15-R15 -> 0 | U15: =X15+Z15+AB15+AD15+AF15+AH15+AJ15+AL15+AN15+AP15+AR15+AT15 -> 115 | V15: =Y15+AA15+AC15+AE15+AG15+AI15+AK15+AM15+AO15+AQ15+AS15+AU15 -> 0 | W15: =IF(H15<>"", TEXT(H15, "DD/MM/YY"), "") -> 06/04/25 | Z15: 5 | AD15: 110
B16: 45722 | C16: 0 | D16: 1000 | E16: givenLend-->Nagad | G16: monday | H16: 45754 | I16: =X16+Z16+AB16+AD16+AF16+AH16+AJ16+AL16+AN16+AP16+AR16+AT16 -> 150 | J16: =Y16+AA16+AC16+AE16+AG16+AI16+AK16+AM16+AO16+AQ16+AS16+AU16 -> 0 | L16: 45774 | M16: Rajib Vai | N16: =1500+1000 -> 2500 | P16: donation | Q16: 1500 | R16: =sum(AR4:AR39)+sum(AS4:AS39) -> 1460 | S16: =Q16-R16 -> 40 | U16: =X16+Z16+AB16+AD16+AF16+AH16+AJ16+AL16+AN16+AP16+AR16+AT16 -> 150 | V16: =Y16+AA16+AC16+AE16+AG16+AI16+AK16+AM16+AO16+AQ16+AS16+AU16 -> 0 | W16: =IF(H16<>"", TEXT(H16, "DD/MM/YY"), "") -> 07/04/25 | X16: 135 | Z16: 15
B17: 45722 | C17: 0 | D17: 100 | E17: add-->bKash | G17: tuesday | H17: 45755 | I17: =X17+Z17+AB17+AD17+AF17+AH17+AJ17+AL17+AN17+AP17+AR17+AT17 -> 7015 | J17: =Y17+AA17+AC17+AE17+AG17+AI17+AK17+AM17+AO17+AQ17+AS17+AU17 -> 1855 | P17: mess | Q17: 1500 | R17: =sum(X4:X39)+sum(Y4:Y39) -> 1660 | S17: =Q17-R17 -> -160 | U17: =X17+Z17+AB17+AD17+AF17+AH17+AJ17+AL17+AN17+AP17+AR17+AT17 -> 7015 | V17: =Y17+AA17+AC17+AE17+AG17+AI17+AK17+AM17+AO17+AQ17+AS17+AU17 -> 1855 | W17: =IF(H17<>"", TEXT(H17, "DD/MM/YY"), "") -> 08/04/25 | Z17: 15 | AI17: =1850+5 -> 1855 | AN17: 7000
D18: 9000 | E18: add-->S_A/C | G18: wednesday | H18: 45756 | I18: =X18+Z18+AB18+AD18+AF18+AH18+AJ18+AL18+AN18+AP18+AR18+AT18 -> 85 | J18: =Y18+AA18+AC18+AE18+AG18+AI18+AK18+AM18+AO18+AQ18+AS18+AU18 -> 0 | U18: =X18+Z18+AB18+AD18+AF18+AH18+AJ18+AL18+AN18+AP18+AR18+AT18 -> 85 | V18: =Y18+AA18+AC18+AE18+AG18+AI18+AK18+AM18+AO18+AQ18+AS18+AU18 -> 0 | W18: =IF(H18<>"", TEXT(H18, "DD/MM/YY"), "") -> 09/04/25 | X18: 70 | Z18: 15
C19: 15 | D19: 5000 | E19: S_A/C-->Cash | G19: thursday | H19: 45757 | I19: =X19+Z19+AB19+AD19+AF19+AH19+AJ19+AL19+AN19+AP19+AR19+AT19 -> 75 | J19: =Y19+AA19+AC19+AE19+AG19+AI19+AK19+AM19+AO19+AQ19+AS19+AU19 -> 0 | U19: =X19+Z19+AB19+AD19+AF19+AH19+AJ19+AL19+AN19+AP19+AR19+AT19 -> 75 | V19: =Y19+AA19+AC19+AE19+AG19+AI19+AK19+AM19+AO19+AQ19+AS19+AU19 -> 0 | W19: =IF(H19<>"", TEXT(H19, "DD/MM/YY"), "") -> 10/04/25 | Z19: =30+45 -> 75
C20: 15 | D20: 5000 | E20: S_A/C-->Cash | G20: friday | H20: 45758 | I20: =X20+Z20+AB20+AD20+AF20+AH20+AJ20+AL20+AN20+AP20+AR20+AT20 -> 440 | J20: =Y20+AA20+AC20+AE20+AG20+AI20+AK20+AM20+AO20+AQ20+AS20+AU20 -> 0 | U20: =X20+Z20+AB20+AD20+AF20+AH20+AJ20+AL20+AN20+AP20+AR20+AT20 -> 440 | V20: =Y20+AA20+AC20+AE20+AG20+AI20+AK20+AM20+AO20+AQ20+AS20+AU20 -> 0 | W20: =IF(H20<>"", TEXT(H20, "DD/MM/YY"), "") -> 11/04/25 | Z20: =15+30+15 -> 60 | AB20: 20 | AH20: 350 | AR20: 10
D21: 1000 | E21: S_A/C-->bKash | G21: saturday | H21: 45759 | I21: =X21+Z21+AB21+AD21+AF21+AH21+AJ21+AL21+AN21+AP21+AR21+AT21 -> 130 | J21: =Y21+AA21+AC21+AE21+AG21+AI21+AK21+AM21+AO21+AQ21+AS21+AU21 -> 1205 | U21: =X21+Z21+AB21+AD21+AF21+AH21+AJ21+AL21+AN21+AP21+AR21+AT21 -> 130 | V21: =Y21+AA21+AC21+AE21+AG21+AI21+AK21+AM21+AO21+AQ21+AS21+AU21 -> 1205 | W21: =IF(H21<>"", TEXT(H21, "DD/MM/YY"), "") -> 12/04/25 | Z21: =15*4 -> 60 | AB21: 20 | AD21: 50 | AK21: 1205
D22: 200 | E22: Nagad-->Cash | G22: sunday | H22: 45760 | I22: =X22+Z22+AB22+AD22+AF22+AH22+AJ22+AL22+AN22+AP22+AR22+AT22 -> 45 | J22: =Y22+AA22+AC22+AE22+AG22+AI22+AK22+AM22+AO22+AQ22+AS22+AU22 -> 0 | U22: =X22+Z22+AB22+AD22+AF22+AH22+AJ22+AL22+AN22+AP22+AR22+AT22 -> 45 | V22: =Y22+AA22+AC22+AE22+AG22+AI22+AK22+AM22+AO22+AQ22+AS22+AU22 -> 0 | W22: =IF(H22<>"", TEXT(H22, "DD/MM/YY"), "") -> 13/04/25 | Z22: 15 | AB22: 30
D23: 200 | E23: Cash-->bKash | G23: monday | H23: 45761 | I23: =X23+Z23+AB23+AD23+AF23+AH23+AJ23+AL23+AN23+AP23+AR23+AT23 -> 265 | J23: =Y23+AA23+AC23+AE23+AG23+AI23+AK23+AM23+AO23+AQ23+AS23+AU23 -> 0 | L23: LEND TAKEN FROM | N23: =sum(N25:N30) -> 0 | U23: =X23+Z23+AB23+AD23+AF23+AH23+AJ23+AL23+AN23+AP23+AR23+AT23 -> 265 | V23: =Y23+AA23+AC23+AE23+AG23+AI23+AK23+AM23+AO23+AQ23+AS23+AU23 -> 0 | W23: =IF(H23<>"", TEXT(H23, "DD/MM/YY"), "") -> 14/04/25 | Z23: =15+20+5+15 -> 55 | AB23: 20 | AH23: 190
D24: 1720 | E24: S_A/C-->Cash | G24: tuesday | H24: 45762 | I24: =X24+Z24+AB24+AD24+AF24+AH24+AJ24+AL24+AN24+AP24+AR24+AT24 -> 170 | J24: =Y24+AA24+AC24+AE24+AG24+AI24+AK24+AM24+AO24+AQ24+AS24+AU24 -> 0 | L24: Date | M24: Taken From | N24: Amount | U24: =X24+Z24+AB24+AD24+AF24+AH24+AJ24+AL24+AN24+AP24+AR24+AT24 -> 170 | V24: =Y24+AA24+AC24+AE24+AG24+AI24+AK24+AM24+AO24+AQ24+AS24+AU24 -> 0 | W24: =IF(H24<>"", TEXT(H24, "DD/MM/YY"), "") -> 15/04/25 | X24: 130 | Z24: 40
D25: 1399 | E25: S_A/C-->Cash | G25: wednesday | H25: 45763 | I25: =X25+Z25+AB25+AD25+AF25+AH25+AJ25+AL25+AN25+AP25+AR25+AT25 -> 0 | J25: =Y25+AA25+AC25+AE25+AG25+AI25+AK25+AM25+AO25+AQ25+AS25+AU25 -> 100 | U25: =X25+Z25+AB25+AD25+AF25+AH25+AJ25+AL25+AN25+AP25+AR25+AT25 -> 0 | V25: =Y25+AA25+AC25+AE25+AG25+AI25+AK25+AM25+AO25+AQ25+AS25+AU25 -> 100 | W25: =IF(H25<>"", TEXT(H25, "DD/MM/YY"), "") -> 16/04/25 | AG25: 100
B26: 45742 | D26: 1500 | E26: S_A/C-->bKash | G26: thursday | H26: 45764 | I26: =X26+Z26+AB26+AD26+AF26+AH26+AJ26+AL26+AN26+AP26+AR26+AT26 -> 2540 | J26: =Y26+AA26+AC26+AE26+AG26+AI26+AK26+AM26+AO26+AQ26+AS26+AU26 -> 0 | U26: =X26+Z26+AB26+AD26+AF26+AH26+AJ26+AL26+AN26+AP26+AR26+AT26 -> 2540 | V26: =Y26+AA26+AC26+AE26+AG26+AI26+AK26+AM26+AO26+AQ26+AS26+AU26 -> 0 | W26: =IF(H26<>"", TEXT(H26, "DD/MM/YY"), "") -> 17/04/25 | Z26: =15+290 -> 305 | AB26: =210+70+60 -> 340 | AD26: =125+50 -> 175 | AJ26: 1720
B27: 45742 | D27: 1500 | E27: bKash-->givenLend | G27: friday | H27: 45765 | I27: =X27+Z27+AB27+AD27+AF27+AH27+AJ27+AL27+AN27+AP27+AR27+AT27 -> 960 | J27: =Y27+AA27+AC27+AE27+AG27+AI27+AK27+AM27+AO27+AQ27+AS27+AU27 -> 0 | U27: =X27+Z27+AB27+AD27+AF27+AH27+AJ27+AL27+AN27+AP27+AR27+AT27 -> 960 | V27: =Y27+AA27+AC27+AE27+AG27+AI27+AK27+AM27+AO27+AQ27+AS27+AU27 -> 0 | W27: =IF(H27<>"", TEXT(H27, "DD/MM/YY"), "") -> 18/04/25 | Z27: =20+10 -> 30 | AB27: =220+70+40+500 -> 830 | AJ27: =20+30+10+40 -> 100
B28: 45743 | D28: 1000 | E28: S_A/C-->bKash | G28: saturday | H28: 45766 | I28: =X28+Z28+AB28+AD28+AF28+AH28+AJ28+AL28+AN28+AP28+AR28+AT28 -> 1090 | J28: =Y28+AA28+AC28+AE28+AG28+AI28+AK28+AM28+AO28+AQ28+AS28+AU28 -> 0 | U28: =X28+Z28+AB28+AD28+AF28+AH28+AJ28+AL28+AN28+AP28+AR28+AT28 -> 1090 | V28: =Y28+AA28+AC28+AE28+AG28+AI28+AK28+AM28+AO28+AQ28+AS28+AU28 -> 0 | W28: =IF(H28<>"", TEXT(H28, "DD/MM/YY"), "") -> 19/04/25 | Z28: =300+10 -> 310 | AB28: =25+50+230+20 -> 325 | AH28: 20 | AJ28: =20+20+170+65+20+100+40 -> 435
B29: 45743 | D29: 1000 | E29: bKash-->givenLend | G29: sunday | H29: 45767 | I29: =X29+Z29+AB29+AD29+AF29+AH29+AJ29+AL29+AN29+AP29+AR29+AT29 -> 5960 | J29: =Y29+AA29+AC29+AE29+AG29+AI29+AK29+AM29+AO29+AQ29+AS29+AU29 -> 0 | U29: =X29+Z29+AB29+AD29+AF29+AH29+AJ29+AL29+AN29+AP29+AR29+AT29 -> 5960 | V29: =Y29+AA29+AC29+AE29+AG29+AI29+AK29+AM29+AO29+AQ29+AS29+AU29 -> 0 | W29: =IF(H29<>"", TEXT(H29, "DD/MM/YY"), "") -> 20/04/25 | Z29: =195+300+25+90+45+35+90 -> 780 | AB29: =50 -> 50 | AD29: =10 -> 10 | AJ29: =1970+430+1350+250+60+60+1000 -> 5120
E30: None | G30: monday | H30: 45768 | I30: =X30+Z30+AB30+AD30+AF30+AH30+AJ30+AL30+AN30+AP30+AR30+AT30 -> 0 | J30: =Y30+AA30+AC30+AE30+AG30+AI30+AK30+AM30+AO30+AQ30+AS30+AU30 -> 0 | U30: =X30+Z30+AB30+AD30+AF30+AH30+AJ30+AL30+AN30+AP30+AR30+AT30 -> 0 | V30: =Y30+AA30+AC30+AE30+AG30+AI30+AK30+AM30+AO30+AQ30+AS30+AU30 -> 0 | W30: =IF(H30<>"", TEXT(H30, "DD/MM/YY"), "") -> 21/04/25
E31: None | G31: tuesday | H31: 45769 | I31: =X31+Z31+AB31+AD31+AF31+AH31+AJ31+AL31+AN31+AP31+AR31+AT31 -> 0 | J31: =Y31+AA31+AC31+AE31+AG31+AI31+AK31+AM31+AO31+AQ31+AS31+AU31 -> 0 | U31: =X31+Z31+AB31+AD31+AF31+AH31+AJ31+AL31+AN31+AP31+AR31+AT31 -> 0 | V31: =Y31+AA31+AC31+AE31+AG31+AI31+AK31+AM31+AO31+AQ31+AS31+AU31 -> 0 | W31: =IF(H31<>"", TEXT(H31, "DD/MM/YY"), "") -> 22/04/25
E32: None | G32: wednesday | H32: 45770 | I32: =X32+Z32+AB32+AD32+AF32+AH32+AJ32+AL32+AN32+AP32+AR32+AT32 -> 1345 | J32: =Y32+AA32+AC32+AE32+AG32+AI32+AK32+AM32+AO32+AQ32+AS32+AU32 -> 150 | U32: =X32+Z32+AB32+AD32+AF32+AH32+AJ32+AL32+AN32+AP32+AR32+AT32 -> 1345 | V32: =Y32+AA32+AC32+AE32+AG32+AI32+AK32+AM32+AO32+AQ32+AS32+AU32 -> 150 | W32: =IF(H32<>"", TEXT(H32, "DD/MM/YY"), "") -> 23/04/25 | X32: =1325 -> 1325 | AG32: 150 | AH32: 20
E33: None | G33: thursday | H33: 45771 | I33: =X33+Z33+AB33+AD33+AF33+AH33+AJ33+AL33+AN33+AP33+AR33+AT33 -> 30 | J33: =Y33+AA33+AC33+AE33+AG33+AI33+AK33+AM33+AO33+AQ33+AS33+AU33 -> 200 | U33: =X33+Z33+AB33+AD33+AF33+AH33+AJ33+AL33+AN33+AP33+AR33+AT33 -> 30 | V33: =Y33+AA33+AC33+AE33+AG33+AI33+AK33+AM33+AO33+AQ33+AS33+AU33 -> 200 | W33: =IF(H33<>"", TEXT(H33, "DD/MM/YY"), "") -> 24/04/25 | Z33: 30 | AG33: 200
E34: None | G34: friday | H34: 45772 | I34: =X34+Z34+AB34+AD34+AF34+AH34+AJ34+AL34+AN34+AP34+AR34+AT34 -> 57 | J34: =Y34+AA34+AC34+AE34+AG34+AI34+AK34+AM34+AO34+AQ34+AS34+AU34 -> 689 | U34: =X34+Z34+AB34+AD34+AF34+AH34+AJ34+AL34+AN34+AP34+AR34+AT34 -> 57 | V34: =Y34+AA34+AC34+AE34+AG34+AI34+AK34+AM34+AO34+AQ34+AS34+AU34 -> 689 | W34: =IF(H34<>"", TEXT(H34, "DD/MM/YY"), "") -> 25/04/25 | Z34: =22+15 -> 37 | AB34: 20 | AG34: 689
E35: None | G35: saturday | H35: 45773 | I35: =X35+Z35+AB35+AD35+AF35+AH35+AJ35+AL35+AN35+AP35+AR35+AT35 -> 1494 | J35: =Y35+AA35+AC35+AE35+AG35+AI35+AK35+AM35+AO35+AQ35+AS35+AU35 -> 50 | U35: =X35+Z35+AB35+AD35+AF35+AH35+AJ35+AL35+AN35+AP35+AR35+AT35 -> 1494 | V35: =Y35+AA35+AC35+AE35+AG35+AI35+AK35+AM35+AO35+AQ35+AS35+AU35 -> 50 | W35: =IF(H35<>"", TEXT(H35, "DD/MM/YY"), "") -> 26/04/25 | Z35: =30+15+30 -> 75 | AB35: 20 | AG35: 50 | AH35: 1399
E36: None | I36: =X36+Z36+AB36+AD36+AF36+AH36+AJ36+AL36+AN36+AP36+AR36+AT36 -> 55 | J36: =Y36+AA36+AC36+AE36+AG36+AI36+AK36+AM36+AO36+AQ36+AS36+AU36 -> 0 | U36: =X36+Z36+AB36+AD36+AF36+AH36+AJ36+AL36+AN36+AP36+AR36+AT36 -> 55 | V36: =Y36+AA36+AC36+AE36+AG36+AI36+AK36+AM36+AO36+AQ36+AS36+AU36 -> 0 | W36: 45774 | Z36: =30+25 -> 55
E37: None | I37: =X37+Z37+AB37+AD37+AF37+AH37+AJ37+AL37+AN37+AP37+AR37+AT37 -> 0 | J37: =Y37+AA37+AC37+AE37+AG37+AI37+AK37+AM37+AO37+AQ37+AS37+AU37 -> 0 | U37: =X37+Z37+AB37+AD37+AF37+AH37+AJ37+AL37+AN37+AP37+AR37+AT37 -> 0 | V37: =Y37+AA37+AC37+AE37+AG37+AI37+AK37+AM37+AO37+AQ37+AS37+AU37 -> 0 | W37: =IF(H37<>"", TEXT(H37, "DD/MM/YY"), "")
E38: None | I38: =X38+Z38+AB38+AD38+AF38+AH38+AJ38+AL38+AN38+AP38+AR38+AT38 -> 0 | J38: =Y38+AA38+AC38+AE38+AG38+AI38+AK38+AM38+AO38+AQ38+AS38+AU38 -> 0 | U38: =X38+Z38+AB38+AD38+AF38+AH38+AJ38+AL38+AN38+AP38+AR38+AT38 -> 0 | V38: =Y38+AA38+AC38+AE38+AG38+AI38+AK38+AM38+AO38+AQ38+AS38+AU38 -> 0 | W38: =IF(H38<>"", TEXT(H38, "DD/MM/YY"), "")
E39: None | I39: =X39+Z39+AB39+AD39+AF39+AH39+AJ39+AL39+AN39+AP39+AR39+AT39 -> 0 | J39: =Y39+AA39+AC39+AE39+AG39+AI39+AK39+AM39+AO39+AQ39+AS39+AU39 -> 0 | U39: =X39+Z39+AB39+AD39+AF39+AH39+AJ39+AL39+AN39+AP39+AR39+AT39 -> 0 | V39: =Y39+AA39+AC39+AE39+AG39+AI39+AK39+AM39+AO39+AQ39+AS39+AU39 -> 0 | W39: =IF(H39<>"", TEXT(H39, "DD/MM/YY"), "")
G49: 45805 | H49: =190+110 -> 300
G50: 45806 | H50: =100+50 -> 150 | I50: need to give santo | K50: 140
G51: 45807 | H51: =20+80 -> 100

Sheet data
A1: Category | B1: Subcategory | C1: UniqueCategories | D1: PaymentMethod | E1: Account | F1: Formula | G1: SavingsAcc
A2: RentAndPaybill | B2: HouseRent | C2: {=UNIQUE(A2:A1006)} -> RentAndPaybill | D2: Cash | E2: Cash | G2: EximBank_2.5 | K2: FLATTEN(ARRAYFORMULA(IF(D2:D7<>TRANSPOSE(D2:D7),D2:D7&" > "&TRANSPOSE(D2:D7),"")))
A3: RentAndPaybill | B3: ElectricBill_Dhk | C3: Bazar | D3: SCB | E3: SCB | G3: CityBank_10
A4: RentAndPaybill | B4: ElectricBill_Swk | C4: HouseholdAccessories | D4: SBL | E4: SBL | G4: BracBank_10
A5: RentAndPaybill | B5: GassBill | C5: MobileInternet | D5: EXIM | E5: EXIM | G5: SBL_root
A6: RentAndPaybill | B6: WifiBill | C6: ExtraExpenses | D6: bKash | E6: bKash | G6: Exim_root
A7: RentAndPaybill | B7: ServiceBill | C7: Savings | D7: Nagad | E7: Nagad
A8: Bazar | B8: DailyBazar | C8: Donation | D8: City | E8: LendTaken
A9: Bazar | B9: Fruits | C9: Pay | E9: LendGiven
A10: Bazar | B10: AdvGiven | E10: City
A11: Bazar | B11: Others | E11: Add
A12: HouseholdAccessories | B12: HouseholdAccessories | E12: Pay
A13: HouseholdAccessories | B13: DailyAccessories
A14: HouseholdAccessories | B14: Medicine
A15: MobileInternet | B15: ForMine
A16: MobileInternet | B16: ForOthers
A17: ExtraExpenses | B17: Tea
A18: ExtraExpenses | B18: Travel
A19: ExtraExpenses | B19: AiSubs
A20: ExtraExpenses | B20: BooksOrCourses
A21: ExtraExpenses | B21: ExtraExpenses
A22: Savings | B22: EximBank_2.5
A23: Savings | B23: CityBank_10
A24: Savings | B24: BracBank_10
... A31: Pay | B31: BracService

Sheet June 25
B2: T r a n s a c t i o n & P a y | H2: DAY | I2: Date | L2: FINANCIAL STATUS | N2: =M4+M5+M6+M8+M9 -> 420 | P2: Date | Q2: Category | R2: Subcategory | S2: Payment Method | T2: Amount | U2: Remarks
B3: Date | C3: Cost | D3: Amount | E3: FROM | F3: TO | J3: Cost | L3: Type | M3: Current Status | N3: Start with | P3: 45807 | Q3: Bazar | R3: DailyBazar | S3: Cash | T3: =360+20+330+30 -> 740
B4: 45804 | D4: 49500 | E4: Add | F4: SCB | H4: =TEXT(I4, "dddd") -> Monday | I4: 45803 | J4: {=sum(IF(($P$3:$P$100=I4), $T$3:$T$100, 0))} -> 0 | L4: {=INDIRECT("Account")} -> Cash | M4: {=N4 - sum(IF(($E$4:$E$49=L4), $D$4:$D$39 + $C$4:$C$39, 0)) + sum(IF(($F$4:$F$49=L4), $D$4:$D$39, 0)) - sum(IF(($S$3:$S$100=L4), $T$3:$T$100, 0))} -> 35 | N4: 0 | P4: 45807 | Q4: Bazar | R4: Fruits | S4: Cash | T4: 400
B5: 45804 | D5: 3333 | E5: Add | F5: SCB | H5: =TEXT(I5, "dddd") -> Tuesday | I5: 45804 | J5: {=sum(IF(($P$3:$P$100=I5), $T$3:$T$100, 0))} -> 0 | L5: SCB | M5: {=N5 - sum(IF(($E$4:$E$49=L5), $D$4:$D$39 + $C$4:$C$39, 0)) + sum(IF(($F$4:$F$49=L5), $D$4:$D$39, 0)) - sum(IF(($S$3:$S$100=L5), $T$3:$T$100, 0))} -> 8 | N5: 0 | P5: 45808 | Q5: ExtraExpenses | R5: ExtraExpenses | S5: Cash | T5: 103000
B6: 45804 | D6: 150000 | E6: Add | F6: SCB | H6: =TEXT(I6, "dddd") -> Wednesday | I6: 45805 | J6: {=sum(IF(($P$3:$P$100=I6), $T$3:$T$100, 0))} -> 0 | L6: SBL | M6: {=N6 - sum(IF(($E$4:$E$49=L6), $D$4:$D$39 + $C$4:$C$39, 0)) + sum(IF(($F$4:$F$49=L6), $D$4:$D$39, 0)) - sum(IF(($S$3:$S$100=L6), $T$3:$T$100, 0))} -> 249 | N6: 10264 | P6: 45808 | Q6: HouseholdAccessories | R6: DailyAccessories | S6: Cash | T6: 40 | U6: shampoo
B7: 45805 | C7: 15 | D7: 10000 | E7: SCB | F7: Cash | H7: =TEXT(I7, "dddd") -> Thursday | I7: 45806 | J7: {=sum(IF(($P$3:$P$100=I7), $T$3:$T$100, 0))} -> 0 | L7: EXIM | M7: {=N7 - sum(IF(($E$4:$E$49=L7), $D$4:$D$39 + $C$4:$C$39, 0)) + sum(IF(($F$4:$F$49=L7), $D$4:$D$39, 0)) - sum(IF(($S$3:$S$100=L7), $T$3:$T$100, 0))} -> 2500 | P7: 45808 | Q7: Bazar | R7: Others | S7: Cash | T7: 80 | U7: ice-cream
B8: 45808 | D8: 1000 | E8: SCB | F8: bKash | H8: =TEXT(I8, "dddd") -> Friday | I8: 45807 | J8: {=sum(IF(($P$3:$P$100=I8), $T$3:$T$100, 0))} -> 1140 | L8: bKash | M8: {=N8 - sum(IF(($E$4:$E$49=L8), $D$4:$D$39 + $C$4:$C$39, 0)) + sum(IF(($F$4:$F$49=L8), $D$4:$D$39, 0)) - sum(IF(($S$3:$S$100=L8), $T$3:$T$100, 0))} -> 11 | N8: 431 | P8: 45808 | Q8: ExtraExpenses | R8: Travel | S8: Cash | T8: =10+20+300 -> 330
B9: 45808 | D9: 103000 | E9: SCB | F9: Cash | H9: =TEXT(I9, "dddd") -> Saturday | I9: 45808 | J9: {=sum(IF(($P$3:$P$100=I9), $T$3:$T$100, 0))} -> 104274 | L9: Nagad | M9: {=N9 - sum(IF(($E$4:$E$49=L9), $D$4:$D$39 + $C$4:$C$39, 0)) + sum(IF(($F$4:$F$49=L9), $D$4:$D$39, 0)) - sum(IF(($S$3:$S$100=L9), $T$3:$T$100, 0))} -> 117 | N9: 117 | P9: 45808 | Q9: ExtraExpenses | R9: Tea | S9: Cash | T9: =15+75+45 -> 135
B10: 45808 | D10: 1750 | E10: SCB | F10: Cash | H10: =TEXT(I10, "dddd") -> Sunday | I10: 45809 | J10: {=sum(IF(($P$3:$P$100=I10), $T$3:$T$100, 0))} -> 6000 | L10: LendTaken | M10: {=N10 - sum(IF(($E$4:$E$49=L10), $D$4:$D$39 + $C$4:$C$39, 0)) + sum(IF(($F$4:$F$49=L10), $D$4:$D$39, 0)) - sum(IF(($S$3:$S$100=L10), $T$3:$T$100, 0))} -> 150000 | N10: 150000 | P10: 45809 | Q10: ExtraExpenses | R10: ExtraExpenses | S10: Cash | T10: 5500 | U10: fridge
B11: 45810 | C11: 15 | D11: 20000 | E11: SCB | F11: Cash | H11: =TEXT(I11, "dddd") -> Monday | I11: 45810 | J11: {=sum(IF(($P$3:$P$100=I11), $T$3:$T$100, 0))} -> 800 | L11: LendGiven | M11: {=N11 - sum(IF(($E$4:$E$49=L11), $D$4:$D$39 + $C$4:$C$39, 0)) + sum(IF(($F$4:$F$49=L11), $D$4:$D$39, 0)) - sum(IF(($S$3:$S$100=L11), $T$3:$T$100, 0))} -> 5500 | N11: 2500 | P11: 45809 | Q11: Bazar | R11: AdvGiven | S11: Cash | T11: 500 | U11: ammu
B12: 45810 | D12: 8000 | E12: SCB | F12: Cash | H12: =TEXT(I12, "dddd") -> Tuesday | I12: 45811 | J12: {=sum(IF(($P$3:$P$100=I12), $T$3:$T$100, 0))} -> 8020 | L12: City | P12: 45810 | Q12: Bazar | R12: AdvGiven | S12: Cash | T12: 500 | U12: ammu
B13: 45811 | C13: 15 | D13: 20000 | E13: SCB | F13: Cash | H13: =TEXT(I13, "dddd") -> Wednesday | I13: 45812 | J13: {=sum(IF(($P$3:$P$100=I13), $T$3:$T$100, 0))} -> 49918 | P13: 45810 | Q13: Donation | R13: Donation | S13: Cash | T13: 300
B14: 45812 | C14: 15 | D14: 20000 | E14: SCB | F14: Cash | H14: =TEXT(I14, "dddd") -> Thursday | I14: 45813 | J14: {=sum(IF(($P$3:$P$100=I14), $T$3:$T$100, 0))} -> 4720 | P14: 45811 | Q14: ExtraExpenses | R14: Tea | S14: Cash | T14: 20
B15: 45812 | D15: 1000 | E15: SCB | F15: bKash | H15: =TEXT(I15, "dddd") -> Friday | I15: 45814 | J15: {=sum(IF(($P$3:$P$100=I15), $T$3:$T$100, 0))} -> 2437 | L15: LEND GIVEN TO | N15: =sum(N17:N22) -> 0 | P15: 45812 | Q15: HouseholdAccessories | R15: HouseholdAccessories | S15: Cash | T15: 2000 | U15: ammu
B16: 45816 | D16: 1000 | E16: SCB | F16: bKash | H16: =TEXT(I16, "dddd") -> Saturday | I16: 45815 | J16: {=sum(IF(($P$3:$P$100=I16), $T$3:$T$100, 0))} -> 0 | L16: Date | M16: Given To | N16: Amount | P16: 45812 | Q16: ExtraExpenses | R16: ExtraExpenses | S16: Cash | T16: 5000 | U16: fan
B17: 45818 | C17: 15 | D17: 10000 | E17: SCB | F17: Cash | H17: =TEXT(I17, "dddd") -> Sunday | I17: 45816 | J17: {=sum(IF(($P$3:$P$100=I17), $T$3:$T$100, 0))} -> 680 | P17: 45812 | Q17: ExtraExpenses | R17: ExtraExpenses | S17: bKash | T17: 580 | U17: fan
B18: 45818 | C18: 15 | D18: 10000 | E18: SBL | F18: Cash | H18: =TEXT(I18, "dddd") -> Monday | I18: 45817 | J18: {=sum(IF(($P$3:$P$100=I18), $T$3:$T$100, 0))} -> 3000 | P18: 45812 | Q18: ExtraExpenses | R18: ExtraExpenses | S18: Cash | T18: 250 | U18: sim-teletalk
B19: 45814 | D19: 3000 | E19: SCB | F19: bKash | H19: =TEXT(I19, "dddd") -> Tuesday | I19: 45818 | J19: {=sum(IF(($P$3:$P$100=I19), $T$3:$T$100, 0))} -> 2140 | P19: 45812 | Q19: ExtraExpenses | R19: ExtraExpenses | S19: Cash | T19: 3910 | U19: gas stove
B20: 45819 | D20: 2500 | E20: SCB | F20: EXIM | H20: =TEXT(I20, "dddd") -> Wednesday | I20: 45819 | J20: {=sum(IF(($P$3:$P$100=I20), $T$4:$T$100, 0))} -> 487 | P20: 45812 | Q20: ExtraExpenses | R20: Travel | S20: Cash | T20: =10+10+30+30+1600 -> 1680 | U20: home-shifting
B21: 45814 | D21: 3000 | E21: bKash | F21: LendGiven | H21: =TEXT(I21, "dddd") -> Thursday | I21: 45820 | J21: {=sum(IF(($P$3:$P$100=I21), $T$4:$T$100, 0))} -> 140 | P21: 45812 | Q21: ExtraExpenses | R21: ExtraExpenses | S21: Cash | T21: 35000 | U21: fridge
B22: 45821 | D22: 500 | E22: SCB | F22: bKash | H22: =TEXT(I22, "dddd") -> Friday | I22: 45821 | J22: {=sum(IF(($P$3:$P$100=I22), $T$4:$T$100, 0))} -> 1510 | P22: 45812 | Q22: HouseholdAccessories | R22: HouseholdAccessories | S22: Cash | T22: =20+200+830 -> 1050 | U22: light, boti
B23: 45829 | D23: 1000 | E23: SCB | F23: bKash | H23: =TEXT(I23, "dddd") -> Saturday | I23: 45822 | J23: {=sum(IF(($P$3:$P$100=I23), $T$4:$T$100, 0))} -> 735 | P23: 45812 | Q23: Bazar | R23: DailyBazar | S23: Cash | T23: =155+90+80+40 -> 365
H24: =TEXT(I24, "dddd") -> Sunday | I24: 45823 | J24: {=sum(IF(($P$3:$P$100=I24), $T$4:$T$100, 0))} -> 130 | L24: LEND TAKEN FROM | N24: =sum(N26:N31) -> 0 | P24: 45812 | Q24: Bazar | R24: Others | S24: Cash | T24: =25+10 -> 35
H25: =TEXT(I25, "dddd") -> Monday | I25: 45824 | J25: {=sum(IF(($P$3:$P$100=I25), $T$4:$T$100, 0))} -> 600 | L25: Date | M25: Taken From | N25: Amount | P25: 45813 | Q25: Bazar | R25: DailyBazar | S25: Cash | T25: =350+400+2000+20+500 -> 3270
H26: =TEXT(I26, "dddd") -> Tuesday | I26: 45825 | J26: {=sum(IF(($P$3:$P$100=I26), $T$4:$T$100, 0))} -> 20 | P26: 45813 | Q26: HouseholdAccessories | R26: DailyAccessories | S26: Cash | T26: 130 | U26: vim
H27: =TEXT(I27, "dddd") -> Wednesday | I27: 45826 | J27: {=sum(IF(($P$3:$P$100=I27), $T$4:$T$100, 0))} -> 400 | P27: 45813 | Q27: HouseholdAccessories | R27: HouseholdAccessories | S27: Cash | T27: =100+70 -> 170 | U27: rosi, electronics
H28: =TEXT(I28, "dddd") -> Thursday | I28: 45827 | J28: {=sum(IF(($P$3:$P$100=I28), $T$4:$T$100, 0))} -> 250 | P28: 45813 | Q28: Bazar | R28: Others | S28: Cash | T28: =200+200+50 -> 450 | U28: ice-cream, biskit, nasta
H29: =TEXT(I29, "dddd") -> Friday | I29: 45828 | J29: {=sum(IF(($P$3:$P$100=I29), $T$4:$T$100, 0))} -> 20 | P29: 45813 | Q29: Bazar | R29: Fruits | S29: Cash | T29: 200
H30: =TEXT(I30, "dddd") -> Saturday | I30: 45829 | J30: {=sum(IF(($P$3:$P$100=I30), $T$4:$T$100, 0))} -> 600 | P30: 45811 | Q30: RentAndPaybill | R30: HouseRent | S30: Cash | T30: 8000 | U30: prev
H31: =TEXT(I31, "dddd") -> Sunday | I31: 45830 | J31: {=sum(IF(($P$3:$P$100=I31), $T$4:$T$100, 0))} -> 410 | P31: 45814 | Q31: Donation | R31: Donation | S31: Cash | T31: 965 | U31: can't find source
H32: =TEXT(I32, "dddd") -> Monday | I32: 45831 | J32: {=sum(IF(($P$3:$P$100=I32), $T$4:$T$100, 0))} -> 125 | P32: 45808 | Q32: RentAndPaybill | R32: ElectricBill_Swk | S32: bKash | T32: 491
H33: =TEXT(I33, "dddd") -> Tuesday | I33: 45832 | J33: {=sum(IF(($P$3:$P$100=I33), $T$4:$T$100, 0))} -> 1201 | N33: =sum(N35:N40) -> 0 | P33: 45808 | Q33: MobileInternet | R33: ForMine | S33: bKash | T33: 148
H34: =TEXT(I34, "dddd") -> Wednesday | I34: 45833 | J34: {=sum(IF(($P$3:$P$100=I34), $T$4:$T$100, 0))} -> 100 | P34: 45808 | Q34: MobileInternet | R34: ForMine | S34: bKash | T34: 50
H35: =TEXT(I35, "dddd") -> Thursday | I35: 45834 | J35: {=sum(IF(($P$3:$P$100=I35), $T$4:$T$100, 0))} -> 0 | P35: 45812 | Q35: MobileInternet | R35: ForMine | S35: bKash | T35: 48
P36: 45813 | Q36: RentAndPaybill | R36: ElectricBill_Dhk | S36: bKash | T36: 500
P37: 45814 | Q37: Bazar | R37: DailyBazar | S37: Cash | T37: =250+190+275+40+40+20+360 -> 1175
P38: 45814 | Q38: Donation | R38: Donation | S38: Cash | T38: =20+20+15 -> 55
P39: 45816 | Q39: Donation | R39: Donation | S39: bKash | T39: 500
P40: 45816 | Q40: ExtraExpenses | R40: ExtraExpenses | S40: Cash | T40: 180
P41: 45817 | Q41: Bazar | R41: AdvGiven | S41: Cash | T41: 3000
B42: B U D G E T | P42: 45818 | Q42: Bazar | R42: AdvGiven | S42: Cash | T42: 2000
P43: 45818 | Q43: HouseholdAccessories | R43: HouseholdAccessories | S43: Cash | T43: 50
B44: Category | E44: cost | F44: Subcategory | I44: Cost | J44: Remain | P44: 45818 | Q44: Bazar | R44: Others | S44: Cash | T44: 50
B45: RentAndPaybill | E45: xxx | F45: {=INDIRECT("Subcategory")} -> HouseRent | P45: 45818 | Q45: ExtraExpenses | R45: Travel | S45: Cash | T45: =30+10 -> 40
F46: ElectricBill_Dhk | P46: 45819 | Q46: RentAndPaybill | R46: HouseRent | S46: Cash | T46: 18000
F47: ElectricBill_Swk | P47: 45819 | Q47: Bazar | R47: Fruits | S47: Cash | T47: 245
F48: GassBill | P48: 45814 | Q48: MobileInternet | R48: ForMine | S48: bKash | T48: 242
F49: WifiBill | P49: 45821 | Q49: Donation | R49: Donation | S49: Cash | T49: 20
F50: ServiceBill | P50: 45821 | Q50: Bazar | R50: Others | S50: Cash | T50: =220 -> 220
B51: Bazar | F51: DailyBazar | P51: 45821 | Q51: RentAndPaybill | R51: WifiBill | S51: bKash | T51: 840
F52: Fruits | P52: 45821 | Q52: MobileInternet | R52: ForOthers | S52: bKash | T52: 208
F53: AdvGiven | P53: 45820 | Q53: MobileInternet | R53: ForMine | S53: bKash | T53: 242
F54: Others | P54: 45822 | Q54: ExtraExpenses | R54: Travel | S54: Cash | T54: =75+65 -> 140
B55: HouseholdAccessories | F55: HouseholdAccessories | P55: 45822 | Q55: ExtraExpenses | R55: Tea | S55: Cash | T55: 20
F56: DailyAccessories | P56: 45822 | Q56: ExtraExpenses | R56: ExtraExpenses | S56: Cash | T56: =240+35 -> 275
F57: Medicine | P57: 45822 | Q57: Bazar | R57: Others | S57: Cash | T57: 30
B58: MobileInternet | F58: ForMine | P58: 45823 | Q58: Bazar | R58: Fruits | S58: Cash | T58: =160+50+200 -> 410
F59: ForOthers | P59: 45824 | Q59: ExtraExpenses | R59: HouseholdAccessories | S59: Cash | T59: =130 -> 130
B60: ExtraExpenses | F60: Tea | P60: 45825 | Q60: ExtraExpenses | R60: ExtraExpenses | S60: Cash | T60: 600
F61: Travel | P61: 45826 | Q61: Bazar | R61: Others | S61: Cash | T61: 20
F62: AiSubs | P62: 45827 | Q62: Bazar | R62: Others | S62: Cash | T62: 400
B63: Savings | F63: BooksOrCourses | P63: 45827 | Q63: Bazar | R63: Others | S63: Cash | T63: 50
F64: ExtraExpenses | P64: 45827 | Q64: ExtraExpenses | R64: HouseholdAccessories | S64: Cash | T64: 100
B65: Donation | F65: EximBank_2.5 | P65: 45827 | Q65: MobileInternet | R65: ForOthers | S65: bKash | T65: 50
F66: CityBank_10 | P66: 45828 | Q66: ExtraExpenses | R66: Travel | S66: Cash | T66: 50
F67: BracBank_10 | P67: 45829 | Q67: ExtraExpenses | R67: Travel | S67: Cash | T67: 20
F68: SBL_root | P68: 45829 | Q68: ExtraExpenses | R68: Tea | S68: Cash | T68: =35+70+20 -> 125
F69: Exim_root | P69: 45829 | Q69: HouseholdAccessories | R69: HouseholdAccessories | S69: Cash | T69: 60
F70: Donation | P70: 45829 | Q70: Bazar | R70: Others | S70: Cash | T70: 285
F71: Unknown | P71: 45830 | Q71: Bazar | R71: Others | S71: Cash | T71: 100
F72: CityService | P72: 45830 | Q72: HouseholdAccessories | R72: HouseholdAccessories | S72: Cash | T72: 80
F73: SblService | P73: 45830 | Q73: ExtraExpenses | R73: ExtraExpenses | S73: Cash | T73: 30
P74: 45831 | Q74: HouseholdAccessories | R74: HouseholdAccessories | S74: Cash | T74: 300
P75: 45831 | Q75: Bazar | R75: Others | S75: Cash | T75: 20
P76: 45832 | Q76: HouseholdAccessories | R76: HouseholdAccessories | S76: Cash | T76: 105
P77: 45832 | Q77: Bazar | R77: Others | S77: Cash | T77: 180
P78: 45832 | Q78: RentAndPaybill | R78: ElectricBill_Swk | S78: bKash | T78: 451
P79: 45832 | Q79: MobileInternet | R79: ForMine | S79: bKash | T79: 270
P80: 45829 | Q80: RentAndPaybill | R80: ElectricBill_Dhk | S80: bKash | T80: 300
P81: 45833 | Q81: Bazar | R81: DailyBazar | S81: Cash | T81: 30
P82: 45833 | Q82: HouseholdAccessories | R82: Medicine | S82: Cash | T82: 100

Sheet July 25
B2: T r a n s a c t i o n & P a y | H2: DAY | I2: Date | J2: =sum(J4:J39) -> 39094 | L2: FINANCIAL STATUS | N2: =M4+M5+M8+M9 -> 60838 | P2: Date | Q2: Category | R2: Subcategory | S2: Payment Method | T2: Amount | U2: Remarks
B3: Date | C3: Cost | D3: Amount | E3: FROM | F3: TO | J3: Cost | L3: Type | M3: Current Status | N3: Start with | P3: 45834 | Q3: HouseholdAccessories | R3: HouseholdAccessories | S3: Cash | T3: =320+110 -> 430 | U3: mask+odofresh
B4: 45834 | D4: 39500 | E4: Add | F4: SCB | H4: =TEXT(I4, "dddd") -> Thursday | I4: 45834 | J4: {=sum(IF(($P$3:$P$100=I4), $T$3:$T$100, 0))} -> 1130 | L4: {=INDIRECT("Account")} -> Cash | M4: {=N4 - sum(IF(($E$4:$E$49=L4), $D$4:$D$39 + $C$4:$C$39, 0)) + sum(IF(($F$4:$F$49=L4), $D$4:$D$39, 0)) - sum(IF(($S$3:$S$100=L4), $T$3:$T$100, 0))} -> 3725 | N4: 0 | P4: 45835 | Q4: Bazar | R4: DailyBazar | S4: Cash | T4: 30
B5: 45834 | C5: 0 | D5: 30000 | E5: SCB | F5: Cash | H5: =TEXT(I5, "dddd") -> Friday | I5: 45835 | J5: {=sum(IF(($P$3:$P$100=I5), $T$3:$T$100, 0))} -> 40 | L5: SCB | M5: {=N5 - sum(IF(($E$4:$E$49=L5), $D$4:$D$39 + $C$4:$C$39, 0)) + sum(IF(($F$4:$F$49=L5), $D$4:$D$39, 0)) - sum(IF(($S$3:$S$100=L5), $T$3:$T$100, 0))} -> 57034 | N5: =31 -> 31 | P5: 45836 | Q5: ExtraExpenses | R5: Travel | S5: Cash | T5: =80+65 -> 145
B6: 45838 | D6: 53333 | E6: Add | F6: SCB | H6: =TEXT(I6, "dddd") -> Saturday | I6: 45836 | J6: {=sum(IF(($P$3:$P$100=I6), $T$3:$T$100, 0))} -> 9765 | L6: SBL | M6: {=N6 - sum(IF(($E$4:$E$49=L6), $D$4:$D$39 + $C$4:$C$39, 0)) + sum(IF(($F$4:$F$49=L6), $D$4:$D$39, 0)) - sum(IF(($S$3:$S$100=L6), $T$3:$T$100, 0))} -> 30191 | N6: 191 | P6: 45836 | Q6: ExtraExpenses | R6: ExtraExpenses | S6: Cash | T6: =3500+30 -> 3530 | U6: fan
B7: 45838 | D7: 30000 | E7: Add | F7: SBL | H7: =TEXT(I7, "dddd") -> Sunday | I7: 45837 | J7: {=sum(IF(($P$3:$P$100=I7), $T$3:$T$100, 0))} -> 1230 | L7: EXIM | M7: {=N7 - sum(IF(($E$4:$E$49=L7), $D$4:$D$39 + $C$4:$C$39, 0)) + sum(IF(($F$4:$F$49=L7), $D$4:$D$39, 0)) - sum(IF(($S$3:$S$100=L7), $T$3:$T$100, 0))} -> 285 | N7: 285 | P7: 45836 | Q7: Bazar | R7: DailyBazar | S7: Cash | T7: 90
B8: 45838 | D8: 800 | E8: SCB | F8: Nagad | H8: =TEXT(I8, "dddd") -> Monday | I8: 45838 | J8: {=sum(IF(($P$3:$P$100=I8), $T$3:$T$100, 0))} -> 385 | L8: bKash | M8: {=N8 - sum(IF(($E$4:$E$49=L8), $D$4:$D$39 + $C$4:$C$39, 0)) + sum(IF(($F$4:$F$49=L8), $D$4:$D$39, 0)) - sum(IF(($S$3:$S$100=L8), $T$3:$T$100, 0))} -> 77 | N8: 11 | P8: 45834 | Q8: ExtraExpenses | R8: Travel | S8: Cash | T8: 700 | U8: abbu
B9: 45846 | D9: 1000 | E9: SCB | F9: bKash | H9: =TEXT(I9, "dddd") -> Tuesday | I9: 45839 | J9: {=sum(IF(($P$3:$P$100=I9), $T$3:$T$100, 0))} -> 905 | L9: Nagad | M9: {=N9 - sum(IF(($E$4:$E$49=L9), $D$4:$D$39 + $C$4:$C$39, 0)) + sum(IF(($F$4:$F$49=L9), $D$4:$D$39, 0)) - sum(IF(($S$3:$S$100=L9), $T$3:$T$100, 0))} -> 2 | N9: 87 | P9: 45837 | Q9: Bazar | R9: DailyBazar | S9: Cash | T9: =660+20+50 -> 730 | U9: murgi
B10: 45850 | C10: 15 | D10: 3000 | E10: SCB | F10: Cash | H10: =TEXT(I10, "dddd") -> Wednesday | I10: 45840 | J10: {=sum(IF(($P$3:$P$100=I10), $T$3:$T$100, 0))} -> 200 | L10: LendTaken | M10: 140000 | N10: 150000 | P10: 45837 | Q10: Bazar | R10: Fruits | S10: Cash | T10: 300 | U10: mango
B11: 45851 | D11: 7000 | E11: Add | F11: SCB | H11: =TEXT(I11, "dddd") -> Thursday | I11: 45841 | J11: {=sum(IF(($P$3:$P$100=I11), $T$3:$T$100, 0))} -> 450 | L11: LendGiven | M11: {=N11 - sum(IF(($E$4:$E$49=L11), $D$4:$D$39 + $C$4:$C$39, 0)) + sum(IF(($F$4:$F$49=L11), $D$4:$D$39, 0)) - sum(IF(($S$3:$S$100=L11), $T$3:$T$100, 0))} -> 5500 | N11: =2500+3000 -> 5500 | P11: 45837 | Q11: Bazar | R11: Others | S11: Cash | T11: 50
B12: 45862 | C12: 15 | D12: 5000 | E12: SCB | F12: Cash | H12: =TEXT(I12, "dddd") -> Friday | I12: 45842 | J12: {=sum(IF(($P$3:$P$100=I12), $T$3:$T$100, 0))} -> 0 | L12: City | P12: 45837 | Q12: HouseholdAccessories | R12: HouseholdAccessories | S12: Cash | T12: 150 | U12: fork spoon
B13: 45855 | D13: 500 | E13: SCB | F13: bKash | H13: =TEXT(I13, "dddd") -> Saturday | I13: 45843 | J13: {=sum(IF(($P$3:$P$100=I13), $T$3:$T$100, 0))} -> 0 | P13: 45836 | Q13: Bazar | R13: AdvGiven | S13: Cash | T13: 6000 | U13: ammu - 5k, sis - 1K
H14: =TEXT(I14, "dddd") -> Sunday | I14: 45844 | J14: {=sum(IF(($P$3:$P$100=I14), $T$3:$T$100, 0))} -> 17450 | P14: 45835 | Q14: Donation | R14: Donation | S14: Cash | T14: 10
H15: =TEXT(I15, "dddd") -> Monday | I15: 45845 | J15: {=sum(IF(($P$3:$P$100=I15), $T$3:$T$100, 0))} -> 20 | L15: LEND GIVEN TO | N15: =sum(N17:N22) -> 0 | P15: 45837 | Q15: Donation | R15: Unknown | S15: Cash | T15: 0 | U15: X
H16: =TEXT(I16, "dddd") -> Tuesday | I16: 45846 | J16: {=sum(IF(($P$3:$P$100=I16), $T$3:$T$100, 0))} -> 0 | L16: Date | M16: Given To | N16: Amount | P16: 45838 | Q16: Bazar | R16: Others | S16: Cash | T16: =180+10 -> 190 | U16: noodles
H17: =TEXT(I17, "dddd") -> Wednesday | I17: 45847 | J17: {=sum(IF(($P$3:$P$100=I17), $T$3:$T$100, 0))} -> 140 | L17: 45774 | M17: 2500 | N17: Rajib vai | P17: 45838 | Q17: Bazar | R17: DailyBazar | S17: Cash | T17: 195 | U17: cal
H18: =TEXT(I18, "dddd") -> Thursday | I18: 45848 | J18: {=sum(IF(($P$3:$P$100=I18), $T$3:$T$100, 0))} -> 0 | M18: 3000 | N18: Rafi vai | P18: 45839 | Q18: RentAndPaybill | R18: ElectricBill_Dhk | S18: Nagad | T18: 805
H19: =TEXT(I19, "dddd") -> Friday | I19: 45849 | J19: {=sum(IF(($P$3:$P$100=I19), $T$3:$T$100, 0))} -> 1678 | M19: 100 | N19: arafat vai | P19: 45839 | Q19: HouseholdAccessories | R19: HouseholdAccessories | S19: Cash | T19: =50+50 -> 100
H20: =TEXT(I20, "dddd") -> Saturday | I20: 45850 | J20: {=sum(IF(($P$3:$P$100=I20), $T$3:$T$100, 0))} -> 285 | P20: 45840 | Q20: Bazar | R20: Others | S20: Cash | T20: 200
H21: =TEXT(I21, "dddd") -> Sunday | I21: 45851 | J21: {=sum(IF(($P$3:$P$100=I21), $T$3:$T$100, 0))} -> 460 | P21: 45841 | Q21: Bazar | R21: Fruits | S21: Cash | T21: 400
H22: =TEXT(I22, "dddd") -> Monday | I22: 45852 | J22: {=sum(IF(($P$3:$P$100=I22), $T$3:$T$100, 0))} -> 200 | P22: 45841 | Q22: Bazar | R22: Others | S22: Cash | T22: 50
H23: =TEXT(I23, "dddd") -> Tuesday | I23: 45853 | J23: {=sum(IF(($P$3:$P$100=I23), $T$3:$T$100, 0))} -> 140 | P23: 45844 | Q23: RentAndPaybill | R23: HouseRent | S23: Cash | T23: 13000
H24: =TEXT(I24, "dddd") -> Wednesday | I24: 45854 | J24: {=sum(IF(($P$3:$P$100=I24), $T$3:$T$100, 0))} -> 210 | L24: LEND TAKEN FROM | N24: =sum(N26:N31) -> 0 | P24: 45844 | Q24: RentAndPaybill | R24: GassBill | S24: Cash | T24: 1080
H25: =TEXT(I25, "dddd") -> Thursday | I25: 45855 | J25: {=sum(IF(($P$3:$P$100=I25), $T$3:$T$100, 0))} -> 1220 | L25: Date | M25: Taken From | N25: Amount | P25: 45844 | Q25: RentAndPaybill | R25: ServiceBill | S25: Cash | T25: =600+200+20 -> 820
H26: =TEXT(I26, "dddd") -> Friday | I26: 45856 | J26: {=sum(IF(($P$3:$P$100=I26), $T$3:$T$100, 0))} -> 0 | P26: 45844 | Q26: Savings | R26: EximBank_2.5 | S26: SCB | T26: 2500 | U26: EXIM
H27: =TEXT(I27, "dddd") -> Saturday | I27: 45857 | J27: {=sum(IF(($P$3:$P$100=I27), $T$3:$T$100, 0))} -> 0 | P27: 45845 | Q27: ExtraExpenses | R27: Tea | S27: Cash | T27: 20
H28: =TEXT(I28, "dddd") -> Sunday | I28: 45858 | J28: {=sum(IF(($P$3:$P$100=I28), $T$3:$T$100, 0))} -> 420 | P28: 45847 | Q28: Bazar | R28: Others | S28: Cash | T28: 140
H29: =TEXT(I29, "dddd") -> Monday | I29: 45859 | J29: {=sum(IF(($P$3:$P$100=I29), $T$3:$T$100, 0))} -> 260 | P29: 45849 | Q29: Donation | R29: Donation | S29: Cash | T29: 10
H30: =TEXT(I30, "dddd") -> Tuesday | I30: 45860 | J30: {=sum(IF(($P$3:$P$100=I30), $T$3:$T$100, 0))} -> 670 | P30: 45849 | Q30: ExtraExpenses | R30: Travel | S30: Cash | T30: 30
H31: =TEXT(I31, "dddd") -> Wednesday | I31: 45861 | J31: {=sum(IF(($P$3:$P$100=I31), $T$3:$T$100, 0))} -> 100 | P31: 45849 | Q31: ExtraExpenses | R31: Tea | S31: Cash | T31: =30+60 -> 90
H32: =TEXT(I32, "dddd") -> Thursday | I32: 45862 | J32: {=sum(IF(($P$3:$P$100=I32), $T$3:$T$100, 0))} -> 536 | P32: 45849 | Q32: Bazar | R32: Fruits | S32: Cash | T32: =300+40 -> 340
H33: =TEXT(I33, "dddd") -> Friday | I33: 45863 | J33: {=sum(IF(($P$3:$P$100=I33), $T$3:$T$100, 0))} -> 1200 | N33: =sum(N35:N40) -> 0 | P33: 45849 | Q33: Bazar | R33: AdvGiven | S33: Cash | T33: 1000
H34: =TEXT(I34, "dddd") -> Saturday | I34: 45864 | J34: {=sum(IF(($P$3:$P$100=I34), $T$3:$T$100, 0))} -> 0 | P34: 45850 | Q34: HouseholdAccessories | R34: DailyAccessories | S34: Cash | T34: 40
H35: =TEXT(I35, "dddd") -> Sunday | I35: 45865 | J35: {=sum(IF(($P$3:$P$100=I35), $T$3:$T$100, 0))} -> 0 | P35: 45850 | Q35: Bazar | R35: Others | S35: Cash | T35: =45+200 -> 245
J36: {=sum(IF(($P$3:$P$100=I36), $T$3:$T$100, 0))} -> 0 | P36: 45851 | Q36: ExtraExpenses | R36: ExtraExpenses | S36: Cash | T36: 350 | U36: team
P37: 45851 | Q37: HouseholdAccessories | R37: Medicine | S37: Cash | T37: 90
P38: 45851 | Q38: Donation | R38: Donation | S38: Cash | T38: 20
P39: 45852 | Q39: Donation | R39: Donation | S39: Cash | T39: 200
P40: 45853 | Q40: Bazar | R40: Others | S40: Cash | T40: 140
P41: 45854 | Q41: Bazar | R41: Others | S41: Cash | T41: 160
B42: B U D G E T | P42: 45854 | Q42: Donation | R42: Unknown | S42: Cash | T42: 20
P43: 45855 | Q43: Bazar | R43: Others | S43: Cash | T43: 380
B44: Category | E44: Budget | F44: Subcategory | I44: Budget | J44: Cost | P44: 45858 | Q44: HouseholdAccessories | R44: DailyAccessories | S44: Cash | T44: 420
B45: RentAndPaybill | E45: =Sum(I45:I50) -> 16970 | F45: {=INDIRECT("Subcategory")} -> HouseRent | I45: 13000 | J45: {=sum(IF(($R$3:$R$100=F45), $T$3:$T$100, 0))} -> 13000 | P45: 45859 | Q45: Bazar | R45: Fruits | S45: Cash | T45: 70
F46: ElectricBill_Dhk | I46: 800 | J46: {=sum(IF(($R$3:$R$100=F46), $T$3:$T$100, 0))} -> 805 | L46: =I45+I48+I50 -> 14880 | P46: 45859 | Q46: ExtraExpenses | R46: Medicine | S46: Cash | T46: 100
F47: ElectricBill_Swk | I47: 450 | J47: {=sum(IF(($R$3:$R$100=F47), $T$3:$T$100, 0))} -> 386 | P47: 45859 | Q47: ExtraExpenses | R47: ExtraExpenses | S47: Cash | T47: 90
F48: GassBill | I48: 1080 | J48: {=sum(IF(($R$3:$R$100=F48), $T$3:$T$100, 0))} -> 1080 | L48: =sum(I45:I50) -> 16970 | P48: 45860 | Q48: Bazar | R48: AdvGiven | S48: Cash | T48: 500
F49: WifiBill | I49: 840 | J49: {=sum(IF(($R$3:$R$100=F49), $T$3:$T$100, 0))} -> 840 | P49: 45860 | Q49: Donation | R49: Unknown | S49: Cash | T49: 100
F50: ServiceBill | I50: =200+600 -> 800 | J50: {=sum(IF(($R$3:$R$100=F50), $T$3:$T$100, 0))} -> 820 | P50: 45861 | Q50: Donation | R50: Donation | S50: Cash | T50: 100
B51: Bazar | E51: =Sum(I51:I54) -> 9500 | F51: DailyBazar | I51: 2000 | J51: {=sum(IF(($R$3:$R$100=F51), $T$3:$T$100, 0))} -> 1045 | L51: =800+450+840+300 -> 2390 | P51: 45860 | Q51: Bazar | R51: Fruits | S51: Cash | T51: 70
F52: Fruits | I52: 1000 | J52: {=sum(IF(($R$3:$R$100=F52), $T$3:$T$100, 0))} -> 1910 | P52: 45862 | Q52: ExtraExpenses | R52: ExtraExpenses | S52: Cash | T52: 150
F53: AdvGiven | I53: 6000 | J53: {=sum(IF(($R$3:$R$100=F53), $T$3:$T$100, 0))} -> 7940 | P53: 45863 | Q53: Donation | R53: Donation | S53: Cash | T53: =10+20 -> 30
F54: Others | I54: 500 | J54: {=sum(IF(($R$3:$R$100=F54), $T$3:$T$100, 0))} -> 1555 | P54: 45863 | Q54: Bazar | R54: Fruits | S54: Cash | T54: =300+430 -> 730
B55: HouseholdAccessories | F55: HouseholdAccessories | I55: 1000 | J55: {=sum(IF(($R$3:$R$100=F55), $T$3:$T$100, 0))} -> 680 | P55: 45863 | Q55: Bazar | R55: AdvGiven | S55: Cash | T55: 440
F56: DailyAccessories | I56: 1000 | J56: {=sum(IF(($R$3:$R$100=F56), $T$3:$T$100, 0))} -> 460 | P56: 45849 | Q56: MobileInternet | R56: ForOthers | S56: bKash | T56: 208
F57: Medicine | I57: 300 | J57: {=sum(IF(($R$3:$R$100=F57), $T$3:$T$100, 0))} -> 190 | P57: 45855 | Q57: RentAndPaybill | R57: WifiBill | S57: bKash | T57: 840
B58: MobileInternet | F58: ForMine | I58: 100 | J58: {=sum(IF(($R$3:$R$100=F58), $T$3:$T$100, 0))} -> 30 | P58: 45862 | Q58: RentAndPaybill | R58: ElectricBill_Swk | S58: bKash | T58: 386
F59: ForOthers | I59: 300 | J59: {=sum(IF(($R$3:$R$100=F59), $T$3:$T$100, 0))} -> 258 | P59: 45844 | Q59: MobileInternet | R59: ForOthers | S59: Nagad | T59: 50
B60: ExtraExpenses | F60: Tea | I60: 0 | J60: {=sum(IF(($R$3:$R$100=F60), $T$3:$T$100, 0))} -> 110 | P60: 45854 | Q60: MobileInternet | R60: ForMine | S60: Nagad | T60: 30
F61: Travel | I61: 700 | J61: {=sum(IF(($R$3:$R$100=F61), $T$3:$T$100, 0))} -> 875
F62: AiSubs | I62: 3500 | J62: {=sum(IF(($R$3:$R$100=F62), $T$3:$T$100, 0))} -> 0
B63: Savings | F63: BooksOrCourses | I63: 2500 | J63: {=sum(IF(($R$3:$R$100=F63), $T$3:$T$100, 0))} -> 0
F64: ExtraExpenses | J64: {=sum(IF(($R$3:$R$100=F64), $T$3:$T$100, 0))} -> 4120
B65: Donation | F65: EximBank_2.5 | I65: 130 | J65: {=sum(IF(($R$3:$R$100=F65), $T$3:$T$100, 0))} -> 2500
F66: CityBank_10
F67: BracBank_10 | H67: Total | I67: =SUM(I45:I65) -> 36000 | J67: =SUM(J45:J65) -> 38604
F68: SBL_root | H68: Non-Cash | I68: =I46+I47+I49+I58+I59+I63 -> 4990 | J68: =J46+J47+J49+J58+J59+J63 -> 2319
F69: Exim_root | H69: Cash | I69: =I67-I68 -> 31010 | J69: =J67-J68 -> 36285
F70: Donation
F71: Unknown
F72: CityService
F73: SblService

Sheet Aug 25
B2: T r a n s a c t i o n & P a y | H2: DAY | I2: Date | J2: =sum(J4:J39) -> 41856 | L2: FINANCIAL STATUS | N2: =M4+M5+M8+M9 -> 21276 | P2: Date | Q2: Category | R2: Subcategory | S2: Payment Method | T2: Amount | U2: Remarks
B3: Date | C3: Cost | D3: Amount | E3: FROM | F3: TO | J3: Cost | L3: Type | M3: Current Status | N3: Start with | P3: 45864 | Q3: Bazar | R3: AdvGiven | S3: Cash | T3: 2000
B4: 45865 | D4: 39500 | E4: Add | F4: SCB | H4: =TEXT(I4, "dddd") -> Saturday | I4: 45864 | J4: {=sum(IF(($P$3:$P$100=I4), $T$3:$T$100, 0))} -> 2100 | L4: {=INDIRECT("Account")} -> Cash | M4: {=N4 - sum(IF(($E$4:$E$49=L4), $D$4:$D$39 + $C$4:$C$39, 0)) + sum(IF(($F$4:$F$49=L4), $D$4:$D$39, 0)) - sum(IF(($S$3:$S$100=L4), $T$3:$T$100, 0))} -> 4145 | N4: ='July 25'!M4 -> 3725 | P4: 45864 | Q4: Donation | R4: Donation | S4: Cash | T4: 20
B5: 45866 | D5: 1000 | E5: SCB | F5: bKash | H5: =TEXT(I5, "dddd") -> Sunday | I5: 45865 | J5: {=sum(IF(($P$3:$P$100=I5), $T$3:$T$100, 0))} -> 700 | L5: SCB | M5: {=N5 - sum(IF(($E$4:$E$49=L5), $D$4:$D$39 + $C$4:$C$39, 0)) + sum(IF(($F$4:$F$49=L5), $D$4:$D$39, 0)) - sum(IF(($S$3:$S$100=L5), $T$3:$T$100, 0))} -> 16704 | N5: ='July 25'!M5 -> 57034 | P5: 45864 | Q5: ExtraExpenses | R5: Tea | S5: Cash | T5: 60 | U5: resort
B6: 45866 | C6: 15 | D6: 10000 | E6: SBL | F6: Cash | H6: =TEXT(I6, "dddd") -> Monday | I6: 45866 | J6: {=sum(IF(($P$3:$P$100=I6), $T$3:$T$100, 0))} -> 1630 | L6: SBL | M6: {=N6 - sum(IF(($E$4:$E$49=L6), $D$4:$D$39 + $C$4:$C$39, 0)) + sum(IF(($F$4:$F$49=L6), $D$4:$D$39, 0)) - sum(IF(($S$3:$S$100=L6), $T$3:$T$100, 0))} -> 30176 | N6: ='July 25'!M6 -> 30191 | P6: 45865 | Q6: Donation | R6: Donation | S6: Cash | T6: 700 | U6: due clear to santo
B7: 45866 | D7: 2000 | E7: Cash | F7: City | H7: =TEXT(I7, "dddd") -> Tuesday | I7: 45867 | J7: {=sum(IF(($P$3:$P$100=I7), $T$3:$T$100, 0))} -> 5000 | L7: EXIM | M7: {=N7 - sum(IF(($E$4:$E$49=L7), $D$4:$D$39 + $C$4:$C$39, 0)) + sum(IF(($F$4:$F$49=L7), $D$4:$D$39, 0)) - sum(IF(($S$3:$S$100=L7), $T$3:$T$100, 0))} -> 285 | N7: ='July 25'!M7 -> 285 | P7: 45866 | Q7: RentAndPaybill | R7: ElectricBill_Dhk | S7: bKash | T7: 800
B8: 45866 | D8: 10000 | E8: SCB | F8: SBL | H8: =TEXT(I8, "dddd") -> Wednesday | I8: 45868 | J8: {=sum(IF(($P$3:$P$100=I8), $T$3:$T$100, 0))} -> 1476 | L8: bKash | M8: {=N8 - sum(IF(($E$4:$E$49=L8), $D$4:$D$39 + $C$4:$C$39, 0)) + sum(IF(($F$4:$F$49=L8), $D$4:$D$39, 0)) - sum(IF(($S$3:$S$100=L8), $T$3:$T$100, 0))} -> 425 | N8: ='July 25'!M8 -> 77 | P8: 45866 | Q8: MobileInternet | R8: ForOthers | S8: bKash | T8: 50
B9: 45868 | D9: 1000 | E9: SCB | F9: bKash | H9: =TEXT(I9, "dddd") -> Thursday | I9: 45869 | J9: {=sum(IF(($P$3:$P$100=I9), $T$3:$T$100, 0))} -> 0 | L9: Nagad | M9: {=N9 - sum(IF(($E$4:$E$49=L9), $D$4:$D$39 + $C$4:$C$39, 0)) + sum(IF(($F$4:$F$49=L9), $D$4:$D$39, 0)) - sum(IF(($S$3:$S$100=L9), $T$3:$T$100, 0))} -> 2 | N9: ='July 25'!M9 -> 2 | P9: 45866 | Q9: Bazar | R9: Fruits | S9: Cash | T9: 150 | U9: amra+peyara
B10: 45870 | D10: 2500 | E10: SCB | F10: EXIM | H10: =TEXT(I10, "dddd") -> Friday | I10: 45870 | J10: {=sum(IF(($P$3:$P$100=I10), $T$3:$T$100, 0))} -> 4375 | L10: LendTaken | M10: =N10-10000 -> 130000 | N10: ='July 25'!M10 -> 140000 | P10: 45866 | Q10: ExtraExpenses | R10: ExtraExpenses | S10: bKash | T10: 30
B11: 45873 | D11: 25000 | E11: SCB | F11: City | H11: =TEXT(I11, "dddd") -> Saturday | I11: 45871 | J11: {=sum(IF(($P$3:$P$100=I11), $T$3:$T$100, 0))} -> 80 | L11: LendGiven | M11: {=N11 - sum(IF(($E$4:$E$49=L11), $D$4:$D$39 + $C$4:$C$39, 0)) + sum(IF(($F$4:$F$49=L11), $D$4:$D$39, 0)) - sum(IF(($S$3:$S$100=L11), $T$3:$T$100, 0))} -> 5500 | N11: ='July 25'!M11 -> 5500 | P11: 45867 | Q11: Bazar | R11: AdvGiven | S11: Cash | T11: 5000
B12: 45874 | C12: 0 | D12: 20000 | E12: City | F12: Cash | H12: =TEXT(I12, "dddd") -> Sunday | I12: 45872 | J12: {=sum(IF(($P$3:$P$100=I12), $T$3:$T$100, 0))} -> 0 | L12: City | M12: {=N12 - sum(IF(($E$4:$E$49=L12), $D$4:$D$39 + $C$4:$C$39, 0)) + sum(IF(($F$4:$F$49=L12), $D$4:$D$39, 0)) - sum(IF(($S$3:$S$100=L12), $T$3:$T$100, 0))} -> 1332 | N12: 0 | P12: 45866 | Q12: Bazar | R12: DailyBazar | S12: Cash | T12: 600 | U12: chingri
D13: 34330 | E13: SCB | F13: Pay | H13: =TEXT(I13, "dddd") -> Monday | I13: 45873 | J13: {=sum(IF(($P$3:$P$100=I13), $T$3:$T$100, 0))} -> 20 | P13: 45868 | Q13: ExtraExpenses | R13: ExtraExpenses | S13: Cash | T13: =10+20 -> 30
B14: 45886 | D14: 1000 | E14: SCB | F14: bKash | H14: =TEXT(I14, "dddd") -> Tuesday | I14: 45874 | J14: {=sum(IF(($P$3:$P$100=I14), $T$3:$T$100, 0))} -> 16110 | P14: 45868 | Q14: HouseholdAccessories | R14: DailyAccessories | S14: Cash | T14: 30
B15: 45890 | C15: 0 | D15: 2000 | E15: City | F15: Cash | H15: =TEXT(I15, "dddd") -> Wednesday | I15: 45875 | J15: {=sum(IF(($P$3:$P$100=I15), $T$3:$T$100, 0))} -> 320 | L15: LEND GIVEN TO | N15: =sum(N17:N22) -> 0 | P15: 45870 | Q15: Savings | R15: EximBank_2.5 | S15: EXIM | T15: 2500
B16: 45893 | D16: 5000 | E16: SCB | F16: City | H16: =TEXT(I16, "dddd") -> Thursday | I16: 45876 | J16: {=sum(IF(($P$3:$P$100=I16), $T$3:$T$100, 0))} -> 0 | L16: Date | M16: Given To | N16: Amount | P16: 45868 | Q16: Pay | R16: CityService | S16: City | T16: =173+690+345 -> 1208
B17: 45893 | C17: 0 | D17: 5000 | E17: City | F17: Cash | H17: =TEXT(I17, "dddd") -> Friday | I17: 45877 | J17: {=sum(IF(($P$3:$P$100=I17), $T$3:$T$100, 0))} -> 830 | L17: 45774 | M17: 2500 | N17: Rajib vai | P17: 45870 | Q17: Bazar | R17: DailyBazar | S17: Cash | T17: =1100+600+50 -> 1750 | U17: fish+duck
H18: =TEXT(I18, "dddd") -> Saturday | I18: 45878 | J18: {=sum(IF(($P$3:$P$100=I18), $T$3:$T$100, 0))} -> 3410 | M18: 3000 | N18: Rafi vai | P18: 45870 | Q18: Bazar | R18: Others | S18: Cash | T18: 60
H19: =TEXT(I19, "dddd") -> Sunday | I19: 45879 | J19: {=sum(IF(($P$3:$P$100=I19), $T$3:$T$100, 0))} -> 1035 | M19: 150 | N19: arafat vai | P19: 45870 | Q19: Donation | R19: Donation | S19: Cash | T19: 45
H20: =TEXT(I20, "dddd") -> Monday | I20: 45880 | J20: {=sum(IF(($P$3:$P$100=I20), $T$3:$T$100, 0))} -> 15 | P20: 45870 | Q20: ExtraExpenses | R20: Travel | S20: Cash | T20: 20
H21: =TEXT(I21, "dddd") -> Tuesday | I21: 45881 | J21: {=sum(IF(($P$3:$P$100=I21), $T$3:$T$100, 0))} -> 230 | P21: 45871 | Q21: Bazar | R21: Others | S21: Cash | T21: 80
H22: =TEXT(I22, "dddd") -> Wednesday | I22: 45882 | J22: {=sum(IF(($P$3:$P$100=I22), $T$3:$T$100, 0))} -> 115 | P22: 45873 | Q22: Bazar | R22: Others | S22: Cash | T22: 20
H23: =TEXT(I23, "dddd") -> Thursday | I23: 45883 | J23: {=sum(IF(($P$3:$P$100=I23), $T$3:$T$100, 0))} -> 10 | P23: 45874 | Q23: Bazar | R23: AdvGiven | S23: Cash | T23: 1000
H24: =TEXT(I24, "dddd") -> Friday | I24: 45884 | J24: {=sum(IF(($P$3:$P$100=I24), $T$3:$T$100, 0))} -> 40 | L24: LEND TAKEN FROM | N24: =sum(N26:N31) -> 0 | P24: 45874 | Q24: Bazar | R24: Others | S24: Cash | T24: =10+20 -> 30
H25: =TEXT(I25, "dddd") -> Saturday | I25: 45885 | J25: {=sum(IF(($P$3:$P$100=I25), $T$3:$T$100, 0))} -> 300 | L25: Date | M25: Taken From | N25: Amount | P25: 45874 | Q25: Bazar | R25: DailyBazar | S25: Cash | T25: 200 | U25: duck egg
H26: =TEXT(I26, "dddd") -> Sunday | I26: 45886 | J26: {=sum(IF(($P$3:$P$100=I26), $T$3:$T$100, 0))} -> 60 | P26: 45874 | Q26: RentAndPaybill | R26: HouseRent | S26: Cash | T26: 13000
H27: =TEXT(I27, "dddd") -> Monday | I27: 45887 | J27: {=sum(IF(($P$3:$P$100=I27), $T$3:$T$100, 0))} -> 160 | P27: 45874 | Q27: RentAndPaybill | R27: GassBill | S27: Cash | T27: 1080
H28: =TEXT(I28, "dddd") -> Tuesday | I28: 45888 | J28: {=sum(IF(($P$3:$P$100=I28), $T$3:$T$100, 0))} -> 65 | P28: 45874 | Q28: RentAndPaybill | R28: ServiceBill | S28: Cash | T28: 800
H29: =TEXT(I29, "dddd") -> Wednesday | I29: 45889 | J29: {=sum(IF(($P$3:$P$100=I29), $T$3:$T$100, 0))} -> 10 | P29: 45875 | Q29: Bazar | R29: Others | S29: Cash | T29: 200 | U29: ice-cream
H30: =TEXT(I30, "dddd") -> Thursday | I30: 45890 | J30: {=sum(IF(($P$3:$P$100=I30), $T$3:$T$100, 0))} -> 0 | P30: 45875 | Q30: Bazar | R30: AdvGiven | S30: Cash | T30: 120 | U30: rest of rent bill
H31: =TEXT(I31, "dddd") -> Friday | I31: 45891 | J31: {=sum(IF(($P$3:$P$100=I31), $T$3:$T$100, 0))} -> 2815 | P31: 45877 | Q31: ExtraExpenses | R31: Travel | S31: Cash | T31: =60+60+80+80 -> 280 | U31: go to park
H32: =TEXT(I32, "dddd") -> Saturday | I32: 45892 | J32: {=sum(IF(($P$3:$P$100=I32), $T$3:$T$100, 0))} -> 0 | P32: 45877 | Q32: ExtraExpenses | R32: ExtraExpenses | S32: Cash | T32: =100+100+50 -> 250 | U32: toy
H33: =TEXT(I33, "dddd") -> Sunday | I33: 45893 | J33: {=sum(IF(($P$3:$P$100=I33), $T$3:$T$100, 0))} -> 285 | N33: =sum(N35:N40) -> 0 | P33: 45877 | Q33: Bazar | R33: Others | S33: Cash | T33: 100 | U33: ice-cream
H34: =TEXT(I34, "dddd") -> Monday | I34: 45894 | J34: {=sum(IF(($P$3:$P$100=I34), $T$3:$T$100, 0))} -> 665 | P34: 45877 | Q34: Donation | R34: Donation | S34: Cash | T34: 200 | U34: poor people, near mosque
H35: =TEXT(I35, "dddd") -> Tuesday | I35: 45895 | J35: {=sum(IF(($P$3:$P$100=I35), $T$3:$T$100, 0))} -> 0 | P35: 45878 | Q35: ExtraExpenses | R35: ExtraExpenses | S35: City | T35: 2460 | U35: gpt plus
J36: {=sum(IF(($P$3:$P$100=I36), $T$3:$T$100, 0))} -> 0 | P36: 45878 | Q36: Bazar | R36: Others | S36: Cash | T36: 950 | U36: pizza
P37: 45879 | Q37: Bazar | R37: Others | S37: Cash | T37: 480 | U37: milk
P38: 45879 | Q38: HouseholdAccessories | R38: HouseholdAccessories | S38: Cash | T38: 130 | U38: vim
P39: 45879 | Q39: Bazar | R39: Fruits | S39: Cash | T39: 400 | U39: komla
P40: 45879 | Q40: ExtraExpenses | R40: Tea | S40: Cash | T40: 15
P41: 45879 | Q41: Donation | R41: Donation | S41: Cash | T41: 10
B42: B U D G E T | P42: 45880 | Q42: ExtraExpenses | R42: Tea | S42: Cash | T42: 15
P43: 45881 | Q43: Bazar | R43: Fruits | S43: Cash | T43: =150+65 -> 215 | U43: peyara +
B44: Category | E44: Budget | F44: Subcategory | I44: Budget | J44: Cost | L44: TGC | P44: 45881 | Q44: ExtraExpenses | R44: Tea | S44: Cash | T44: 15
B45: RentAndPaybill | E45: =Sum(I45:I50) -> 16970 | F45: {=INDIRECT("Subcategory")} -> HouseRent | I45: 13000 | J45: {=sum(IF(($R$3:$R$100=F45), $T$3:$T$100, 0))} -> 13000 | L45: =sum(J45:J50) -> 16906 | M45: =I45+I48+I50 -> 14880 | P45: 45882 | Q45: ExtraExpenses | R45: Tea | S45: Cash | T45: =15+20 -> 35
F46: ElectricBill_Dhk | I46: 800 | J46: {=sum(IF(($R$3:$R$100=F46), $T$3:$T$100, 0))} -> 800 | P46: 45882 | Q46: Bazar | R46: Others | S46: Cash | T46: 80
F47: ElectricBill_Swk | I47: 450 | J47: {=sum(IF(($R$3:$R$100=F47), $T$3:$T$100, 0))} -> 386 | P47: 45883 | Q47: ExtraExpenses | R47: Tea | S47: Cash | T47: 10
F48: GassBill | I48: 1080 | J48: {=sum(IF(($R$3:$R$100=F48), $T$3:$T$100, 0))} -> 1080 | P48: 45885 | Q48: ExtraExpenses | R48: ExtraExpenses | S48: Cash | T48: =200+50 -> 250 | U48: rubics cube
F49: WifiBill | I49: 840 | J49: {=sum(IF(($R$3:$R$100=F49), $T$3:$T$100, 0))} -> 840 | P49: 45885 | Q49: Bazar | R49: Fruits | S49: Cash | T49: 50
F50: ServiceBill | I50: =200+600 -> 800 | J50: {=sum(IF(($R$3:$R$100=F50), $T$3:$T$100, 0))} -> 800 | P50: 45886 | Q50: ExtraExpenses | R50: Travel | S50: Cash | T50: =30+30 -> 60
B51: Bazar | E51: =Sum(I51:I54) -> 10500 | F51: DailyBazar | I51: 3000 | J51: {=sum(IF(($R$3:$R$100=F51), $T$3:$T$100, 0))} -> 5120 | L51: =sum(J51:J54) -> 17268 | P51: 45884 | Q51: Bazar | R51: Others | S51: Cash | T51: 40
F52: Fruits | I52: 1000 | J52: {=sum(IF(($R$3:$R$100=F52), $T$3:$T$100, 0))} -> 1465 | P52: 45888 | Q52: ExtraExpenses | R52: Tea | S52: Cash | T52: 15
F53: AdvGiven | I53: 6000 | J53: {=sum(IF(($R$3:$R$100=F53), $T$3:$T$100, 0))} -> 8120 | P53: 45889 | Q53: ExtraExpenses | R53: ExtraExpenses | S53: Cash | T53: 10
F54: Others | I54: 500 | J54: {=sum(IF(($R$3:$R$100=F54), $T$3:$T$100, 0))} -> 2563 | P54: 45888 | Q54: HouseholdAccessories | R54: DailyAccessories | S54: Cash | T54: 50
B55: HouseholdAccessories | F55: HouseholdAccessories | I55: 300 | J55: {=sum(IF(($R$3:$R$100=F55), $T$3:$T$100, 0))} -> 130 | P55: 45887 | Q55: Bazar | R55: Others | S55: Cash | T55: =160 -> 160 | U55: ice-cream
F56: DailyAccessories | I56: 200 | J56: {=sum(IF(($R$3:$R$100=F56), $T$3:$T$100, 0))} -> 80 | P56: 45868 | Q56: MobileInternet | R56: ForOthers | S56: bKash | T56: 208
F57: Medicine | I57: 300 | J57: {=sum(IF(($R$3:$R$100=F57), $T$3:$T$100, 0))} -> 270 | P57: 45842 | Q57: MobileInternet | R57: ForMine | S57: bKash | T57: 30
B58: MobileInternet | F58: ForMine | I58: 100 | J58: {=sum(IF(($R$3:$R$100=F58), $T$3:$T$100, 0))} -> 80 | P58: 45855 | Q58: MobileInternet | R58: Others | S58: bKash | T58: =208+50 -> 258
F59: ForOthers | I59: 300 | J59: {=sum(IF(($R$3:$R$100=F59), $T$3:$T$100, 0))} -> 258 | P59: 45855 | Q59: RentAndPaybill | R59: WifiBill | S59: bKash | T59: 840
B60: ExtraExpenses | F60: Tea | I60: 200 | J60: {=sum(IF(($R$3:$R$100=F60), $T$3:$T$100, 0))} -> 195 | P60: 45856 | Q60: MobileInternet | R60: ForMine | S60: bKash | T60: 30
F61: Travel | I61: 300 | J61: {=sum(IF(($R$3:$R$100=F61), $T$3:$T$100, 0))} -> 400 | P61: 45859 | Q61: RentAndPaybill | R61: ElectricBill_Swk | S61: bKash | T61: 386
F62: AiSubs | I62: =500+2500 -> 3000 | J62: {=sum(IF(($R$3:$R$100=F62), $T$3:$T$100, 0))} -> 0 | P62: 45864 | Q62: MobileInternet | R62: ForMine | S62: bKash | T62: 20
B63: Savings | F63: BooksOrCourses | I63: 2500 | J63: {=sum(IF(($R$3:$R$100=F63), $T$3:$T$100, 0))} -> 0 | P63: 45891 | Q63: Bazar | R63: DailyBazar | S63: Cash | T63: =840+500+980+100+70+60+20 -> 2570 | U63: chingri+shing+fusfus++
F64: ExtraExpenses | J64: {=sum(IF(($R$3:$R$100=F64), $T$3:$T$100, 0))} -> 3030 | P64: 45891 | Q64: Donation | R64: Donation | S64: Cash | T64: =50+50 -> 100
B65: Donation | F65: EximBank_2.5 | I65: =330+500 -> 830 | J65: {=sum(IF(($R$3:$R$100=F65), $T$3:$T$100, 0))} -> 2500 | P65: 45891 | Q65: Bazar | R65: Others | S65: Cash | T65: =60+45 -> 105
F66: CityBank_10 | J66: {=sum(IF(($R$3:$R$100=F66), $T$3:$T$100, 0))} -> 0 | P66: 45891 | Q66: ExtraExpenses | R66: Travel | S66: Cash | T66: =20+20 -> 40
B67: Pay | F67: BracBank_10 | I67: 0 | J67: {=sum(IF(($R$3:$R$100=F67), $T$3:$T$100, 0))} -> 0 | P67: 45893 | Q67: ExtraExpenses | R67: Tea | S67: Cash | T67: 15
F68: SBL_root | I68: 0 | J68: {=sum(IF(($R$3:$R$100=F68), $T$3:$T$100, 0))} -> 0 | P68: 45893 | Q68: HouseholdAccessories | R68: Medicine | S68: Cash | T68: =150+120 -> 270
F69: Exim_root | P69: 45894 | Q69: ExtraExpenses | R69: Tea | S69: Cash | T69: 15
F70: Donation | H70: Total | I70: =SUM(I45:I68) -> 35500 | J70: =SUM(J45:J68) -> 41117 | L70: =I70-J70 -> -5617 | P70: 45894 | Q70: Bazar | R70: Fruits | S70: Cash | T70: =430+220 -> 650 | U70: ANAR + MANGO
F71: Unknown | H71: Non-Cash | I71: =I46+I47+I49+I58+I59+I63+I67+I68 -> 4990 | J71: =J46+J47+J49+J58+J59+J63+J67+J68 -> 2364 | L71: =I71-J71 -> 2626
F72: CityService | H72: Cash | I72: =I70-I71 -> 30510 | J72: =J70-J71 -> 38753 | L72: =I72-J72 -> -8243
F73: SblService

Sheet Sept 25
B2: T r a n s a c t i o n & P a y | H2: DAY | I2: Date | J2: =sum(J4:J39) -> 42574 | L2: FINANCIAL STATUS | N2: =M4+M5+M8+M9 -> 12889 | P2: Date | Q2: Category | R2: Subcategory | S2: Payment Method | T2: Amount | U2: Remarks
B3: Date | C3: Cost | D3: Amount | E3: FROM | F3: TO | J3: Cost | L3: Type | M3: Current Status | N3: Start with | P3: 45895 | Q3: ExtraExpenses | R3: Travel | S3: Cash | T3: =10+50+30 -> 90
B4: 45895 | D4: 39500 | E4: Add | F4: SCB | H4: =TEXT(I4, "dddd") -> Tuesday | I4: 45895 | J4: {=sum(IF(($P$3:$P$100=I4), $T$3:$T$100, 0))} -> 1020 | L4: {=INDIRECT("Account")} -> Cash | M4: {=N4 - sum(IF(($E$4:$E$49=L4), $D$4:$D$39 + $C$4:$C$39, 0)) + sum(IF(($F$4:$F$49=L4), $D$4:$D$39, 0)) - sum(IF(($S$3:$S$100=L4), $T$3:$T$100, 0))} -> 1835 | N4: ='Aug 25'!M4 -> 4145 | P4: 45895 | Q4: Bazar | R4: Fruits | S4: Cash | T4: 130
B5: 45895 | D5: 1667 | E5: Add | F5: SCB | H5: =TEXT(I5, "dddd") -> Wednesday | I5: 45896 | J5: {=sum(IF(($P$3:$P$100=I5), $T$3:$T$100, 0))} -> 15 | L5: SCB | M5: {=N5 - sum(IF(($E$4:$E$49=L5), $D$4:$D$39 + $C$4:$C$39, 0)) + sum(IF(($F$4:$F$49=L5), $D$4:$D$39, 0)) - sum(IF(($S$3:$S$100=L5), $T$3:$T$100, 0))} -> 10371 | N5: ='Aug 25'!M5 -> 16704 | P5: 45896 | Q5: ExtraExpenses | R5: Tea | S5: Cash | T5: 15
B6: 45900 | D6: 30000 | E6: SCB | F6: City | H6: =TEXT(I6, "dddd") -> Thursday | I6: 45897 | J6: {=sum(IF(($P$3:$P$100=I6), $T$3:$T$100, 0))} -> 0 | L6: SBL | M6: {=N6 - sum(IF(($E$4:$E$49=L6), $D$4:$D$39 + $C$4:$C$39, 0)) + sum(IF(($F$4:$F$49=L6), $D$4:$D$39, 0)) - sum(IF(($S$3:$S$100=L6), $T$3:$T$100, 0))} -> 30176 | N6: ='Aug 25'!M6 -> 30176 | P6: 45895 | Q6: RentAndPaybill | R6: ElectricBill_Dhk | S6: City | T6: 800 | U6: given on 21 Aug
B7: 45902 | D7: 1000 | E7: SCB | F7: bKash | H7: =TEXT(I7, "dddd") -> Friday | I7: 45898 | J7: {=sum(IF(($P$3:$P$100=I7), $T$3:$T$100, 0))} -> 0 | L7: EXIM | M7: {=N7 - sum(IF(($E$4:$E$49=L7), $D$4:$D$39 + $C$4:$C$39, 0)) + sum(IF(($F$4:$F$49=L7), $D$4:$D$39, 0)) - sum(IF(($S$3:$S$100=L7), $T$3:$T$100, 0))} -> 285 | N7: ='Aug 25'!M7 -> 285 | P7: 45900 | Q7: Bazar | R7: Others | S7: Cash | T7: =225+75+20 -> 320 | U7: misti+chokolet+chips
B8: 45900 | D8: 20000 | E8: City | F8: Cash | H8: =TEXT(I8, "dddd") -> Saturday | I8: 45899 | J8: {=sum(IF(($P$3:$P$100=I8), $T$3:$T$100, 0))} -> 275 | L8: bKash | M8: {=N8 - sum(IF(($E$4:$E$49=L8), $D$4:$D$39 + $C$4:$C$39, 0)) + sum(IF(($F$4:$F$49=L8), $D$4:$D$39, 0)) - sum(IF(($S$3:$S$100=L8), $T$3:$T$100, 0))} -> 681 | N8: ='Aug 25'!M8 -> 425 | P8: 45869 | Q8: ExtraExpenses | R8: Travel | S8: Cash | T8: 250 | U8: travel
B9: 45908 | D9: 10000 | E9: City | F9: Cash | H9: =TEXT(I9, "dddd") -> Sunday | I9: 45900 | J9: {=sum(IF(($P$3:$P$100=I9), $T$3:$T$100, 0))} -> 320 | L9: Nagad | M9: {=N9 - sum(IF(($E$4:$E$49=L9), $D$4:$D$39 + $C$4:$C$39, 0)) + sum(IF(($F$4:$F$49=L9), $D$4:$D$39, 0)) - sum(IF(($S$3:$S$100=L9), $T$3:$T$100, 0))} -> 2 | N9: ='Aug 25'!M9 -> 2 | P9: 45901 | Q9: HouseholdAccessories | R9: HouseholdAccessories | S9: Cash | T9: =700+30 -> 730 | U9: plate+bati+brush
B10: 45911 | D10: 4000 | E10: SCB | F10: City | H10: =TEXT(I10, "dddd") -> Monday | I10: 45901 | J10: {=sum(IF(($P$3:$P$100=I10), $T$3:$T$100, 0))} -> 7850 | L10: LendTaken | M10: =N10-10000 -> 120000 | N10: ='Aug 25'!M10 -> 130000 | P10: 45902 | Q10: ExtraExpenses | R10: Tea | S10: Cash | T10: 15
B11: 45917 | D11: 1000 | E11: City | F11: bKash | H11: =TEXT(I11, "dddd") -> Tuesday | I11: 45902 | J11: {=sum(IF(($P$3:$P$100=I11), $T$3:$T$100, 0))} -> 1165 | L11: LendGiven | M11: {=N11 - sum(IF(($E$4:$E$49=L11), $D$4:$D$39 + $C$4:$C$39, 0)) + sum(IF(($F$4:$F$49=L11), $D$4:$D$39, 0)) - sum(IF(($S$3:$S$100=L11), $T$3:$T$100, 0))} -> 5500 | N11: ='Aug 25'!M11 -> 5500 | P11: 45902 | Q11: ExtraExpenses | R11: Travel | S11: Cash | T11: =100+60 -> 160 | U11: travel
B12: 45923 | D12: 1000 | E12: City | F12: bKash | H12: =TEXT(I12, "dddd") -> Wednesday | I12: 45903 | J12: {=sum(IF(($P$3:$P$100=I12), $T$3:$T$100, 0))} -> 0 | L12: City | M12: {=N12 - sum(IF(($E$4:$E$49=L12), $D$4:$D$39 + $C$4:$C$39, 0)) + sum(IF(($F$4:$F$49=L12), $D$4:$D$39, 0)) - sum(IF(($S$3:$S$100=L12), $T$3:$T$100, 0))} -> 8062 | N12: ='Aug 25'!M12 -> 1332 | P12: 45902 | Q12: ExtraExpenses | R12: Travel | S12: bKash | T12: 710 | U12: travel
B13: 45923 | D13: 10000 | E13: SCB | F13: City | H13: =TEXT(I13, "dddd") -> Thursday | I13: 45904 | J13: {=sum(IF(($P$3:$P$100=I13), $T$3:$T$100, 0))} -> 2810 | P13: 45902 | Q13: HouseholdAccessories | R13: Medicine | S13: Cash | T13: 60
B14: 45923 | D14: 2000 | E14: City | F14: Cash | H14: =TEXT(I14, "dddd") -> Friday | I14: 45905 | J14: {=sum(IF(($P$3:$P$100=I14), $T$3:$T$100, 0))} -> 60 | P14: 45902 | Q14: Bazar | R14: Others | S14: Cash | T14: 200 | U14: ice-cream
H15: =TEXT(I15, "dddd") -> Saturday | I15: 45906 | J15: {=sum(IF(($P$3:$P$100=I15), $T$3:$T$100, 0))} -> 2230 | L15: LEND GIVEN TO | N15: =sum(N17:N22) -> 0 | P15: 45902 | Q15: HouseholdAccessories | R15: DailyAccessories | S15: Cash | T15: 20
H16: =TEXT(I16, "dddd") -> Sunday | I16: 45907 | J16: {=sum(IF(($P$3:$P$100=I16), $T$3:$T$100, 0))} -> 115 | L16: Date | M16: Given To | N16: Amount | P16: 45904 | Q16: Bazar | R16: Others | S16: Cash | T16: 680 | U16: misti
H17: =TEXT(I17, "dddd") -> Monday | I17: 45908 | J17: {=sum(IF(($P$3:$P$100=I17), $T$3:$T$100, 0))} -> 995 | L17: 45774 | M17: 2500 | N17: Rajib vai | P17: 45904 | Q17: ExtraExpenses | R17: ExtraExpenses | S17: Cash | T17: 350 | U17: gari toy
H18: =TEXT(I18, "dddd") -> Tuesday | I18: 45909 | J18: {=sum(IF(($P$3:$P$100=I18), $T$3:$T$100, 0))} -> 3865 | M18: 3000 | N18: Rafi vai | P18: 45904 | Q18: Bazar | R18: DailyBazar | S18: Cash | T18: =550+430 -> 980 | U18: mach + murgi
H19: =TEXT(I19, "dddd") -> Wednesday | I19: 45910 | J19: {=sum(IF(($P$3:$P$100=I19), $T$3:$T$100, 0))} -> 14895 | P19: 45904 | Q19: Bazar | R19: Fruits | S19: Cash | T19: 300 | U19: komla
H20: =TEXT(I20, "dddd") -> Thursday | I20: 45911 | J20: {=sum(IF(($P$3:$P$100=I20), $T$3:$T$100, 0))} -> 2565 | P20: 45904 | Q20: RentAndPaybill | R20: ElectricBill_Dhk | S20: Cash | T20: 500 | U20: due 500
H21: =TEXT(I21, "dddd") -> Friday | I21: 45912 | J21: {=sum(IF(($P$3:$P$100=I21), $T$3:$T$100, 0))} -> 0 | P21: 45905 | Q21: Donation | R21: Donation | S21: Cash | T21: 20
H22: =TEXT(I22, "dddd") -> Saturday | I22: 45913 | J22: {=sum(IF(($P$3:$P$100=I22), $T$3:$T$100, 0))} -> 0 | P22: 45905 | Q22: ExtraExpenses | R22: Travel | S22: Cash | T22: 40
H23: =TEXT(I23, "dddd") -> Sunday | I23: 45914 | J23: {=sum(IF(($P$3:$P$100=I23), $T$3:$T$100, 0))} -> 745 | P23: 45906 | Q23: HouseholdAccessories | R23: Medicine | S23: Cash | T23: 750 | U23: medi
H24: =TEXT(I24, "dddd") -> Monday | I24: 45915 | J24: {=sum(IF(($P$3:$P$100=I24), $T$3:$T$100, 0))} -> 1015 | L24: LEND TAKEN FROM | N24: =sum(N26:N31) -> 0 | P24: 45906 | Q24: Bazar | R24: Others | S24: Cash | T24: 100 | U24: juich
H25: =TEXT(I25, "dddd") -> Tuesday | I25: 45916 | J25: {=sum(IF(($P$3:$P$100=I25), $T$3:$T$100, 0))} -> 0 | L25: Date | M25: Taken From | N25: Amount | P25: 45906 | Q25: Bazar | R25: DailyBazar | S25: Cash | T25: =1300+20 -> 1320 | U25: pati-hash
H26: =TEXT(I26, "dddd") -> Wednesday | I26: 45917 | J26: {=sum(IF(($P$3:$P$100=I26), $T$3:$T$100, 0))} -> 840 | P26: 45906 | Q26: Bazar | R26: Fruits | S26: Cash | T26: 60
H27: =TEXT(I27, "dddd") -> Thursday | I27: 45918 | J27: {=sum(IF(($P$3:$P$100=I27), $T$3:$T$100, 0))} -> 0 | P27: 45907 | Q27: ExtraExpenses | R27: Tea | S27: Cash | T27: 15
H28: =TEXT(I28, "dddd") -> Friday | I28: 45919 | J28: {=sum(IF(($P$3:$P$100=I28), $T$3:$T$100, 0))} -> 0 | P28: 45907 | Q28: Bazar | R28: Fruits | S28: Cash | T28: 70
H29: =TEXT(I29, "dddd") -> Saturday | I29: 45920 | J29: {=sum(IF(($P$3:$P$100=I29), $T$3:$T$100, 0))} -> 500 | P29: 45907 | Q29: Bazar | R29: DailyBazar | S29: Cash | T29: 30
H30: =TEXT(I30, "dddd") -> Sunday | I30: 45921 | J30: {=sum(IF(($P$3:$P$100=I30), $T$3:$T$100, 0))} -> 438 | P30: 45908 | Q30: ExtraExpenses | R30: Tea | S30: Cash | T30: 15
H31: =TEXT(I31, "dddd") -> Monday | I31: 45922 | J31: {=sum(IF(($P$3:$P$100=I31), $T$3:$T$100, 0))} -> 0 | P31: 45908 | Q31: HouseholdAccessories | R31: DailyAccessories | S31: Cash | T31: =350+130 -> 480 | U31: pest + goodnight refill
H32: =TEXT(I32, "dddd") -> Tuesday | I32: 45923 | J32: {=sum(IF(($P$3:$P$100=I32), $T$3:$T$100, 0))} -> 826 | P32: 45908 | Q32: HouseholdAccessories | R32: Medicine | S32: Cash | T32: 500 | U32: med
H33: =TEXT(I33, "dddd") -> Wednesday | I33: 45924 | J33: {=sum(IF(($P$3:$P$100=I33), $T$3:$T$100, 0))} -> 0 | N33: =sum(N35:N40) -> 0 | P33: 45909 | Q33: ExtraExpenses | R33: Travel | S33: Cash | T33: =700+200 -> 900 | U33: travel
H34: =TEXT(I34, "dddd") -> Thursday | I34: 45925 | J34: {=sum(IF(($P$3:$P$100=I34), $T$3:$T$100, 0))} -> 30 | P34: 45910 | Q34: RentAndPaybill | R34: HouseRent | S34: Cash | T34: 13000
H35: =TEXT(I35, "dddd") -> Friday | I35: 45926 | J35: {=sum(IF(($P$3:$P$100=I35), $T$3:$T$100, 0))} -> 0 | P35: 45910 | Q35: RentAndPaybill | R35: GassBill | S35: Cash | T35: 1080
J36: {=sum(IF(($P$3:$P$100=I36), $T$3:$T$100, 0))} -> 0 | P36: 45910 | Q36: RentAndPaybill | R36: ServiceBill | S36: Cash | T36: 800
P37: 45901 | Q37: Bazar | R37: AdvGiven | S37: Cash | T37: =5000+120+2000 -> 7120
P38: 45899 | Q38: MobileInternet | R38: ForOthers | S38: bKash | T38: =275 -> 275
P39: 45909 | Q39: MobileInternet | R39: ForMine | S39: bKash | T39: =30+30+30+30 -> 120
P40: 45909 | Q40: Donation | R40: Unknown | S40: Cash | T40: 345 | U40: U n k n o w n
P41: 45909 | Q41: Savings | R41: EximBank_2.5 | S41: SCB | T41: 2500
B42: B U D G E T | P42: 45910 | Q42: ExtraExpenses | R42: Tea | S42: Cash | T42: 15
P43: 45911 | Q43: ExtraExpenses | R43: Tea | S43: Cash | T43: 15
B44: Category | E44: Budget | F44: Subcategory | I44: Budget | J44: Cost | L44: TGC | P44: 45911 | Q44: HouseholdAccessories | R44: DailyAccessories | S44: Cash | T44: 60
B45: RentAndPaybill | E45: =Sum(I45:I50) -> 16970 | F45: {=INDIRECT("Subcategory")} -> HouseRent | I45: 13000 | J45: {=sum(IF(($R$3:$R$100=F45), $T$3:$T$100, 0))} -> 13000 | L45: =sum(J45:J50) -> 17461 | M45: =I45+I48+I50 -> 14880 | P45: 45911 | Q45: Bazar | R45: Others | S45: Cash | T45: 20
F46: ElectricBill_Dhk | I46: 800 | J46: {=sum(IF(($R$3:$R$100=F46), $T$3:$T$100, 0))} -> 1300 | P46: 45911 | Q46: ExtraExpenses | R46: ExtraExpenses | S46: City | T46: 2470
F47: ElectricBill_Swk | I47: 450 | J47: {=sum(IF(($R$3:$R$100=F47), $T$3:$T$100, 0))} -> 441 | P47: 45914 | Q47: ExtraExpenses | R47: Tea | S47: Cash | T47: 15
F48: GassBill | I48: 1080 | J48: {=sum(IF(($R$3:$R$100=F48), $T$3:$T$100, 0))} -> 1080 | P48: 45914 | Q48: HouseholdAccessories | R48: HouseholdAccessories | S48: Cash | T48: 150
F49: WifiBill | I49: 840 | J49: {=sum(IF(($R$3:$R$100=F49), $T$3:$T$100, 0))} -> 840 | P49: 45914 | Q49: HouseholdAccessories | R49: DailyAccessories | S49: Cash | T49: 180
F50: ServiceBill | I50: =200+600 -> 800 | J50: {=sum(IF(($R$3:$R$100=F50), $T$3:$T$100, 0))} -> 800 | P50: 45914 | Q50: ExtraExpenses | R50: Medicine | S50: Cash | T50: 400
B51: Bazar | E51: =Sum(I51:I54) -> 12000 | F51: DailyBazar | I51: 3000 | J51: {=sum(IF(($R$3:$R$100=F51), $T$3:$T$100, 0))} -> 2330 | L51: =sum(J51:J54) -> 12920 | P51: 45915 | Q51: ExtraExpenses | R51: Tea | S51: Cash | T51: 15
F52: Fruits | I52: 1000 | J52: {=sum(IF(($R$3:$R$100=F52), $T$3:$T$100, 0))} -> 650 | P52: 45915 | Q52: Bazar | R52: AdvGiven | S52: Cash | T52: 1000
F53: AdvGiven | I53: 6000 | J53: {=sum(IF(($R$3:$R$100=F53), $T$3:$T$100, 0))} -> 8620 | P53: 45917 | Q53: RentAndPaybill | R53: WifiBill | S53: bKash | T53: 840
F54: Others | I54: 2000 | J54: {=sum(IF(($R$3:$R$100=F54), $T$3:$T$100, 0))} -> 1320 | P54: 45920 | Q54: Bazar | R54: AdvGiven | S54: Cash | T54: 500
B55: HouseholdAccessories | E55: =sum(I55:I57) -> 5200 | F55: HouseholdAccessories | I55: 100 | J55: {=sum(IF(($R$3:$R$100=F55), $T$3:$T$100, 0))} -> 880 | L55: =sum(J55:J58) -> 3620 | P55: 45921 | Q55: ExtraExpenses | R55: Travel | S55: Cash | T55: =30+50 -> 80
F56: DailyAccessories | I56: 100 | J56: {=sum(IF(($R$3:$R$100=F56), $T$3:$T$100, 0))} -> 740 | P56: 45923 | Q56: ExtraExpenses | R56: Tea | S56: Cash | T56: =15*5+10+40 -> 125
F57: Medicine | I57: 5000 | J57: {=sum(IF(($R$3:$R$100=F57), $T$3:$T$100, 0))} -> 1880 | P57: 45923 | Q57: Bazar | R57: Fruits | S57: Cash | T57: 90
B58: MobileInternet | E58: =I58+I59 -> 400 | F58: ForMine | I58: 100 | J58: {=sum(IF(($R$3:$R$100=F58), $T$3:$T$100, 0))} -> 120 | P58: 45923 | Q58: ExtraExpenses | R58: Medicine | S58: Cash | T58: =100+70 -> 170
F59: ForOthers | I59: 300 | J59: {=sum(IF(($R$3:$R$100=F59), $T$3:$T$100, 0))} -> 633 | P59: 45921 | Q59: MobileInternet | R59: ForOthers | S59: bKash | T59: =208+50+100 -> 358
B60: ExtraExpenses | F60: Tea | I60: 200 | J60: {=sum(IF(($R$3:$R$100=F60), $T$3:$T$100, 0))} -> 275 | P60: 45923 | Q60: RentAndPaybill | R60: ElectricBill_Swk | S60: bKash | T60: 441
F61: Travel | I61: 300 | J61: {=sum(IF(($R$3:$R$100=F61), $T$3:$T$100, 0))} -> 2230 | P61: 45925 | Q61: ExtraExpenses | R61: Tea | S61: Cash | T61: =15+15 -> 30
F62: AiSubs | I62: 100 | J62: {=sum(IF(($R$3:$R$100=F62), $T$3:$T$100, 0))} -> 0
B63: Savings | F63: BooksOrCourses | I63: 2500 | J63: {=sum(IF(($R$3:$R$100=F63), $T$3:$T$100, 0))} -> 0
F64: ExtraExpenses | I64: 0 | J64: {=sum(IF(($R$3:$R$100=F64), $T$3:$T$100, 0))} -> 2820
B65: Donation | F65: EximBank_2.5 | I65: 30 | J65: {=sum(IF(($R$3:$R$100=F65), $T$3:$T$100, 0))} -> 2500
F66: CityBank_10 | I66: 0 | J66: {=sum(IF(($R$3:$R$100=F66), $T$3:$T$100, 0))} -> 0
B67: Pay | F67: BracBank_10 | I67: 0 | J67: {=sum(IF(($R$3:$R$100=F67), $T$3:$T$100, 0))} -> 0
F68: SBL_root | I68: 0 | J68: {=sum(IF(($R$3:$R$100=F68), $T$3:$T$100, 0))} -> 0
F69: Exim_root
F70: Donation | H70: Total | I70: =SUM(I45:I68) -> 37700 | J70: =SUM(J45:J68) -> 42459 | L70: =I70-J70 -> -4759
F71: Unknown | H71: Non-Cash | I71: =I46+I47+I49+I58+I59+I63+I67+I68 -> 4990 | J71: =J46+J47+J49+J58+J59+J63+J67+J68 -> 3334 | L71: =I71-J71 -> 1656
F72: CityService | H72: Cash | I72: =I70-I71 -> 32710 | J72: =J70-J71 -> 39125 | L72: =I72-J72 -> -6415
F73: SblService

Sheet Oct 25
B2: T r a n s a c t i o n & P a y | H2: DAY | I2: Date | J2: =sum(J4:J39) -> 73823 | L2: FINANCIAL STATUS | N2: =M4+M5+M8+M9+M12 -> 35047 | P2: Date | Q2: Category | R2: Subcategory | S2: Payment Method | T2: Amount | U2: Remarks
B3: Date | C3: Cost | D3: Amount | E3: FROM | F3: TO | J3: Cost | L3: Type | M3: Current Status | N3: Start with | P3: 45926 | Q3: Donation | R3: Donation | S3: Cash | T3: 10
B4: 45925 | D4: 37834 | E4: Add | F4: SCB | H4: =TEXT(I4, "dddd") -> Friday | I4: 45926 | J4: {=sum(IF(($P$3:$P$100=I4), $T$3:$T$100, 0))} -> 795 | L4: {=INDIRECT("Account")} -> Cash | M4: {=N4 - sum(IF(($E$4:$E$49=L4), $D$4:$D$39 + $C$4:$C$39, 0)) + sum(IF(($F$4:$F$49=L4), $D$4:$D$39, 0)) - sum(IF(($S$3:$S$100=L4), $T$3:$T$100, 0))} -> 17250 | N4: ='Sept 25'!M4 -> 1835 | P4: 45926 | Q4: HouseholdAccessories | R4: DailyAccessories | S4: Cash | T4: 85
B5: 45925 | D5: 15000 | E5: Add | F5: SCB | H5: =TEXT(I5, "dddd") -> Saturday | I5: 45927 | J5: {=sum(IF(($P$3:$P$100=I5), $T$3:$T$100, 0))} -> 7860 | L5: SCB | M5: {=N5 - sum(IF(($E$4:$E$49=L5), $D$4:$D$39 + $C$4:$C$39, 0)) + sum(IF(($F$4:$F$49=L5), $D$4:$D$39, 0)) - sum(IF(($S$3:$S$100=L5), $T$3:$T$100, 0))} -> 435 | N5: ='Sept 25'!M5 -> 10371 | P5: 45926 | Q5: Bazar | R5: AdvGiven | S5: Cash | T5: =500+200 -> 700
B6: 45927 | C6: 15 | D6: 10000 | E6: SCB | F6: Cash | H6: =TEXT(I6, "dddd") -> Sunday | I6: 45928 | J6: {=sum(IF(($P$3:$P$100=I6), $T$3:$T$100, 0))} -> 360 | L6: SBL | M6: {=N6 - sum(IF(($E$4:$E$49=L6), $D$4:$D$39 + $C$4:$C$39, 0)) + sum(IF(($F$4:$F$49=L6), $D$4:$D$39, 0)) - sum(IF(($S$3:$S$100=L6), $T$3:$T$100, 0))} -> 156 | N6: ='Sept 25'!M6 -> 30176 | P6: 45927 | Q6: Bazar | R6: AdvGiven | S6: Cash | T6: 5000
B7: 45931 | C7: 15 | D7: 10000 | E7: SCB | F7: Cash | H7: =TEXT(I7, "dddd") -> Monday | I7: 45929 | J7: {=sum(IF(($P$3:$P$100=I7), $T$3:$T$100, 0))} -> 0 | L7: EXIM | M7: {=N7 - sum(IF(($E$4:$E$49=L7), $D$4:$D$39 + $C$4:$C$39, 0)) + sum(IF(($F$4:$F$49=L7), $D$4:$D$39, 0)) - sum(IF(($S$3:$S$100=L7), $T$3:$T$100, 0))} -> 285 | N7: ='Sept 25'!M7 -> 285 | P7: 45927 | Q7: ExtraExpenses | R7: Medicine | S7: Cash | T7: =500+300+1990 -> 2790 | U7: dental for ammu
B8: 45927 | D8: 30000 | E8: SCB | F8: City | H8: =TEXT(I8, "dddd") -> Tuesday | I8: 45930 | J8: {=sum(IF(($P$3:$P$100=I8), $T$3:$T$100, 0))} -> 0 | L8: bKash | M8: {=N8 - sum(IF(($E$4:$E$49=L8), $D$4:$D$39 + $C$4:$C$39, 0)) + sum(IF(($F$4:$F$49=L8), $D$4:$D$39, 0)) - sum(IF(($S$3:$S$100=L8), $T$3:$T$100, 0))} -> 218 | N8: ='Sept 25'!M8 -> 681 | P8: 45927 | Q8: Bazar | R8: Fruits | S8: Cash | T8: 70
B9: 45935 | D9: 20000 | E9: City | F9: Cash | H9: =TEXT(I9, "dddd") -> Wednesday | I9: 45931 | J9: {=sum(IF(($P$3:$P$100=I9), $T$3:$T$100, 0))} -> 510 | L9: Nagad | M9: {=N9 - sum(IF(($E$4:$E$49=L9), $D$4:$D$39 + $C$4:$C$39, 0)) + sum(IF(($F$4:$F$49=L9), $D$4:$D$39, 0)) - sum(IF(($S$3:$S$100=L9), $T$3:$T$100, 0))} -> 2 | N9: ='Sept 25'!M9 -> 2 | P9: 45928 | Q9: Bazar | R9: Others | S9: Cash | T9: 360 | U9: ice cream
B10: 45936 | D10: 40 | E10: Add | F10: bKash | H10: =TEXT(I10, "dddd") -> Thursday | I10: 45932 | J10: {=sum(IF(($P$3:$P$100=I10), $T$3:$T$100, 0))} -> 0 | L10: LendTaken | M10: =N10-10000 -> 110000 | N10: ='Sept 25'!M10 -> 120000 | P10: 45931 | Q10: Bazar | R10: DailyBazar | S10: Cash | T10: 200 | U10: tel
B11: 45945 | C11: 20 | D11: 30000 | E11: SBL | F11: SCB | H11: =TEXT(I11, "dddd") -> Friday | I11: 45933 | J11: {=sum(IF(($P$3:$P$100=I11), $T$3:$T$100, 0))} -> 4230 | L11: LendGiven | M11: {=N11 - sum(IF(($E$4:$E$49=L11), $D$4:$D$39 + $C$4:$C$39, 0)) + sum(IF(($F$4:$F$49=L11), $D$4:$D$39, 0)) - sum(IF(($S$3:$S$100=L11), $T$3:$T$100, 0))} -> 5500 | N11: ='Sept 25'!M11 -> 5500 | P11: 45931 | Q11: Bazar | R11: Fruits | S11: Cash | T11: =100+80 -> 180 | U11: kola+amra
B12: 45945 | D12: 12000 | E12: SCB | F12: Cash | H12: =TEXT(I12, "dddd") -> Saturday | I12: 45934 | J12: {=sum(IF(($P$3:$P$100=I12), $T$3:$T$100, 0))} -> 0 | L12: City | M12: {=N12 - sum(IF(($E$4:$E$49=L12), $D$4:$D$39 + $C$4:$C$39, 0)) + sum(IF(($F$4:$F$49=L12), $D$4:$D$39, 0)) - sum(IF(($S$3:$S$100=L12), $T$3:$T$100, 0))} -> 17142 | N12: ='Sept 25'!M12 -> 8062 | P12: 45931 | Q12: Bazar | R12: Others | S12: Cash | T12: =30 -> 30
B13: 45948 | D13: 1500 | E13: City | F13: bKash | H13: =TEXT(I13, "dddd") -> Sunday | I13: 45935 | J13: {=sum(IF(($P$3:$P$100=I13), $T$3:$T$100, 0))} -> 15614 | P13: 45931 | Q13: Bazar | R13: Others | S13: Cash | T13: 100
B14: 45942 | D14: 50 | E14: Add | F14: City | H14: =TEXT(I14, "dddd") -> Monday | I14: 45936 | J14: {=sum(IF(($P$3:$P$100=I14), $T$3:$T$100, 0))} -> 170 | P14: 45933 | Q14: ExtraExpenses | R14: ExtraExpenses | S14: Cash | T14: =2300 -> 2300 | U14: 3pc for ammu
B15: 45948 | D15: 25 | E15: Add | F15: bKash | H15: =TEXT(I15, "dddd") -> Tuesday | I15: 45937 | J15: {=sum(IF(($P$3:$P$100=I15), $T$3:$T$100, 0))} -> 15 | L15: LEND GIVEN TO | N15: =sum(N17:N22) -> 0 | P15: 45933 | Q15: Bazar | R15: Others | S15: Cash | T15: =40+20 -> 60
B16: 45949 | D16: 5000 | E16: Add | F16: Cash | H16: =TEXT(I16, "dddd") -> Wednesday | I16: 45938 | J16: {=sum(IF(($P$3:$P$100=I16), $T$3:$T$100, 0))} -> 150 | L16: Date | M16: Given To | N16: Amount | P16: 45933 | Q16: Bazar | R16: Others | S16: Cash | T16: 570 | U16: misti
B17: 45954 | D17: 4000 | E17: SCB | F17: City | H17: =TEXT(I17, "dddd") -> Thursday | I17: 45939 | J17: {=sum(IF(($P$3:$P$100=I17), $T$3:$T$100, 0))} -> 2500 | L17: 45774 | M17: 2500 | N17: Rajib vai | P17: 45933 | Q17: Bazar | R17: DailyBazar | S17: Cash | T17: =380+700+100 -> 1180 | U17: fish+alu
H18: =TEXT(I18, "dddd") -> Friday | I18: 45940 | J18: {=sum(IF(($P$3:$P$100=I18), $T$3:$T$100, 0))} -> 2830 | M18: 3000 | N18: Rafi vai | P18: 45933 | Q18: Bazar | R18: Fruits | S18: Cash | T18: 100 | U18: malta
H19: =TEXT(I19, "dddd") -> Saturday | I19: 45941 | J19: {=sum(IF(($P$3:$P$100=I19), $T$3:$T$100, 0))} -> 2500 | P19: 45933 | Q19: Donation | R19: Donation | S19: Cash | T19: 20
H20: =TEXT(I20, "dddd") -> Sunday | I20: 45942 | J20: {=sum(IF(($P$3:$P$100=I20), $T$3:$T$100, 0))} -> 6090 | P20: 45935 | Q20: RentAndPaybill | R20: HouseRent | S20: Cash | T20: 13000
H21: =TEXT(I21, "dddd") -> Monday | I21: 45943 | J21: {=sum(IF(($P$3:$P$100=I21), $T$3:$T$100, 0))} -> 0 | P21: 45935 | Q21: RentAndPaybill | R21: GassBill | S21: Cash | T21: 1080
H22: =TEXT(I22, "dddd") -> Tuesday | I22: 45944 | J22: {=sum(IF(($P$3:$P$100=I22), $T$3:$T$100, 0))} -> 45 | P22: 45935 | Q22: RentAndPaybill | R22: ServiceBill | S22: Cash | T22: 800
H23: =TEXT(I23, "dddd") -> Wednesday | I23: 45945 | J23: {=sum(IF(($P$3:$P$100=I23), $T$3:$T$100, 0))} -> 24440 | P23: 45935 | Q23: Bazar | R23: AdvGiven | S23: Cash | T23: 120
H24: =TEXT(I24, "dddd") -> Thursday | I24: 45946 | J24: {=sum(IF(($P$3:$P$100=I24), $T$3:$T$100, 0))} -> 330 | L24: LEND TAKEN FROM | N24: =sum(N26:N31) -> 0 | P24: 45935 | Q24: ExtraExpenses | R24: Tea | S24: Cash | T24: 15
H25: =TEXT(I25, "dddd") -> Friday | I25: 45947 | J25: {=sum(IF(($P$3:$P$100=I25), $T$3:$T$100, 0))} -> 50 | L25: Date | M25: Taken From | N25: Amount | P25: 45935 | Q25: Bazar | R25: Fruits | S25: Cash | T25: =130+50 -> 180
H26: =TEXT(I26, "dddd") -> Saturday | I26: 45948 | J26: {=sum(IF(($P$3:$P$100=I26), $T$3:$T$100, 0))} -> 3819 | P26: 45936 | Q26: HouseholdAccessories | R26: DailyAccessories | S26: Cash | T26: =130+40 -> 170
H27: =TEXT(I27, "dddd") -> Sunday | I27: 45949 | J27: {=sum(IF(($P$3:$P$100=I27), $T$3:$T$100, 0))} -> 1515 | P27: 45937 | Q27: ExtraExpenses | R27: Tea | S27: Cash | T27: 15
H28: =TEXT(I28, "dddd") -> Monday | I28: 45950 | J28: {=sum(IF(($P$3:$P$100=I28), $T$3:$T$100, 0))} -> 0 | P28: 45938 | Q28: Bazar | R28: Fruits | S28: Cash | T28: =100+50 -> 150
H29: =TEXT(I29, "dddd") -> Tuesday | I29: 45951 | J29: {=sum(IF(($P$3:$P$100=I29), $T$3:$T$100, 0))} -> 0 | P29: 45939 | Q29: ExtraExpenses | R29: Tea | S29: Cash | T29: =15+15 -> 30
H30: =TEXT(I30, "dddd") -> Wednesday | I30: 45952 | J30: {=sum(IF(($P$3:$P$100=I30), $T$3:$T$100, 0))} -> 0 | P30: 45940 | Q30: ExtraExpenses | R30: ExtraExpenses | S30: Cash | T30: =600+1100 -> 1700
H31: =TEXT(I31, "dddd") -> Thursday | I31: 45953 | J31: {=sum(IF(($P$3:$P$100=I31), $T$3:$T$100, 0))} -> 0 | P31: 45940 | Q31: ExtraExpenses | R31: Travel | S31: Cash | T31: 30
H32: =TEXT(I32, "dddd") -> Friday | I32: 45954 | J32: {=sum(IF(($P$3:$P$100=I32), $T$3:$T$100, 0))} -> 0 | P32: 45940 | Q32: HouseholdAccessories | R32: DailyAccessories | S32: Cash | T32: =70+10 -> 80
H33: =TEXT(I33, "dddd") -> Saturday | I33: 45955 | J33: {=sum(IF(($P$3:$P$100=I33), $T$3:$T$100, 0))} -> 0 | N33: =sum(N35:N40) -> 0 | P33: 45940 | Q33: Donation | R33: Donation | S33: Cash | T33: 20
H34: =TEXT(I34, "dddd") -> Sunday | I34: 45956 | J34: {=sum(IF(($P$3:$P$100=I34), $T$3:$T$100, 0))} -> 0 | P34: 45940 | Q34: RentAndPaybill | R34: ElectricBill_Dhk | S34: City | T34: 1000
H35: =TEXT(I35, "dddd") -> Monday | I35: 45957 | J35: {=sum(IF(($P$3:$P$100=I35), $T$3:$T$100, 0))} -> 0 | P35: 45939 | Q35: ExtraExpenses | R35: ExtraExpenses | S35: City | T35: 2470
J36: {=sum(IF(($P$3:$P$100=I36), $T$3:$T$100, 0))} -> 0 | P36: 45935 | Q36: MobileInternet | R36: ForOthers | S36: bKash | T36: =50+319 -> 369
P37: 45935 | Q37: MobileInternet | R37: ForMine | S37: bKash | T37: 50
P38: 45941 | Q38: Savings | R38: EximBank_2.5 | S38: SCB | T38: 2500
P39: 45942 | Q39: Bazar | R39: DailyBazar | S39: Cash | T39: =2100+2000+370+730 -> 5200
P40: 45942 | Q40: Bazar | R40: Fruits | S40: Cash | T40: 500
P41: 45942 | Q41: ExtraExpenses | R41: Travel | S41: Cash | T41: 30
B42: B U D G E T | P42: 45944 | Q42: ExtraExpenses | R42: Tea | S42: Cash | T42: =15*3 -> 45
P43: 45942 | Q43: HouseholdAccessories | R43: HouseholdAccessories | S43: Cash | T43: 360
B44: Category | E44: Budget | F44: Subcategory | I44: Budget | J44: Cost | L44: TGC | P44: 45945 | Q44: ExtraExpenses | R44: Travel | S44: Cash | T44: =180+60-40 -> 200 | U44: to scb
B45: RentAndPaybill | E45: =Sum(I45:I50) -> 17170 | F45: {=INDIRECT("Subcategory")} -> HouseRent | I45: 13000 | J45: {=sum(IF(($R$3:$R$100=F45), $T$3:$T$100, 0))} -> 13000 | L45: =sum(J45:J50) -> 17189 | M45: =I45+I48+I50 -> 14880 | P45: 45946 | Q45: ExtraExpenses | R45: Tea | S45: Cash | T45: =15+15 -> 30
F46: ElectricBill_Dhk | I46: 1000 | J46: {=sum(IF(($R$3:$R$100=F46), $T$3:$T$100, 0))} -> 1000 | P46: 45947 | Q46: ExtraExpenses | R46: Travel | S46: Cash | T46: 50
F47: ElectricBill_Swk | I47: 450 | J47: {=sum(IF(($R$3:$R$100=F47), $T$3:$T$100, 0))} -> 469 | P47: 45948 | Q47: HouseholdAccessories | R47: HouseholdAccessories | S47: Cash | T47: =540+700+250+80+90 -> 1660
F48: GassBill | I48: 1080 | J48: {=sum(IF(($R$3:$R$100=F48), $T$3:$T$100, 0))} -> 1080 | P48: 45948 | Q48: Bazar | R48: DailyBazar | S48: Cash | T48: =580+200+40 -> 820
F49: WifiBill | I49: 840 | J49: {=sum(IF(($R$3:$R$100=F49), $T$3:$T$100, 0))} -> 840 | P49: 45948 | Q49: Bazar | R49: Others | S49: Cash | T49: 30
F50: ServiceBill | I50: =200+600 -> 800 | J50: {=sum(IF(($R$3:$R$100=F50), $T$3:$T$100, 0))} -> 800 | P50: 45949 | Q50: ExtraExpenses | R50: Tea | S50: Cash | T50: 15
B51: Bazar | E51: =Sum(I51:I54) -> 12000 | F51: DailyBazar | I51: 2000 | J51: {=sum(IF(($R$3:$R$100=F51), $T$3:$T$100, 0))} -> 7400 | L51: =sum(J51:J54) -> 15550 | P51: 45949 | Q51: ExtraExpenses | R51: Medicine | S51: Cash | T51: =240+170 -> 410
F52: Fruits | I52: 1000 | J52: {=sum(IF(($R$3:$R$100=F52), $T$3:$T$100, 0))} -> 1180 | P52: 45949 | Q52: HouseholdAccessories | R52: DailyAccessories | S52: Cash | T52: =70+110 -> 180
F53: AdvGiven | I53: 8000 | J53: {=sum(IF(($R$3:$R$100=F53), $T$3:$T$100, 0))} -> 5820 | P53: 45945 | Q53: ExtraExpenses | R53: ExtraExpenses | S53: SCB | T53: =24545-305 -> 24240
F54: Others | I54: 1000 | J54: {=sum(IF(($R$3:$R$100=F54), $T$3:$T$100, 0))} -> 1150 | P54: 45946 | Q54: Donation | R54: Donation | S54: bKash | T54: 300
B55: HouseholdAccessories | E55: =sum(I55:I57) -> 3400 | F55: HouseholdAccessories | I55: 200 | J55: {=sum(IF(($R$3:$R$100=F55), $T$3:$T$100, 0))} -> 2020 | L55: =sum(J55:J58) -> 5785 | P55: 45948 | Q55: RentAndPaybill | R55: WifiBill | S55: bKash | T55: 840
F56: DailyAccessories | I56: 200 | J56: {=sum(IF(($R$3:$R$100=F56), $T$3:$T$100, 0))} -> 515 | P56: 45948 | Q56: RentAndPaybill | R56: ElectricBill_Swk | S56: bKash | T56: 469
F57: Medicine | I57: 3000 | J57: {=sum(IF(($R$3:$R$100=F57), $T$3:$T$100, 0))} -> 3200 | P57: 45949 | Q57: Donation | R57: Unknown | S57: Cash | T57: 910
B58: MobileInternet | E58: =I58+I59 -> 400 | F58: ForMine | I58: 100 | J58: {=sum(IF(($R$3:$R$100=F58), $T$3:$T$100, 0))} -> 50
F59: ForOthers | I59: 300 | J59: {=sum(IF(($R$3:$R$100=F59), $T$3:$T$100, 0))} -> 369
B60: ExtraExpenses | F60: Tea | I60: 200 | J60: {=sum(IF(($R$3:$R$100=F60), $T$3:$T$100, 0))} -> 150
F61: Travel | I61: 1000 | J61: {=sum(IF(($R$3:$R$100=F61), $T$3:$T$100, 0))} -> 310
F62: AiSubs | I62: =5000+25000 -> 30000 | J62: {=sum(IF(($R$3:$R$100=F62), $T$3:$T$100, 0))} -> 0
B63: Savings | F63: BooksOrCourses | I63: 2500 | J63: {=sum(IF(($R$3:$R$100=F63), $T$3:$T$100, 0))} -> 0
F64: ExtraExpenses | I64: 0 | J64: {=sum(IF(($R$3:$R$100=F64), $T$3:$T$100, 0))} -> 30710
B65: Donation | F65: EximBank_2.5 | I65: 30 | J65: {=sum(IF(($R$3:$R$100=F65), $T$3:$T$100, 0))} -> 2500
F66: CityBank_10 | I66: 0 | J66: {=sum(IF(($R$3:$R$100=F66), $T$3:$T$100, 0))} -> 0
B67: Pay | F67: BracBank_10 | I67: 0 | J67: {=sum(IF(($R$3:$R$100=F67), $T$3:$T$100, 0))} -> 0
F68: SBL_root | I68: 0 | J68: {=sum(IF(($R$3:$R$100=F68), $T$3:$T$100, 0))} -> 0
F69: Exim_root
F70: Donation | H70: Total | I70: =SUM(I45:I68) -> 66700 | J70: =SUM(J45:J68) -> 72563 | L70: =I70-J70 -> -5863
F71: Unknown | H71: Non-Cash | I71: =I46+I47+I49+I58+I59+I63+I67+I68 -> 5190 | J71: =J46+J47+J49+J58+J59+J63+J67+J68 -> 2728 | L71: =I71-J71 -> 2462
F72: CityService | H72: Cash | I72: =I70-I71 -> 61510 | J72: =J70-J71 -> 69835 | L72: =I72-J72 -> -8325
F73: SblService

Sheet Nov 25
B2: T r a n s a c t i o n & P a y | H2: DAY | I2: Date | J2: =sum(J4:J39) -> 46366 | L2: FINANCIAL STATUS | N2: =M4+M5+M8+M9+M12 -> 2370 | P2: Date | Q2: Category | R2: Subcategory | S2: Payment Method | T2: Amount | U2: Remarks
B3: Date | C3: Cost | D3: Amount | E3: FROM | F3: TO | J3: Cost | L3: Type | M3: Current Status | N3: Start with | P3: 45967 | Q3: Bazar | R3: DailyBazar | S3: Cash | T3: =100+140 -> 240 | U3: dim
B4: 45956 | D4: 39500 | E4: Add | F4: SCB | H4: =TEXT(I4, "dddd") -> Sunday | I4: 45956 | J4: {=sum(IF(($P$3:$P$100=I4), $T$3:$T$100, 0))} -> 0 | L4: {=INDIRECT("Account")} -> Cash | M4: {=N4 - sum(IF(($E$4:$E$49=L4), $D$4:$D$39 + $C$4:$C$39, 0)) + sum(IF(($F$4:$F$49=L4), $D$4:$D$39, 0)) - sum(IF(($S$3:$S$100=L4), $T$3:$T$100, 0))} -> 20 | N4: ='Oct 25'!M4 -> 17250 | P4: 45966 | Q4: Bazar | R4: Others | S4: Cash | T4: =400+440 -> 840 | U4: cake + chokolet
B5: 45956 | D5: 1667 | E5: Add | F5: SCB | H5: =TEXT(I5, "dddd") -> Monday | I5: 45957 | J5: {=sum(IF(($P$3:$P$100=I5), $T$3:$T$100, 0))} -> 0 | L5: SCB | M5: {=N5 - sum(IF(($E$4:$E$49=L5), $D$4:$D$39 + $C$4:$C$39, 0)) + sum(IF(($F$4:$F$49=L5), $D$4:$D$39, 0)) - sum(IF(($S$3:$S$100=L5), $T$3:$T$100, 0))} -> 1477 | N5: ='Oct 25'!M5 -> 435 | P5: 45967 | Q5: ExtraExpenses | R5: Tea | S5: Cash | T5: =15*3 -> 45
B6: 45963 | D6: 1000 | E6: City | F6: bKash | H6: =TEXT(I6, "dddd") -> Tuesday | I6: 45958 | J6: {=sum(IF(($P$3:$P$100=I6), $T$3:$T$100, 0))} -> 0 | L6: SBL | M6: {=N6 - sum(IF(($E$4:$E$49=L6), $D$4:$D$39 + $C$4:$C$39, 0)) + sum(IF(($F$4:$F$49=L6), $D$4:$D$39, 0)) - sum(IF(($S$3:$S$100=L6), $T$3:$T$100, 0))} -> 17156 | N6: ='Oct 25'!M6 -> 156 | P6: 45963 | Q6: Bazar | R6: AdvGiven | S6: Cash | T6: =2000+200 -> 2200
B7: 45963 | D7: 117 | E7: Add | F7: City | H7: =TEXT(I7, "dddd") -> Wednesday | I7: 45959 | J7: {=sum(IF(($P$3:$P$100=I7), $T$3:$T$100, 0))} -> 0 | L7: EXIM | M7: {=N7 - sum(IF(($E$4:$E$49=L7), $D$4:$D$39 + $C$4:$C$39, 0)) + sum(IF(($F$4:$F$49=L7), $D$4:$D$39, 0)) - sum(IF(($S$3:$S$100=L7), $T$3:$T$100, 0))} -> 285 | N7: ='Oct 25'!M7 -> 285 | P7: 45966 | Q7: MobileInternet | R7: ForMine | S7: bKash | T7: 265
B8: 45963 | D8: 9800 | E8: Cash | H8: =TEXT(I8, "dddd") -> Thursday | I8: 45960 | J8: {=sum(IF(($P$3:$P$100=I8), $T$3:$T$100, 0))} -> 0 | L8: bKash | M8: {=N8 - sum(IF(($E$4:$E$49=L8), $D$4:$D$39 + $C$4:$C$39, 0)) + sum(IF(($F$4:$F$49=L8), $D$4:$D$39, 0)) - sum(IF(($S$3:$S$100=L8), $T$3:$T$100, 0))} -> 532 | N8: ='Oct 25'!M8 -> 218 | P8: 45965 | Q8: MobileInternet | R8: ForOthers | S8: bKash | T8: =208-25 -> 183 | U8: 25 cash back
B9: 45967 | D9: 1205 | E9: Add | F9: SCB | H9: =TEXT(I9, "dddd") -> Friday | I9: 45961 | J9: {=sum(IF(($P$3:$P$100=I9), $T$3:$T$100, 0))} -> 0 | L9: Nagad | M9: {=N9 - sum(IF(($E$4:$E$49=L9), $D$4:$D$39 + $C$4:$C$39, 0)) + sum(IF(($F$4:$F$49=L9), $D$4:$D$39, 0)) - sum(IF(($S$3:$S$100=L9), $T$3:$T$100, 0))} -> 2 | N9: ='Oct 25'!M9 -> 2 | P9: 45963 | Q9: ExtraExpenses | R9: Travel | S9: bKash | T9: 665 | U9: 5 charge
B10: 45968 | D10: 10000 | E10: SCB | F10: City | H10: =TEXT(I10, "dddd") -> Saturday | I10: 45962 | J10: {=sum(IF(($P$3:$P$100=I10), $T$3:$T$100, 0))} -> 105 | L10: LendTaken | M10: =N10-10000 -> 100000 | N10: ='Oct 25'!M10 -> 110000 | P10: 45962 | Q10: MobileInternet | R10: ForMine | S10: bKash | T10: =30+75 -> 105 | U10: prev month - adjustment
B11: 45968 | D11: 20000 | E11: City | F11: Cash | H11: =TEXT(I11, "dddd") -> Sunday | I11: 45963 | J11: {=sum(IF(($P$3:$P$100=I11), $T$3:$T$100, 0))} -> 2865 | L11: LendGiven | M11: {=N11 - sum(IF(($E$4:$E$49=L11), $D$4:$D$39 + $C$4:$C$39, 0)) + sum(IF(($F$4:$F$49=L11), $D$4:$D$39, 0)) - sum(IF(($S$3:$S$100=L11), $T$3:$T$100, 0))} -> 7550 | N11: ='Oct 25'!M11 -> 5500 | P11: 45965 | Q11: ExtraExpenses | R11: ExtraExpenses | S11: SCB | T11: 9450 | U11: nepal tour due pay
B12: 45969 | D12: 1000 | E12: City | F12: bKash | H12: =TEXT(I12, "dddd") -> Monday | I12: 45964 | J12: {=sum(IF(($P$3:$P$100=I12), $T$3:$T$100, 0))} -> 1000 | L12: City | M12: {=N12 - sum(IF(($E$4:$E$49=L12), $D$4:$D$39 + $C$4:$C$39, 0)) + sum(IF(($F$4:$F$49=L12), $D$4:$D$39, 0)) - sum(IF(($S$3:$S$100=L12), $T$3:$T$100, 0))} -> 339 | N12: ='Oct 25'!M12 -> 17142 | P12: 45964 | Q12: RentAndPaybill | R12: ElectricBill_Dhk | S12: City | T12: 1000
B13: 45969 | D13: 50 | E13: Add | F13: City | H13: =TEXT(I13, "dddd") -> Tuesday | I13: 45965 | J13: {=sum(IF(($P$3:$P$100=I13), $T$3:$T$100, 0))} -> 9633 | P13: 45968 | Q13: HouseholdAccessories | R13: HouseholdAccessories | S13: Cash | T13: =490+425 -> 915 | U13: water bottle + water drum
B14: 45975 | D14: 20000 | E14: SCB | F14: SBL | H14: =TEXT(I14, "dddd") -> Wednesday | I14: 45966 | J14: {=sum(IF(($P$3:$P$100=I14), $T$3:$T$100, 0))} -> 1105 | P14: 45968 | Q14: Bazar | R14: Others | S14: Cash | T14: =695+50+80+15 -> 840 | U14: chokolet + soft drinks
B15: 45978 | D15: 1500 | E15: City | F15: Cash | H15: =TEXT(I15, "dddd") -> Thursday | I15: 45967 | J15: {=sum(IF(($P$3:$P$100=I15), $T$3:$T$100, 0))} -> 285 | L15: LEND GIVEN TO | N15: =sum(N17:N22) -> 0 | P15: 45969 | Q15: RentAndPaybill | R15: HouseRent | S15: Cash | T15: 13000
B16: 45979 | D16: 3000 | E16: SBL | F16: bKash | H16: =TEXT(I16, "dddd") -> Friday | I16: 45968 | J16: {=sum(IF(($P$3:$P$100=I16), $T$3:$T$100, 0))} -> 1755 | L16: Date | M16: Given To | N16: Amount | P16: 45969 | Q16: RentAndPaybill | R16: GassBill | S16: Cash | T16: 1080
B17: 45979 | D17: 2050 | E17: bKash | F17: LendGiven | H17: =TEXT(I17, "dddd") -> Saturday | I17: 45969 | J17: {=sum(IF(($P$3:$P$100=I17), $T$3:$T$100, 0))} -> 20530 | L17: 45774 | M17: 2500 | N17: Rajib vai | P17: 45969 | Q17: RentAndPaybill | R17: ServiceBill | S17: Cash | T17: 700
B18: 45984 | D18: 1000 | E18: Cash | F18: SCB | H18: =TEXT(I18, "dddd") -> Sunday | I18: 45970 | J18: {=sum(IF(($P$3:$P$100=I18), $T$3:$T$100, 0))} -> 0 | M18: 3000 | N18: Rafi vai | P18: 45969 | Q18: Bazar | R18: AdvGiven | S18: Cash | T18: =3000+220 -> 3220
H19: =TEXT(I19, "dddd") -> Monday | I19: 45971 | J19: {=sum(IF(($P$3:$P$100=I19), $T$3:$T$100, 0))} -> 0 | L19: 45979 | M19: 2050 | N19: Jahid | P19: 45969 | Q19: Savings | R19: EximBank_2.5 | S19: SCB | T19: 2500
H20: =TEXT(I20, "dddd") -> Tuesday | I20: 45972 | J20: {=sum(IF(($P$3:$P$100=I20), $T$3:$T$100, 0))} -> 30 | P20: 45972 | Q20: ExtraExpenses | R20: Tea | S20: Cash | T20: =15+15 -> 30
H21: =TEXT(I21, "dddd") -> Wednesday | I21: 45973 | J21: {=sum(IF(($P$3:$P$100=I21), $T$3:$T$100, 0))} -> 0 | P21: 45969 | Q21: MobileInternet | R21: ForMine | S21: bKash | T21: 30
H22: =TEXT(I22, "dddd") -> Thursday | I22: 45974 | J22: {=sum(IF(($P$3:$P$100=I22), $T$3:$T$100, 0))} -> 2785 | P22: 45974 | Q22: ExtraExpenses | R22: Medicine | S22: Cash | T22: 300 | U22: given to ammu
H23: =TEXT(I23, "dddd") -> Friday | I23: 45975 | J23: {=sum(IF(($P$3:$P$100=I23), $T$3:$T$100, 0))} -> 3995 | P23: 45974 | Q23: ExtraExpenses | R23: Tea | S23: Cash | T23: 15
H24: =TEXT(I24, "dddd") -> Saturday | I24: 45976 | J24: {=sum(IF(($P$3:$P$100=I24), $T$3:$T$100, 0))} -> 0 | L24: LEND TAKEN FROM | N24: =sum(N26:N31) -> 0 | P24: 45974 | Q24: ExtraExpenses | R24: ExtraExpenses | S24: City | T24: 2470 | U24: claude
H25: =TEXT(I25, "dddd") -> Sunday | I25: 45977 | J25: {=sum(IF(($P$3:$P$100=I25), $T$3:$T$100, 0))} -> 0 | L25: Date | M25: Taken From | N25: Amount | P25: 45975 | Q25: Bazar | R25: DailyBazar | S25: Cash | T25: =1300+490+700+400+900+25 -> 3815 | U25: FISH
H26: =TEXT(I26, "dddd") -> Monday | I26: 45978 | J26: {=sum(IF(($P$3:$P$100=I26), $T$3:$T$100, 0))} -> 1160 | P26: 45975 | Q26: ExtraExpenses | R26: Travel | S26: Cash | T26: 60
H27: =TEXT(I27, "dddd") -> Tuesday | I27: 45979 | J27: {=sum(IF(($P$3:$P$100=I27), $T$3:$T$100, 0))} -> 298 | P27: 45975 | Q27: Bazar | R27: Others | S27: Cash | T27: 50
H28: =TEXT(I28, "dddd") -> Wednesday | I28: 45980 | J28: {=sum(IF(($P$3:$P$100=I28), $T$3:$T$100, 0))} -> 40 | P28: 45975 | Q28: ExtraExpenses | R28: Medicine | S28: Cash | T28: 20
H29: =TEXT(I29, "dddd") -> Thursday | I29: 45981 | J29: {=sum(IF(($P$3:$P$100=I29), $T$3:$T$100, 0))} -> 50 | P29: 45978 | Q29: HouseholdAccessories | R29: DailyAccessories | S29: Cash | T29: =200 -> 200
H30: =TEXT(I30, "dddd") -> Friday | I30: 45982 | J30: {=sum(IF(($P$3:$P$100=I30), $T$3:$T$100, 0))} -> 30 | P30: 45978 | Q30: ExtraExpenses | R30: Medicine | S30: Cash | T30: 100
H31: =TEXT(I31, "dddd") -> Saturday | I31: 45983 | J31: {=sum(IF(($P$3:$P$100=I31), $T$3:$T$100, 0))} -> 200 | P31: 45978 | Q31: ExtraExpenses | R31: Tea | S31: Cash | T31: 20
H32: =TEXT(I32, "dddd") -> Sunday | I32: 45984 | J32: {=sum(IF(($P$3:$P$100=I32), $T$3:$T$100, 0))} -> 380 | P32: 45979 | Q32: RentAndPaybill | R32: ElectricBill_Swk | S32: bKash | T32: 298
H33: =TEXT(I33, "dddd") -> Monday | I33: 45985 | J33: {=sum(IF(($P$3:$P$100=I33), $T$3:$T$100, 0))} -> 120 | L33: Savings | N33: =sum(N35:N40) -> 0 | P33: 45978 | Q33: RentAndPaybill | R33: WifiBill | S33: bKash | T33: 840
H34: =TEXT(I34, "dddd") -> Tuesday | I34: 45986 | J34: {=sum(IF(($P$3:$P$100=I34), $T$3:$T$100, 0))} -> 0 | L34: Type | M34: Current | N34: Prev | P34: 45980 | Q34: Bazar | R34: Others | S34: Cash | T34: 40
H35: =TEXT(I35, "dddd") -> Wednesday | I35: 45987 | J35: {=sum(IF(($P$3:$P$100=I35), $T$3:$T$100, 0))} -> 0 | P35: 45981 | Q35: ExtraExpenses | R35: Tea | S35: Cash | T35: =15+15 -> 30
J36: {=sum(IF(($P$3:$P$100=I36), $T$3:$T$100, 0))} -> 0 | P36: 45981 | Q36: Bazar | R36: Others | S36: Cash | T36: 20
P37: 45982 | Q37: Donation | R37: Donation | S37: Cash | T37: 30
P38: 45975 | Q38: MobileInternet | R38: ForOthers | S38: bKash | T38: 50
P39: 45984 | Q39: HouseholdAccessories | R39: DailyAccessories | S39: SCB | T39: 380
P40: 45985 | Q40: Bazar | R40: Others | S40: Cash | T40: =70+20 -> 90
P41: 45985 | Q41: ExtraExpenses | R41: Tea | S41: Cash | T41: =15*2 -> 30
B42: B U D G E T | P42: 45983 | Q42: MobileInternet | R42: ForOthers | S42: bKash | T42: 200
B44: Category | E44: Budget | F44: Subcategory | I44: Budget | J44: Cost | L44: TGC
B45: RentAndPaybill | E45: =Sum(I45:I50) -> 17070 | F45: {=INDIRECT("Subcategory")} -> HouseRent | I45: 13000 | J45: {=sum(IF(($R$3:$R$100=F45), $T$3:$T$100, 0))} -> 13000 | L45: =sum(J45:J50) -> 16918 | M45: =I45+I48+I50 -> 14780
F46: ElectricBill_Dhk | I46: 1000 | J46: {=sum(IF(($R$3:$R$100=F46), $T$3:$T$100, 0))} -> 1000
F47: ElectricBill_Swk | I47: 450 | J47: {=sum(IF(($R$3:$R$100=F47), $T$3:$T$100, 0))} -> 298
F48: GassBill | I48: 1080 | J48: {=sum(IF(($R$3:$R$100=F48), $T$3:$T$100, 0))} -> 1080
F49: WifiBill | I49: 840 | J49: {=sum(IF(($R$3:$R$100=F49), $T$3:$T$100, 0))} -> 840
F50: ServiceBill | I50: =100+600 -> 700 | J50: {=sum(IF(($R$3:$R$100=F50), $T$3:$T$100, 0))} -> 700
B51: Bazar | E51: =Sum(I51:I54) -> 6000 | F51: DailyBazar | I51: 1000 | J51: {=sum(IF(($R$3:$R$100=F51), $T$3:$T$100, 0))} -> 4055 | L51: =sum(J51:J54) -> 11355
F52: Fruits | I52: 500 | J52: {=sum(IF(($R$3:$R$100=F52), $T$3:$T$100, 0))} -> 0
F53: AdvGiven | I53: 3000 | J53: {=sum(IF(($R$3:$R$100=F53), $T$3:$T$100, 0))} -> 5420
F54: Others | I54: 1500 | J54: {=sum(IF(($R$3:$R$100=F54), $T$3:$T$100, 0))} -> 1880
B55: HouseholdAccessories | E55: =sum(I55:I57) -> 500 | F55: HouseholdAccessories | I55: 200 | J55: {=sum(IF(($R$3:$R$100=F55), $T$3:$T$100, 0))} -> 915 | L55: =sum(J55:J58) -> 2315
F56: DailyAccessories | I56: 200 | J56: {=sum(IF(($R$3:$R$100=F56), $T$3:$T$100, 0))} -> 580
F57: Medicine | I57: 100 | J57: {=sum(IF(($R$3:$R$100=F57), $T$3:$T$100, 0))} -> 420
B58: MobileInternet | E58: =I58+I59 -> 300 | F58: ForMine | I58: 100 | J58: {=sum(IF(($R$3:$R$100=F58), $T$3:$T$100, 0))} -> 400
F59: ForOthers | I59: 200 | J59: {=sum(IF(($R$3:$R$100=F59), $T$3:$T$100, 0))} -> 433
B60: ExtraExpenses | F60: Tea | I60: 200 | J60: {=sum(IF(($R$3:$R$100=F60), $T$3:$T$100, 0))} -> 170
F61: Travel | I61: 800 | J61: {=sum(IF(($R$3:$R$100=F61), $T$3:$T$100, 0))} -> 725
F62: AiSubs | I62: =10000+2500 -> 12500 | J62: {=sum(IF(($R$3:$R$100=F62), $T$3:$T$100, 0))} -> 0
B63: Savings | F63: BooksOrCourses | I63: 2500 | J63: {=sum(IF(($R$3:$R$100=F63), $T$3:$T$100, 0))} -> 0
F64: ExtraExpenses | I64: 0 | J64: {=sum(IF(($R$3:$R$100=F64), $T$3:$T$100, 0))} -> 11920
B65: Donation | F65: EximBank_2.5 | I65: 0 | J65: {=sum(IF(($R$3:$R$100=F65), $T$3:$T$100, 0))} -> 2500
F66: CityBank_10 | I66: 0 | J66: {=sum(IF(($R$3:$R$100=F66), $T$3:$T$100, 0))} -> 0
B67: Pay | F67: BracBank_10 | I67: 0 | J67: {=sum(IF(($R$3:$R$100=F67), $T$3:$T$100, 0))} -> 0
F68: SBL_root | I68: 0 | J68: {=sum(IF(($R$3:$R$100=F68), $T$3:$T$100, 0))} -> 0
F69: Exim_root
F70: Donation | H70: Total | I70: =SUM(I45:I68) -> 39870 | J70: =SUM(J45:J68) -> 46336 | L70: =I70-J70 -> -6466
F71: Unknown | H71: Non-Cash | I71: =I46+I47+I49+I58+I59+I63+I67+I68+I62 -> 17590 | J71: =J46+J47+J49+J58+J59+J63+J67+J68+J62 -> 2971 | L71: =I71-J71 -> 14619
F72: CityService | H72: Cash | I72: =I70-I71 -> 22280 | J72: =J70-J71 -> 43365 | L72: =I72-J72 -> -21085
F73: SblService
D81: nov | E81: 20000 | F81: 20
D82: dec | E82: 5000 | F82: 25
D83: jan | E83: 15000 | F83: 40
D84: feb | E84: 10000 | F84: 50

Sheet Dec 25
B2: T r a n s a c t i o n & P a y | H2: DAY | I2: Date | J2: =sum(J4:J39) -> 7530 | L2: FINANCIAL STATUS | N2: =M4+M5+M8+M9+M12 -> 4693 | P2: Date | Q2: Category | R2: Subcategory | S2: Payment Method | T2: Amount | U2: Remarks
B3: Date | C3: Cost | D3: Amount | E3: FROM | F3: TO | J3: Cost | L3: Type | M3: Current Status | N3: Start with | P3: 45990 | Q3: Bazar | R3: DailyBazar | S3: SCB | T3: 745
B4: 45986 | D4: 39500 | E4: Add | F4: SCB | H4: =TEXT(I4, "dddd") -> Sunday | I4: 45956 | J4: {=sum(IF(($P$3:$P$100=I4), $T$3:$T$100, 0))} -> 0 | L4: {=INDIRECT("Account")} -> Cash | M4: {=N4 - sum(IF(($E$4:$E$49=L4), $D$4:$D$39 + $C$4:$C$39, 0)) + sum(IF(($F$4:$F$49=L4), $D$4:$D$39, 0)) - sum(IF(($S$3:$S$100=L4), $T$3:$T$100, 0))} -> 3000 | N4: ='Nov 25'!M4 -> 20 | P4: 45987 | Q4: ExtraExpenses | R4: ExtraExpenses | S4: City | T4: 2480
B5: 45987 | D5: 20000 | E5: SCB | F5: City | H5: =TEXT(I5, "dddd") -> Monday | I5: 45957 | J5: {=sum(IF(($P$3:$P$100=I5), $T$3:$T$100, 0))} -> 0 | L5: SCB | M5: {=N5 - sum(IF(($E$4:$E$49=L5), $D$4:$D$39 + $C$4:$C$39, 0)) + sum(IF(($F$4:$F$49=L5), $D$4:$D$39, 0)) - sum(IF(($S$3:$S$100=L5), $T$3:$T$100, 0))} -> 1432 | N5: ='Nov 25'!M5 -> 1477 | P5: 45987 | Q5: HouseholdAccessories | R5: Medicine | S5: Cash | T5: 5000
B6: 45987 | D6: 0 | E6: SCB | H6: =TEXT(I6, "dddd") -> Tuesday | I6: 45958 | J6: {=sum(IF(($P$3:$P$100=I6), $T$3:$T$100, 0))} -> 0 | L6: SBL | M6: {=N6 - sum(IF(($E$4:$E$49=L6), $D$4:$D$39 + $C$4:$C$39, 0)) + sum(IF(($F$4:$F$49=L6), $D$4:$D$39, 0)) - sum(IF(($S$3:$S$100=L6), $T$3:$T$100, 0))} -> 2136 | N6: ='Nov 25'!M6 -> 17156 | P6: 45991 | Q6: Bazar | R6: Others | S6: Cash | T6: =1000+170 -> 1170
B7: 45987 | D7: 10000 | E7: City | F7: Cash | H7: =TEXT(I7, "dddd") -> Wednesday | I7: 45959 | J7: {=sum(IF(($P$3:$P$100=I7), $T$3:$T$100, 0))} -> 0 | L7: EXIM | M7: {=N7 - sum(IF(($E$4:$E$49=L7), $D$4:$D$39 + $C$4:$C$39, 0)) + sum(IF(($F$4:$F$49=L7), $D$4:$D$39, 0)) - sum(IF(($S$3:$S$100=L7), $T$3:$T$100, 0))} -> 285 | N7: ='Nov 25'!M7 -> 285 | P7: 45991 | Q7: HouseholdAccessories | R7: HouseholdAccessories | S7: Cash | T7: 1000
B8: 45990 | D8: 1000 | E8: City | F8: bKash | H8: =TEXT(I8, "dddd") -> Thursday | I8: 45960 | J8: {=sum(IF(($P$3:$P$100=I8), $T$3:$T$100, 0))} -> 0 | L8: bKash | M8: {=N8 - sum(IF(($E$4:$E$49=L8), $D$4:$D$39 + $C$4:$C$39, 0)) + sum(IF(($F$4:$F$49=L8), $D$4:$D$39, 0)) - sum(IF(($S$3:$S$100=L8), $T$3:$T$100, 0))} -> 150 | N8: ='Nov 25'!M8 -> 532 | P8: 45990 | Q8: Donation | R8: Donation | S8: bKash | T8: 1005
B9: 45992 | D9: 15000 | E9: SCB | F9: City | H9: =TEXT(I9, "dddd") -> Friday | I9: 45961 | J9: {=sum(IF(($P$3:$P$100=I9), $T$3:$T$100, 0))} -> 0 | L9: Nagad | M9: {=N9 - sum(IF(($E$4:$E$49=L9), $D$4:$D$39 + $C$4:$C$39, 0)) + sum(IF(($F$4:$F$49=L9), $D$4:$D$39, 0)) - sum(IF(($S$3:$S$100=L9), $T$3:$T$100, 0))} -> 2 | N9: ='Nov 25'!M9 -> 2 | P9: 45991 | Q9: Donation | R9: Donation | S9: Cash | T9: 200
B10: 45992 | D10: 20000 | E10: City | F10: Cash | H10: =TEXT(I10, "dddd") -> Saturday | I10: 45962 | J10: {=sum(IF(($P$3:$P$100=I10), $T$3:$T$100, 0))} -> 0 | L10: LendTaken | M10: =N10-10000 -> 90000 | N10: ='Nov 25'!M10 -> 100000 | P10: 45987 | Q10: MobileInternet | R10: ForMine | S10: bKash | T10: =50 -> 50
B11: 46002 | D11: 1000 | E11: City | F11: Cash | H11: =TEXT(I11, "dddd") -> Sunday | I11: 45963 | J11: {=sum(IF(($P$3:$P$100=I11), $T$3:$T$100, 0))} -> 0 | L11: LendGiven | M11: {=N11 - sum(IF(($E$4:$E$49=L11), $D$4:$D$39 + $C$4:$C$39, 0)) + sum(IF(($F$4:$F$49=L11), $D$4:$D$39, 0)) - sum(IF(($S$3:$S$100=L11), $T$3:$T$100, 0))} -> 7550 | N11: ='Nov 25'!M11 -> 7550 | P11: 45992 | Q11: Bazar | R11: Fruits | S11: Cash | T11: 240
B12: 46005 | C12: 10 | D12: 5000 | E12: SBL | F12: City | H12: =TEXT(I12, "dddd") -> Monday | I12: 45964 | J12: {=sum(IF(($P$3:$P$100=I12), $T$3:$T$100, 0))} -> 0 | L12: City | M12: {=N12 - sum(IF(($E$4:$E$49=L12), $D$4:$D$39 + $C$4:$C$39, 0)) + sum(IF(($F$4:$F$49=L12), $D$4:$D$39, 0)) - sum(IF(($S$3:$S$100=L12), $T$3:$T$100, 0))} -> 109 | N12: ='Nov 25'!M12 -> 339 | P12: 45992 | Q12: HouseholdAccessories | R12: HouseholdAccessories | S12: Cash | T12: 200
B13: 46005 | D13: 5000 | E13: City | F13: Cash | H13: =TEXT(I13, "dddd") -> Tuesday | I13: 45965 | J13: {=sum(IF(($P$3:$P$100=I13), $T$3:$T$100, 0))} -> 0 | N13: ='Nov 25'!M13 | P13: 45992 | Q13: ExtraExpenses | R13: Tea | S13: Cash | T13: 10
B14: 46010 | D14: 850 | E14: City | F14: bKash | H14: =TEXT(I14, "dddd") -> Wednesday | I14: 45966 | J14: {=sum(IF(($P$3:$P$100=I14), $T$3:$T$100, 0))} -> 0 | P14: 45992 | Q14: RentAndPaybill | R14: HouseRent | S14: Cash | T14: 13000
B15: 46011 | C15: 10 | D15: 10000 | E15: SBL | F15: City | H15: =TEXT(I15, "dddd") -> Thursday | I15: 45967 | J15: {=sum(IF(($P$3:$P$100=I15), $T$3:$T$100, 0))} -> 0 | L15: LEND GIVEN TO | N15: =sum(N17:N22) -> 0 | P15: 45992 | Q15: RentAndPaybill | R15: GassBill | S15: Cash | T15: 1080
B16: 46011 | D16: 10000 | E16: City | F16: Cash | H16: =TEXT(I16, "dddd") -> Friday | I16: 45968 | J16: {=sum(IF(($P$3:$P$100=I16), $T$3:$T$100, 0))} -> 0 | L16: Date | M16: Given To | N16: Amount | P16: 45992 | Q16: RentAndPaybill | R16: ServiceBill | S16: Cash | T16: 800
B17: 46015 | D17: 400 | E17: SCB | F17: City | H17: =TEXT(I17, "dddd") -> Saturday | I17: 45969 | J17: {=sum(IF(($P$3:$P$100=I17), $T$3:$T$100, 0))} -> 0 | L17: 45774 | M17: 2500 | N17: Rajib vai | P17: 45992 | Q17: Bazar | R17: AdvGiven | S17: Cash | T17: =5000+120 -> 5120
B18: 46015 | D18: 300 | E18: City | F18: bKash | H18: =TEXT(I18, "dddd") -> Sunday | I18: 45970 | J18: {=sum(IF(($P$3:$P$100=I18), $T$3:$T$100, 0))} -> 0 | M18: 3000 | N18: Rafi vai | P18: 45997 | Q18: Bazar | R18: Fruits | S18: Cash | T18: 760
H19: =TEXT(I19, "dddd") -> Monday | I19: 45971 | J19: {=sum(IF(($P$3:$P$100=I19), $T$3:$T$100, 0))} -> 0 | L19: 45979 | M19: 2050 | N19: Jahid | P19: 45997 | Q19: Bazar | R19: DailyBazar | S19: Cash | T19: =220 -> 220
H20: =TEXT(I20, "dddd") -> Tuesday | I20: 45972 | J20: {=sum(IF(($P$3:$P$100=I20), $T$3:$T$100, 0))} -> 0 | P20: 45996 | Q20: ExtraExpenses | R20: Travel | S20: Cash | T20: =200 -> 200
H21: =TEXT(I21, "dddd") -> Wednesday | I21: 45973 | J21: {=sum(IF(($P$3:$P$100=I21), $T$3:$T$100, 0))} -> 0 | P21: 45997 | Q21: ExtraExpenses | R21: Tea | S21: Cash | T21: 60
H22: =TEXT(I22, "dddd") -> Thursday | I22: 45974 | J22: {=sum(IF(($P$3:$P$100=I22), $T$3:$T$100, 0))} -> 0 | P22: 45997 | Q22: Bazar | R22: Others | S22: Cash | T22: =90 -> 90
H23: =TEXT(I23, "dddd") -> Friday | I23: 45975 | J23: {=sum(IF(($P$3:$P$100=I23), $T$3:$T$100, 0))} -> 0 | P23: 45998 | Q23: Savings | R23: EximBank_2.5 | S23: SCB | T23: 2500
H24: =TEXT(I24, "dddd") -> Saturday | I24: 45976 | J24: {=sum(IF(($P$3:$P$100=I24), $T$3:$T$100, 0))} -> 0 | L24: LEND TAKEN FROM | N24: =sum(N26:N31) -> 0 | P24: 45999 | Q24: Bazar | R24: Others | S24: Cash | T24: =20+15 -> 35
H25: =TEXT(I25, "dddd") -> Sunday | I25: 45977 | J25: {=sum(IF(($P$3:$P$100=I25), $T$3:$T$100, 0))} -> 0 | L25: Date | M25: Taken From | N25: Amount | P25: 45998 | Q25: HouseholdAccessories | R25: DailyAccessories | S25: SCB | T25: 250
H26: =TEXT(I26, "dddd") -> Monday | I26: 45978 | J26: {=sum(IF(($P$3:$P$100=I26), $T$3:$T$100, 0))} -> 0 | P26: 46000 | Q26: Bazar | R26: Others | S26: Cash | T26: 20
H27: =TEXT(I27, "dddd") -> Tuesday | I27: 45979 | J27: {=sum(IF(($P$3:$P$100=I27), $T$3:$T$100, 0))} -> 0 | P27: 46001 | Q27: HouseholdAccessories | R27: DailyAccessories | S27: SCB | T27: 560
H28: =TEXT(I28, "dddd") -> Wednesday | I28: 45980 | J28: {=sum(IF(($P$3:$P$100=I28), $T$3:$T$100, 0))} -> 0 | P28: 46001 | Q28: Bazar | R28: Others | S28: SCB | T28: 90
H29: =TEXT(I29, "dddd") -> Thursday | I29: 45981 | J29: {=sum(IF(($P$3:$P$100=I29), $T$3:$T$100, 0))} -> 0 | P29: 46001 | Q29: ExtraExpenses | R29: ExtraExpenses | S29: Cash | T29: 95
H30: =TEXT(I30, "dddd") -> Friday | I30: 45982 | J30: {=sum(IF(($P$3:$P$100=I30), $T$3:$T$100, 0))} -> 0 | P30: 46001 | Q30: HouseholdAccessories | R30: Medicine | S30: Cash | T30: 80
H31: =TEXT(I31, "dddd") -> Saturday | I31: 45983 | J31: {=sum(IF(($P$3:$P$100=I31), $T$3:$T$100, 0))} -> 0 | P31: 46001 | Q31: MobileInternet | R31: ForOthers | S31: bKash | T31: =208+50 -> 258
H32: =TEXT(I32, "dddd") -> Sunday | I32: 45984 | J32: {=sum(IF(($P$3:$P$100=I32), $T$3:$T$100, 0))} -> 0 | P32: 46001 | Q32: MobileInternet | R32: ForMine | S32: bKash | T32: =20+30 -> 50
H33: =TEXT(I33, "dddd") -> Monday | I33: 45985 | J33: {=sum(IF(($P$3:$P$100=I33), $T$3:$T$100, 0))} -> 0 | L33: Savings | N33: =sum(N35:N40) -> 0 | P33: 46000 | Q33: HouseholdAccessories | R33: Medicine | S33: Cash | T33: 260
H34: =TEXT(I34, "dddd") -> Tuesday | I34: 45986 | J34: {=sum(IF(($P$3:$P$100=I34), $T$3:$T$100, 0))} -> 0 | L34: Type | M34: Current | N34: Prev | P34: 46002 | Q34: ExtraExpenses | R34: Travel | S34: Cash | T34: =205+140 -> 345
H35: =TEXT(I35, "dddd") -> Wednesday | I35: 45987 | J35: {=sum(IF(($P$3:$P$100=I35), $T$3:$T$100, 0))} -> 7530 | P35: 46002 | Q35: ExtraExpenses | R35: Tea | S35: Cash | T35: =15+15 -> 30
J36: {=sum(IF(($P$3:$P$100=I36), $T$3:$T$100, 0))} -> 0 | P36: 46002 | Q36: Bazar | R36: Others | S36: Cash | T36: 30
P37: 46003 | Q37: Bazar | R37: Others | S37: Cash | T37: 20
P38: 46004 | Q38: Bazar | R38: Fruits | S38: Cash | T38: =200+40+85 -> 325
P39: 46004 | Q39: Bazar | R39: DailyBazar | S39: Cash | T39: =70 -> 70
P40: 46004 | Q40: Donation | R40: Donation | S40: Cash | T40: 20
P41: 46005 | Q41: ExtraExpenses | R41: ExtraExpenses | S41: Cash | T41: =3000+285+15 -> 3300
B42: B U D G E T | P42: 46006 | Q42: Bazar | R42: Fruits | S42: Cash | T42: =350+20 -> 370
P43: 46007 | Q43: Bazar | R43: DailyBazar | S43: Cash | T43: =750+200+60+5 -> 1015
B44: Category | E44: Budget | F44: Subcategory | I44: Budget | J44: Cost | L44: TGC | P44: 46007 | Q44: Bazar | R44: Others | S44: Cash | T44: =20+10 -> 30
B45: RentAndPaybill | E45: =Sum(I45:I50) -> 16070 | F45: {=INDIRECT("Subcategory")} -> HouseRent | I45: 13000 | J45: {=sum(IF(($R$3:$R$100=F45), $T$3:$T$100, 0))} -> 13000 | L45: =sum(J45:J50) -> 15969 | M45: =I45+I48+I50 -> 14880 | P45: 46008 | Q45: Bazar | R45: Others | S45: Cash | T45: 25
F46: ElectricBill_Dhk | I46: 0 | J46: {=sum(IF(($R$3:$R$100=F46), $T$3:$T$100, 0))} -> 0 | P46: 46009 | Q46: Bazar | R46: Others | S46: Cash | T46: 40
F47: ElectricBill_Swk | I47: 350 | J47: {=sum(IF(($R$3:$R$100=F47), $T$3:$T$100, 0))} -> 249 | P47: 46009 | Q47: ExtraExpenses | R47: Tea | S47: Cash | T47: 15
F48: GassBill | I48: 1080 | J48: {=sum(IF(($R$3:$R$100=F48), $T$3:$T$100, 0))} -> 1080 | P48: 46010 | Q48: RentAndPaybill | R48: WifiBill | S48: bKash | T48: 840
F49: WifiBill | I49: 840 | J49: {=sum(IF(($R$3:$R$100=F49), $T$3:$T$100, 0))} -> 840 | P49: 46011 | Q49: ExtraExpenses | R49: Travel | S49: Cash | T49: =230+180 -> 410
F50: ServiceBill | I50: 800 | J50: {=sum(IF(($R$3:$R$100=F50), $T$3:$T$100, 0))} -> 800 | P50: 46011 | Q50: ExtraExpenses | R50: Tea | S50: Cash | T50: =15+10 -> 25
B51: Bazar | E51: =Sum(I51:I54) -> 8500 | F51: DailyBazar | I51: 1000 | J51: {=sum(IF(($R$3:$R$100=F51), $T$3:$T$100, 0))} -> 2050 | L51: =sum(J51:J54) -> 10755 | P51: 46011 | Q51: HouseholdAccessories | R51: Medicine | S51: Cash | T51: =800+100+3750 -> 4650
F52: Fruits | I52: 1000 | J52: {=sum(IF(($R$3:$R$100=F52), $T$3:$T$100, 0))} -> 1795 | P52: 46012 | Q52: HouseholdAccessories | R52: Medicine | S52: Cash | T52: =400+1150+35 -> 1585
F53: AdvGiven | I53: 5000 | J53: {=sum(IF(($R$3:$R$100=F53), $T$3:$T$100, 0))} -> 5120 | P53: 46012 | Q53: Bazar | R53: Others | S53: Cash | T53: 20
F54: Others | I54: 1500 | J54: {=sum(IF(($R$3:$R$100=F54), $T$3:$T$100, 0))} -> 1790 | P54: 46012 | Q54: Donation | R54: Donation | S54: Cash | T54: 100
B55: HouseholdAccessories | E55: =sum(I55:I57) -> 7000 | F55: HouseholdAccessories | I55: 1200 | J55: {=sum(IF(($R$3:$R$100=F55), $T$3:$T$100, 0))} -> 1200 | L55: =sum(J55:J58) -> 14015 | P55: 46011 | Q55: ExtraExpenses | R55: ExtraExpenses | S55: Cash | T55: 200
F56: DailyAccessories | I56: 300 | J56: {=sum(IF(($R$3:$R$100=F56), $T$3:$T$100, 0))} -> 1060 | P56: 46013 | Q56: Bazar | R56: Others | S56: Cash | T56: 20
F57: Medicine | I57: 5500 | J57: {=sum(IF(($R$3:$R$100=F57), $T$3:$T$100, 0))} -> 11575 | P57: 46014 | Q57: HouseholdAccessories | R57: DailyAccessories | S57: Cash | T57: 250
B58: MobileInternet | E58: =I58+I59 -> 400 | F58: ForMine | I58: 100 | J58: {=sum(IF(($R$3:$R$100=F58), $T$3:$T$100, 0))} -> 180 | L58: =J58+J59 -> 438 | P58: 46014 | Q58: Bazar | R58: Others | S58: Cash | T58: 80
F59: ForOthers | I59: 300 | J59: {=sum(IF(($R$3:$R$100=F59), $T$3:$T$100, 0))} -> 258 | P59: 46015 | Q59: Bazar | R59: Fruits | S59: Cash | T59: 100
B60: ExtraExpenses | E60: =I60+I61+I62 -> 4200 | F60: Tea | I60: 200 | J60: {=sum(IF(($R$3:$R$100=F60), $T$3:$T$100, 0))} -> 165 | L60: =J60+J61+J62 -> 1120 | P60: 46015 | Q60: Bazar | R60: Others | S60: Cash | T60: 20
F61: Travel | I61: 500 | J61: {=sum(IF(($R$3:$R$100=F61), $T$3:$T$100, 0))} -> 955 | P61: 46015 | Q61: ExtraExpenses | R61: Tea | S61: Cash | T61: 25
F62: AiSubs | I62: 3500 | J62: {=sum(IF(($R$3:$R$100=F62), $T$3:$T$100, 0))} -> 0 | P62: 46015 | Q62: RentAndPaybill | R62: ElectricBill_Swk | S62: bKash | T62: 249
B63: Savings | F63: BooksOrCourses | I63: 2500 | J63: {=sum(IF(($R$3:$R$100=F63), $T$3:$T$100, 0))} -> 0 | P63: 46015 | Q63: MobileInternet | R63: ForMine | S63: bKash | T63: =30+50 -> 80
F64: ExtraExpenses | J64: {=sum(IF(($R$3:$R$100=F64), $T$3:$T$100, 0))} -> 6225 | P64: 46017 | Q64: Donation | R64: Donation | S64: Cash | T64: 10
B65: Donation | F65: EximBank_2.5 | I65: 1300 | J65: {=sum(IF(($R$3:$R$100=F65), $T$3:$T$100, 0))} -> 2500 | P65: 46017 | Q65: Bazar | R65: Others | S65: Cash | T65: 100
F66: CityBank_10 | I66: 0 | J66: {=sum(IF(($R$3:$R$100=F66), $T$3:$T$100, 0))} -> 0 | P66: 46018 | Q66: ExtraExpenses | R66: ExtraExpenses | S66: Cash | T66: 100
B67: Pay | F67: BracBank_10 | I67: 0 | J67: {=sum(IF(($R$3:$R$100=F67), $T$3:$T$100, 0))} -> 0 | P67: 46017 | Q67: ExtraExpenses | R67: ExtraExpenses | S67: Cash | T67: 50
F68: SBL_root | I68: 0 | J68: {=sum(IF(($R$3:$R$100=F68), $T$3:$T$100, 0))} -> 0
F69: Exim_root
F70: Donation | H70: Total | I70: =SUM(I45:I68) -> 39970 | J70: =SUM(J45:J68) -> 50842 | L70: =I70-J70 -> -10872
F71: Unknown | H71: Non-Cash | I71: =I46+I47+I49+I58+I59+I63+I67+I68+I62 -> 7590 | J71: =J46+J47+J49+J58+J59+J63+J67+J68+J62 -> 1527 | L71: =I71-J71 -> 6063
F72: CityService | H72: Cash | I72: =I70-I71 -> 32380 | J72: =J70-J71 -> 49315 | L72: =I72-J72 -> -16935
F73: SblService

Sheet Jan 26
B2: T r a n s a c t i o n & P a y | H2: DAY | I2: Date | J2: =sum(J4:J39) -> 59471 | L2: FINANCIAL STATUS | N2: =M4+M5+M8+M9+M12 -> 2309 | P2: Date | Q2: Category | R2: Subcategory | S2: Payment Method | T2: Amount | U2: Remarks
B3: Date | C3: Cost | D3: Amount | E3: FROM | F3: TO | J3: Cost | L3: Type | M3: Current Status | N3: Start with | P3: 46019 | Q3: HouseholdAccessories | R3: Medicine | S3: Cash | T3: 780
B4: 46019 | D4: 49500 | E4: Add | F4: SCB | H4: =TEXT(I4, "dddd") -> Friday | I4: 46017 | J4: {=sum(IF(($P$3:$P$100=I4), $T$3:$T$100, 0))} -> 0 | L4: {=INDIRECT("Account")} -> Cash | M4: {=N4 - sum(IF(($E$4:$E$49=L4), $D$4:$D$39 + $C$4:$C$39, 0)) + sum(IF(($F$4:$F$49=L4), $D$4:$D$39, 0)) - sum(IF(($S$3:$S$100=L4), $T$3:$T$100, 0))} -> 670 | N4: ='Dec 25'!M4 -> 3000 | P4: 46019 | Q4: Bazar | R4: Fruits | S4: Cash | T4: 225
B5: 46020 | D5: 2500 | E5: SCB | F5: City | H5: =TEXT(I5, "dddd") -> Saturday | I5: 46018 | J5: {=sum(IF(($P$3:$P$100=I5), $T$3:$T$100, 0))} -> 0 | L5: SCB | M5: {=N5 - sum(IF(($E$4:$E$49=L5), $D$4:$D$39 + $C$4:$C$39, 0)) + sum(IF(($F$4:$F$49=L5), $D$4:$D$39, 0)) - sum(IF(($S$3:$S$100=L5), $T$3:$T$100, 0))} -> 377 | N5: ='Dec 25'!M5 -> 1432 | P5: 46019 | Q5: ExtraExpenses | R5: ExtraExpenses | S5: Cash | T5: =50+50+150+150+20 -> 420 | U5: pant+muja
B6: 46020 | D6: 20000 | E6: SCB | F6: City | H6: =TEXT(I6, "dddd") -> Sunday | I6: 46019 | J6: {=sum(IF(($P$3:$P$100=I6), $T$3:$T$100, 0))} -> 2127 | L6: SBL | M6: {=N6 - sum(IF(($E$4:$E$49=L6), $D$4:$D$39 + $C$4:$C$39, 0)) + sum(IF(($F$4:$F$49=L6), $D$4:$D$39, 0)) - sum(IF(($S$3:$S$100=L6), $T$3:$T$100, 0))} -> 1711 | N6: ='Dec 25'!M6 -> 2136 | P6: 46019 | Q6: Bazar | R6: Others | S6: Cash | T6: 100
B7: 46020 | D7: 20000 | E7: City | F7: Cash | H7: =TEXT(I7, "dddd") -> Monday | I7: 46020 | J7: {=sum(IF(($P$3:$P$100=I7), $T$3:$T$100, 0))} -> 22515 | L7: EXIM | M7: {=N7 - sum(IF(($E$4:$E$49=L7), $D$4:$D$39 + $C$4:$C$39, 0)) + sum(IF(($F$4:$F$49=L7), $D$4:$D$39, 0)) - sum(IF(($S$3:$S$100=L7), $T$3:$T$100, 0))} -> 285 | N7: ='Dec 25'!M7 -> 285 | P7: 46019 | Q7: Pay | R7: SblService | S7: SBL | T7: =8+50+15+100+60+400-31 -> 602
B8: 46020 | D8: 10000 | E8: SCB | F8: SBL | H8: =TEXT(I8, "dddd") -> Tuesday | I8: 46021 | J8: {=sum(IF(($P$3:$P$100=I8), $T$3:$T$100, 0))} -> 115 | L8: bKash | M8: {=N8 - sum(IF(($E$4:$E$49=L8), $D$4:$D$39 + $C$4:$C$39, 0)) + sum(IF(($F$4:$F$49=L8), $D$4:$D$39, 0)) - sum(IF(($S$3:$S$100=L8), $T$3:$T$100, 0))} -> 136 | N8: ='Dec 25'!M8 -> 150 | P8: 46020 | Q8: Bazar | R8: Others | S8: Cash | T8: 40
B9: 46022 | D9: 2000 | E9: SCB | F9: City | H9: =TEXT(I9, "dddd") -> Wednesday | I9: 46022 | J9: {=sum(IF(($P$3:$P$100=I9), $T$3:$T$100, 0))} -> 309 | L9: Nagad | M9: {=N9 - sum(IF(($E$4:$E$49=L9), $D$4:$D$39 + $C$4:$C$39, 0)) + sum(IF(($F$4:$F$49=L9), $D$4:$D$39, 0)) - sum(IF(($S$3:$S$100=L9), $T$3:$T$100, 0))} -> 2 | N9: ='Dec 25'!M9 -> 2 | P9: 46020 | Q9: RentAndPaybill | R9: HouseRent | S9: Cash | T9: 13000
B10: 46022 | D10: 1000 | E10: City | F10: bKash | H10: =TEXT(I10, "dddd") -> Thursday | I10: 46023 | J10: {=sum(IF(($P$3:$P$100=I10), $T$3:$T$100, 0))} -> 4810 | L10: LendTaken | M10: =N10-50000 -> 40000 | N10: ='Dec 25'!M10 -> 90000 | P10: 46020 | Q10: RentAndPaybill | R10: GassBill | S10: Cash | T10: 1080
B11: 46023 | D11: 5000 | E11: SCB | F11: City | H11: =TEXT(I11, "dddd") -> Friday | I11: 46024 | J11: {=sum(IF(($P$3:$P$100=I11), $T$3:$T$100, 0))} -> 7280 | L11: LendGiven | M11: {=N11 - sum(IF(($E$4:$E$49=L11), $D$4:$D$39 + $C$4:$C$39, 0)) + sum(IF(($F$4:$F$49=L11), $D$4:$D$39, 0)) - sum(IF(($S$3:$S$100=L11), $T$3:$T$100, 0))} -> 7550 | N11: ='Dec 25'!M11 -> 7550 | P11: 46020 | Q11: RentAndPaybill | R11: ServiceBill | S11: Cash | T11: 800
B12: 46023 | D12: 5000 | E12: City | F12: Cash | H12: =TEXT(I12, "dddd") -> Saturday | I12: 46025 | J12: {=sum(IF(($P$3:$P$100=I12), $T$3:$T$100, 0))} -> 1535 | L12: City | M12: {=N12 - sum(IF(($E$4:$E$49=L12), $D$4:$D$39 + $C$4:$C$39, 0)) + sum(IF(($F$4:$F$49=L12), $D$4:$D$39, 0)) - sum(IF(($S$3:$S$100=L12), $T$3:$T$100, 0))} -> 1124 | N12: ='Dec 25'!M12 -> 109 | P12: 46020 | Q12: Bazar | R12: AdvGiven | S12: Cash | T12: =5000+120 -> 5120
B13: 46024 | D13: 5000 | E13: Add | F13: Cash | H13: =TEXT(I13, "dddd") -> Sunday | I13: 46026 | J13: {=sum(IF(($P$3:$P$100=I13), $T$3:$T$100, 0))} -> 45 | N13: ='Nov 25'!M13 | P13: 46020 | Q13: ExtraExpenses | R13: AiSubs | S13: City | T13: 2475
B14: 46025 | D14: 5000 | E14: SCB | F14: City | H14: =TEXT(I14, "dddd") -> Monday | I14: 46027 | J14: {=sum(IF(($P$3:$P$100=I14), $T$3:$T$100, 0))} -> 2090 | P14: 46021 | Q14: Bazar | R14: Others | S14: Cash | T14: =50 -> 50
B15: 46025 | D15: 5000 | E15: City | F15: Cash | H15: =TEXT(I15, "dddd") -> Tuesday | I15: 46028 | J15: {=sum(IF(($P$3:$P$100=I15), $T$3:$T$100, 0))} -> 5755 | L15: LEND GIVEN TO | N15: =sum(N17:N22) -> 0 | P15: 46021 | Q15: ExtraExpenses | R15: ExtraExpenses | S15: Cash | T15: 50
B16: 46028 | C16: 15 | D16: 5000 | E16: SCB | F16: Cash | H16: =TEXT(I16, "dddd") -> Wednesday | I16: 46029 | J16: {=sum(IF(($P$3:$P$100=I16), $T$3:$T$100, 0))} -> 410 | L16: Date | M16: Given To | N16: Amount | P16: 46021 | Q16: ExtraExpenses | R16: Tea | S16: Cash | T16: 15
B17: 46033 | C17: 10 | D17: 10000 | E17: SBL | F17: City | H17: =TEXT(I17, "dddd") -> Thursday | I17: 46030 | J17: {=sum(IF(($P$3:$P$100=I17), $T$3:$T$100, 0))} -> 145 | L17: 45774 | M17: 2500 | N17: Rajib vai | P17: 46022 | Q17: MobileInternet | R17: ForOthers | S17: bKash | T17: =50+259 -> 309
B18: 46033 | D18: 5000 | E18: City | F18: Cash | H18: =TEXT(I18, "dddd") -> Friday | I18: 46031 | J18: {=sum(IF(($P$3:$P$100=I18), $T$3:$T$100, 0))} -> 0 | M18: 3000 | N18: Rafi vai | P18: 46023 | Q18: ExtraExpenses | R18: ExtraExpenses | S18: bKash | T18: 840 | U18: tshirt
B19: 46022 | D19: =220-33 -> 187 | E19: Pay | F19: SBL | H19: =TEXT(I19, "dddd") -> Saturday | I19: 46032 | J19: {=sum(IF(($P$3:$P$100=I19), $T$3:$T$100, 0))} -> 0 | L19: 45979 | M19: 2050 | N19: Jahid | P19: 46023 | Q19: ExtraExpenses | R19: ExtraExpenses | S19: Cash | T19: 3900 | U19: table+chair
B20: 46038 | D20: 1000 | E20: City | F20: bKash | H20: =TEXT(I20, "dddd") -> Sunday | I20: 46033 | J20: {=sum(IF(($P$3:$P$100=I20), $T$3:$T$100, 0))} -> 1080 | P20: 46023 | Q20: ExtraExpenses | R20: Travel | S20: Cash | T20: 30
B21: 46041 | D21: 500 | E21: City | F21: bKash | H21: =TEXT(I21, "dddd") -> Monday | I21: 46034 | J21: {=sum(IF(($P$3:$P$100=I21), $T$3:$T$100, 0))} -> 480 | P21: 46023 | Q21: Bazar | R21: Others | S21: Cash | T21: 40
B22: 46041 | D22: 2000 | E22: Add | F22: SCB | H22: =TEXT(I22, "dddd") -> Tuesday | I22: 46035 | J22: {=sum(IF(($P$3:$P$100=I22), $T$3:$T$100, 0))} -> 90 | P22: 46024 | Q22: ExtraExpenses | R22: Travel | S22: Cash | T22: 50
B23: 46044 | D23: 1500 | E23: SCB | F23: City | H23: =TEXT(I23, "dddd") -> Wednesday | I23: 46036 | J23: {=sum(IF(($P$3:$P$100=I23), $T$3:$T$100, 0))} -> 390 | P23: 46024 | Q23: ExtraExpenses | R23: ExtraExpenses | S23: Cash | T23: =2500+3400+1000+200 -> 7100 | U23: lpg cyllender+cula+toshok
B24: 46044 | D24: 2000 | E24: City | F24: Cash | H24: =TEXT(I24, "dddd") -> Thursday | I24: 46037 | J24: {=sum(IF(($P$3:$P$100=I24), $T$3:$T$100, 0))} -> 2660 | L24: LEND TAKEN FROM | N24: =sum(N26:N31) -> 0 | P24: 46024 | Q24: HouseholdAccessories | R24: DailyAccessories | S24: Cash | T24: 130
H25: =TEXT(I25, "dddd") -> Friday | I25: 46038 | J25: {=sum(IF(($P$3:$P$100=I25), $T$3:$T$100, 0))} -> 970 | L25: Date | M25: Taken From | N25: Amount | P25: 46025 | Q25: Bazar | R25: Others | S25: Cash | T25: =910 -> 910 | U25: doi+misti
H26: =TEXT(I26, "dddd") -> Saturday | I26: 46039 | J26: {=sum(IF(($P$3:$P$100=I26), $T$3:$T$100, 0))} -> 0 | P26: 46025 | Q26: Bazar | R26: DailyBazar | S26: Cash | T26: 80
H27: =TEXT(I27, "dddd") -> Sunday | I27: 46040 | J27: {=sum(IF(($P$3:$P$100=I27), $T$3:$T$100, 0))} -> 530 | P27: 46025 | Q27: HouseholdAccessories | R27: Medicine | S27: Cash | T27: =275+270 -> 545
H28: =TEXT(I28, "dddd") -> Monday | I28: 46041 | J28: {=sum(IF(($P$3:$P$100=I28), $T$3:$T$100, 0))} -> 1985 | P28: 46026 | Q28: ExtraExpenses | R28: Tea | S28: Cash | T28: 15
H29: =TEXT(I29, "dddd") -> Tuesday | I29: 46042 | J29: {=sum(IF(($P$3:$P$100=I29), $T$3:$T$100, 0))} -> 2020 | P29: 46026 | Q29: Bazar | R29: Others | S29: Cash | T29: 30
H30: =TEXT(I30, "dddd") -> Wednesday | I30: 46043 | J30: {=sum(IF(($P$3:$P$100=I30), $T$3:$T$100, 0))} -> 565 | P30: 46027 | Q30: ExtraExpenses | R30: Travel | S30: Cash | T30: =560+810 -> 1370 | U30: n.zoo updown
H31: =TEXT(I31, "dddd") -> Thursday | I31: 46044 | J31: {=sum(IF(($P$3:$P$100=I31), $T$3:$T$100, 0))} -> 435 | P31: 46027 | Q31: ExtraExpenses | R31: ExtraExpenses | S31: Cash | T31: =40+10+50*4+10+430 -> 690 | U31: for n.zoo
H32: =TEXT(I32, "dddd") -> Friday | I32: 46045 | J32: {=sum(IF(($P$3:$P$100=I32), $T$3:$T$100, 0))} -> 900 | P32: 46027 | Q32: HouseholdAccessories | R32: Medicine | S32: Cash | T32: 30
H33: =TEXT(I33, "dddd") -> Saturday | I33: 46046 | J33: {=sum(IF(($P$3:$P$100=I33), $T$3:$T$100, 0))} -> 20 | L33: Savings | N33: =sum(N35:N40) -> 0 | P33: 46028 | Q33: ExtraExpenses | R33: Travel | S33: Cash | T33: =650+10 -> 660 | U33: dhk to swk
H34: =TEXT(I34, "dddd") -> Sunday | I34: 46047 | J34: {=sum(IF(($P$3:$P$100=I34), $T$3:$T$100, 0))} -> 110 | L34: Type | M34: Current | N34: Prev | P34: 46028 | Q34: ExtraExpenses | R34: Tea | S34: Cash | T34: =15+40 -> 55
H35: =TEXT(I35, "dddd") -> Monday | I35: 46048 | J35: {=sum(IF(($P$3:$P$100=I35), $T$3:$T$100, 0))} -> 100 | L35: {=INDIRECT("SavingsAcc")} -> EximBank_2.5 | P35: 46028 | Q35: Bazar | R35: Others | S35: Cash | T35: 40
J36: {=sum(IF(($P$3:$P$100=I36), $T$3:$T$100, 0))} -> 0 | L36: CityBank_10 | P36: 46029 | Q36: HouseholdAccessories | R36: Medicine | S36: Cash | T36: =410-50 -> 360 | U36: med, adjust 50 tk got from jacket
L37: BracBank_10 | P37: 46029 | Q37: ExtraExpenses | R37: Tea | S37: Cash | T37: =15+15 -> 30
L38: SBL_root | P38: 46029 | Q38: Bazar | R38: Others | S38: Cash | T38: 20
L39: Exim_root | P39: 46030 | Q39: Bazar | R39: Fruits | S39: Cash | T39: 145 | U39: malta
P40: 46028 | Q40: ExtraExpenses | R40: ExtraExpenses | S40: Cash | T40: 5000 | U40: given to abbu
P41: 46033 | Q41: ExtraExpenses | R41: Tea | S41: Cash | T41: =15+10+15 -> 40
B42: B U D G E T | P42: 46033 | Q42: ExtraExpenses | R42: Travel | S42: Cash | T42: =100+40+80+120 -> 340
P43: 46033 | Q43: HouseholdAccessories | R43: Medicine | S43: Cash | T43: =300+290+30 -> 620 | U43: doc f suba
B44: Category | E44: Budget | F44: Subcategory | I44: Budget | J44: Cost | L44: TGC | P44: 46033 | Q44: Bazar | R44: Others | S44: Cash | T44: =30+30+20 -> 80
B45: RentAndPaybill | E45: =Sum(I45:I50) -> 16470 | F45: {=INDIRECT("Subcategory")} -> HouseRent | I45: 13000 | J45: {=sum(IF(($R$3:$R$100=F45), $T$3:$T$100, 0))} -> 13000 | L45: =sum(J45:J50) -> 16445 | M45: =I45+I48+I50 -> 14880 | P45: 46034 | Q45: ExtraExpenses | R45: Tea | S45: Cash | T45: 15
F46: ElectricBill_Dhk | I46: 500 | J46: {=sum(IF(($R$3:$R$100=F46), $T$3:$T$100, 0))} -> 500 | P46: 46034 | Q46: Bazar | R46: Fruits | S46: Cash | T46: 175
F47: ElectricBill_Swk | I47: 250 | J47: {=sum(IF(($R$3:$R$100=F47), $T$3:$T$100, 0))} -> 225 | P47: 46034 | Q47: HouseholdAccessories | R47: DailyAccessories | S47: Cash | T47: 250 | U47: g.night
F48: GassBill | I48: 1080 | J48: {=sum(IF(($R$3:$R$100=F48), $T$3:$T$100, 0))} -> 1080 | P48: 46034 | Q48: Donation | R48: Unknown | S48: Cash | T48: 40
F49: WifiBill | I49: 840 | J49: {=sum(IF(($R$3:$R$100=F49), $T$3:$T$100, 0))} -> 840 | P49: 46035 | Q49: Bazar | R49: Fruits | S49: Cash | T49: 90
F50: ServiceBill | I50: 800 | J50: {=sum(IF(($R$3:$R$100=F50), $T$3:$T$100, 0))} -> 800 | P50: 46036 | Q50: Bazar | R50: Fruits | S50: Cash | T50: 40
B51: Bazar | E51: =Sum(I51:I54) -> 8500 | F51: DailyBazar | I51: 500 | J51: {=sum(IF(($R$3:$R$100=F51), $T$3:$T$100, 0))} -> 80 | L51: =sum(J51:J54) -> 9710 | P51: 46036 | Q51: ExtraExpenses | R51: ExtraExpenses | S51: Cash | T51: 350 | U51: toy
F52: Fruits | I52: 500 | J52: {=sum(IF(($R$3:$R$100=F52), $T$3:$T$100, 0))} -> 1075 | P52: 46037 | Q52: Savings | R52: EximBank_2.5 | S52: City | T52: 2510
F53: AdvGiven | I53: 6000 | J53: {=sum(IF(($R$3:$R$100=F53), $T$3:$T$100, 0))} -> 6120 | P53: 46037 | Q53: HouseholdAccessories | R53: Medicine | S53: Cash | T53: 140
F54: Others | I54: 1500 | J54: {=sum(IF(($R$3:$R$100=F54), $T$3:$T$100, 0))} -> 2435 | P54: 46037 | Q54: Bazar | R54: Others | S54: Cash | T54: 10
B55: HouseholdAccessories | E55: =sum(I55:I57) -> 2500 | F55: HouseholdAccessories | I55: 200 | J55: {=sum(IF(($R$3:$R$100=F55), $T$3:$T$100, 0))} -> 520 | L55: =sum(J55:J58) -> 5975 | P55: 46038 | Q55: HouseholdAccessories | R55: Medicine | S55: Cash | T55: 85
F56: DailyAccessories | I56: 300 | J56: {=sum(IF(($R$3:$R$100=F56), $T$3:$T$100, 0))} -> 1440 | P56: 46038 | Q56: HouseholdAccessories | R56: DailyAccessories | S56: Cash | T56: 40
F57: Medicine | I57: 2000 | J57: {=sum(IF(($R$3:$R$100=F57), $T$3:$T$100, 0))} -> 3715 | P57: 46038 | Q57: Donation | R57: Donation | S57: Cash | T57: =20+5 -> 25
B58: MobileInternet | E58: =I58+I59 -> 400 | F58: ForMine | I58: 100 | J58: {=sum(IF(($R$3:$R$100=F58), $T$3:$T$100, 0))} -> 300 | L58: =J58+J59 -> 609 | P58: 46038 | Q58: Bazar | R58: Others | S58: Cash | T58: =40+10 -> 50
F59: ForOthers | I59: 300 | J59: {=sum(IF(($R$3:$R$100=F59), $T$3:$T$100, 0))} -> 309 | P59: 46038 | Q59: MobileInternet | R59: ForMine | S59: bKash | T59: 270
B60: ExtraExpenses | E60: =I60+I61+I62+I63+I64 -> 22650 | F60: Tea | I60: 150 | J60: {=sum(IF(($R$3:$R$100=F60), $T$3:$T$100, 0))} -> 190 | L60: =J60+J61+J62+J63+J64 -> 23705 | P60: 46038 | Q60: RentAndPaybill | R60: ElectricBill_Dhk | S60: City | T60: 500
F61: Travel | I61: 2000 | J61: {=sum(IF(($R$3:$R$100=F61), $T$3:$T$100, 0))} -> 2590 | P61: 46040 | Q61: Bazar | R61: Others | S61: Cash | T61: =40+10+100+50 -> 200
F62: AiSubs | I62: 2500 | J62: {=sum(IF(($R$3:$R$100=F62), $T$3:$T$100, 0))} -> 2475 | P62: 46040 | Q62: ExtraExpenses | R62: Travel | S62: Cash | T62: 120
F63: BooksOrCourses | I63: 0 | J63: {=sum(IF(($R$3:$R$100=F63), $T$3:$T$100, 0))} -> 0 | P63: 46040 | Q63: HouseholdAccessories | R63: Medicine | S63: Cash | T63: 110
F64: ExtraExpenses | I64: 18000 | J64: {=sum(IF(($R$3:$R$100=F64), $T$3:$T$100, 0))} -> 18450 | P64: 46040 | Q64: Donation | R64: Unknown | S64: Cash | T64: 70
B65: Savings | E65: =sum(I65:I68) -> 2500 | F65: EximBank_2.5 | I65: 2500 | J65: {=sum(IF(($R$3:$R$100=F65), $T$3:$T$100, 0))} -> 2510 | L65: =sum(J65:J68) -> 2510 | P65: 46041 | Q65: HouseholdAccessories | R65: Medicine | S65: Cash | T65: =800+40 -> 840
F66: CityBank_10 | I66: 0 | J66: {=sum(IF(($R$3:$R$100=F66), $T$3:$T$100, 0))} -> 0 | P66: 46041 | Q66: ExtraExpenses | R66: Travel | S66: Cash | T66: 20
F67: BracBank_10 | I67: 0 | J67: {=sum(IF(($R$3:$R$100=F67), $T$3:$T$100, 0))} -> 0 | P67: 46041 | Q67: ExtraExpenses | R67: Tea | S67: Cash | T67: 20
F68: SBL_root | I68: 0 | J68: {=sum(IF(($R$3:$R$100=F68), $T$3:$T$100, 0))} -> 0 | P68: 46041 | Q68: Bazar | R68: Others | S68: Cash | T68: =20+20 -> 40
B69: Donation | F69: Exim_root | I69: 200 | J69: {=sum(IF(($R$3:$R$100=F69), $T$3:$T$100, 0))} -> 0 | P69: 46040 | Q69: MobileInternet | R69: ForMine | S69: bKash | T69: 30
F70: Donation | J70: {=sum(IF(($R$3:$R$100=F70), $T$3:$T$100, 0))} -> 25 | P70: 46041 | Q70: RentAndPaybill | R70: WifiBill | S70: bKash | T70: 840
B71: Pay | F71: Unknown | J71: {=sum(IF(($R$3:$R$100=F71), $T$3:$T$100, 0))} -> 190 | P71: 46041 | Q71: RentAndPaybill | R71: ElectricBill_Swk | S71: bKash | T71: 225
F72: CityService | J72: {=sum(IF(($R$3:$R$100=F72), $T$3:$T$100, 0))} -> 0 | P72: 46042 | Q72: HouseholdAccessories | R72: DailyAccessories | S72: SCB | T72: 1020
F73: SblService | P73: 46043 | Q73: HouseholdAccessories | R73: HouseholdAccessories | S73: SCB | T73: 520
P74: 46043 | Q74: Bazar | R74: Others | S74: Cash | T74: =15+30 -> 45
H75: Total | I75: =SUM(I45:I72) -> 53220 | J75: =SUM(J45:J72) -> 58869 | L75: =I75-J75 -> -5649 | P75: 46044 | Q75: Bazar | R75: Fruits | S75: Cash | T75: =90+90+90 -> 270
H76: Non-Cash | I76: =I46+I47+I49+I58+I59+I63+I67+I68+I62+I64+I65+I66 -> 24990 | J76: =J46+J47+J49+J58+J59+J63+J67+J68+J62+J64+J65+J66 -> 25609 | L76: =I76-J76 -> -619 | P76: 46044 | Q76: ExtraExpenses | R76: ExtraExpenses | S76: Cash | T76: 100
H77: Cash | I77: =I75-I76 -> 28230 | J77: =J75-J76 -> 33260 | L77: =I77-J77 -> -5030 | P77: 46044 | Q77: Bazar | R77: Others | S77: Cash | T77: 50
P78: 46044 | Q78: HouseholdAccessories | R78: Medicine | S78: Cash | T78: 15
P79: 46042 | Q79: Bazar | R79: AdvGiven | S79: Cash | T79: =1000 -> 1000
P80: 46045 | Q80: Bazar | R80: Others | S80: Cash | T80: =400+270 -> 670
P81: 46045 | Q81: Bazar | R81: Fruits | S81: Cash | T81: 40
P82: 46045 | Q82: HouseholdAccessories | R82: Medicine | S82: Cash | T82: 190
P83: 46046 | Q83: Bazar | R83: Others | S83: Cash | T83: 20
P84: 46047 | Q84: Bazar | R84: Others | S84: Cash | T84: =20 -> 20
P85: 46047 | Q85: Bazar | R85: Fruits | S85: Cash | T85: 90
P86: 46048 | Q86: Bazar | R86: Others | S86: Cash | T86: 20
P87: 46048 | Q87: Donation | R87: Unknown | S87: Cash | T87: 80

Sheet Feb 26
B2: T r a n s a c t i o n & P a y | H2: DAY | I2: Date | J2: =sum(J4:J39) -> 52753 | L2: FINANCIAL STATUS | N2: =M4+M5+M8+M9+M12 -> 10721 | P2: Date | Q2: Category | R2: Subcategory | S2: Payment Method | T2: Amount | U2: Remarks | W2: R e m i n d M e
B3: Date | C3: Cost | D3: Amount | E3: FROM | F3: TO | J3: Cost | L3: Type | M3: Current Status | N3: Start with | P3: 46049 | Q3: Bazar | R3: Others | S3: Cash | T3: 20 | W3: Date | X3: Task
B4: 46048 | D4: 49500 | E4: Add | F4: SCB | H4: =TEXT(I4, "dddd") -> Monday | I4: 46048 | J4: {=sum(IF(($P$3:$P$100=I4), $T$3:$T$100, 0))} -> 0 | L4: {=INDIRECT("Account")} -> Cash | M4: {=N4 - sum(IF(($E$4:$E$49=L4), $D$4:$D$39 + $C$4:$C$39, 0)) + sum(IF(($F$4:$F$49=L4), $D$4:$D$39, 0)) - sum(IF(($S$3:$S$100=L4), $T$3:$T$100, 0))} -> 6540 | N4: ='Jan 26'!M4 -> 670 | P4: 46049 | Q4: Bazar | R4: Others | S4: SCB | T4: 300 | W4: 46099 | X4: Ticket Dhk to Swk
B5: 46049 | D5: 30000 | E5: SCB | F5: City | H5: =TEXT(I5, "dddd") -> Tuesday | I5: 46049 | J5: {=sum(IF(($P$3:$P$100=I5), $T$3:$T$100, 0))} -> 335 | L5: SCB | M5: {=N5 - sum(IF(($E$4:$E$49=L5), $D$4:$D$39 + $C$4:$C$39, 0)) + sum(IF(($F$4:$F$49=L5), $D$4:$D$39, 0)) - sum(IF(($S$3:$S$100=L5), $T$3:$T$100, 0))} -> 7 | N5: ='Jan 26'!M5 -> 377 | P5: 46049 | Q5: ExtraExpenses | R5: Tea | S5: Cash | T5: 15 | W5: 46107 | X5: Ticket Swk to Dhk
B6: 46049 | D6: 20000 | E6: City | F6: Cash | H6: =TEXT(I6, "dddd") -> Wednesday | I6: 46050 | J6: {=sum(IF(($P$3:$P$100=I6), $T$3:$T$100, 0))} -> 21219 | L6: SBL | M6: {=N6 - sum(IF(($E$4:$E$49=L6), $D$4:$D$39 + $C$4:$C$39, 0)) + sum(IF(($F$4:$F$49=L6), $D$4:$D$39, 0)) - sum(IF(($S$3:$S$100=L6), $T$3:$T$100, 0))} -> 9 | N6: ='Jan 26'!M6 -> 1711 | P6: 46050 | Q6: MobileInternet | R6: ForOthers | S6: bKash | T6: =50+259 -> 309
B7: 46050 | D7: 1000 | E7: City | F7: bKash | H7: =TEXT(I7, "dddd") -> Thursday | I7: 46051 | J7: {=sum(IF(($P$3:$P$100=I7), $T$3:$T$100, 0))} -> 5620 | L7: EXIM | M7: {=N7 - sum(IF(($E$4:$E$49=L7), $D$4:$D$39 + $C$4:$C$39, 0)) + sum(IF(($F$4:$F$49=L7), $D$4:$D$39, 0)) - sum(IF(($S$3:$S$100=L7), $T$3:$T$100, 0))} -> 285 | N7: ='Jan 26'!M7 -> 285 | P7: 46050 | Q7: RentAndPaybill | R7: ElectricBill_Dhk | S7: City | T7: 500
B8: 46051 | D8: 5000 | E8: City | F8: Cash | H8: =TEXT(I8, "dddd") -> Friday | I8: 46052 | J8: {=sum(IF(($P$3:$P$100=I8), $T$3:$T$100, 0))} -> 10 | L8: bKash | M8: {=N8 - sum(IF(($E$4:$E$49=L8), $D$4:$D$39 + $C$4:$C$39, 0)) + sum(IF(($F$4:$F$49=L8), $D$4:$D$39, 0)) - sum(IF(($S$3:$S$100=L8), $T$3:$T$100, 0))} -> 66 | N8: ='Jan 26'!M8 -> 136 | P8: 46050 | Q8: Bazar | R8: Fruits | S8: Cash | T8: =240+150+20 -> 410 | U8: dab + boroi
B9: 46059 | C9: 15 | D9: 10000 | E9: SCB | F9: Cash | H9: =TEXT(I9, "dddd") -> Saturday | I9: 46053 | J9: {=sum(IF(($P$3:$P$100=I9), $T$3:$T$100, 0))} -> 1590 | L9: Nagad | M9: {=N9 - sum(IF(($E$4:$E$49=L9), $D$4:$D$39 + $C$4:$C$39, 0)) + sum(IF(($F$4:$F$49=L9), $D$4:$D$39, 0)) - sum(IF(($S$3:$S$100=L9), $T$3:$T$100, 0))} -> 2 | N9: ='Jan 26'!M9 -> 2 | P9: 46050 | Q9: RentAndPaybill | R9: HouseRent | S9: Cash | T9: 13000
B10: 46069 | D10: 1500 | E10: City | F10: Cash | H10: =TEXT(I10, "dddd") -> Sunday | I10: 46054 | J10: {=sum(IF(($P$3:$P$100=I10), $T$3:$T$100, 0))} -> 485 | L10: LendTaken | M10: =N10-10000 -> 30000 | N10: ='Jan 26'!M10 -> 40000 | P10: 46050 | Q10: RentAndPaybill | R10: GassBill | S10: Cash | T10: 1080
B11: 46071 | C11: 12 | D11: 500 | E11: SBL | F11: bKash | H11: =TEXT(I11, "dddd") -> Monday | I11: 46055 | J11: {=sum(IF(($P$3:$P$100=I11), $T$3:$T$100, 0))} -> 2630 | L11: LendGiven | M11: {=N11 - sum(IF(($E$4:$E$49=L11), $D$4:$D$39 + $C$4:$C$39, 0)) + sum(IF(($F$4:$F$49=L11), $D$4:$D$39, 0)) - sum(IF(($S$3:$S$100=L11), $T$3:$T$100, 0))} -> 7550 | N11: ='Jan 26'!M11 -> 7550 | P11: 46050 | Q11: RentAndPaybill | R11: ServiceBill | S11: Cash | T11: 800
B12: 46072 | C12: 10 | D12: 1180 | E12: SBL | F12: City | H12: =TEXT(I12, "dddd") -> Tuesday | I12: 46056 | J12: {=sum(IF(($P$3:$P$100=I12), $T$3:$T$100, 0))} -> 2685 | L12: City | M12: {=N12 - sum(IF(($E$4:$E$49=L12), $D$4:$D$39 + $C$4:$C$39, 0)) + sum(IF(($F$4:$F$49=L12), $D$4:$D$39, 0)) - sum(IF(($S$3:$S$100=L12), $T$3:$T$100, 0))} -> 4106 | N12: ='Jan 26'!M12 -> 1124 | P12: 46050 | Q12: Bazar | R12: AdvGiven | S12: Cash | T12: =5000+120 -> 5120
B13: 46072 | D13: 200 | E13: City | F13: bKash | H13: =TEXT(I13, "dddd") -> Wednesday | I13: 46057 | J13: {=sum(IF(($P$3:$P$100=I13), $T$3:$T$100, 0))} -> 0 | N13: ='Jan 26'!M13 | P13: 46051 | Q13: HouseholdAccessories | R13: Medicine | S13: SCB | T13: 2600 | U13: test for ammu
B14: 46074 | D14: 2990 | E14: SCB | F14: City | H14: =TEXT(I14, "dddd") -> Thursday | I14: 46058 | J14: {=sum(IF(($P$3:$P$100=I14), $T$3:$T$100, 0))} -> 0 | P14: 46051 | Q14: HouseholdAccessories | R14: Medicine | S14: Cash | T14: 320 | U14: for suba
B15: 46074 | D15: 10000 | E15: Add | F15: Cash | H15: =TEXT(I15, "dddd") -> Friday | I15: 46059 | J15: {=sum(IF(($P$3:$P$100=I15), $T$3:$T$100, 0))} -> 3530 | L15: LEND GIVEN TO | N15: =sum(M17:M22) -> 7550 | P15: 46051 | Q15: Bazar | R15: Others | S15: SCB | T15: 225 | U15: til er naru + mama
H16: =TEXT(I16, "dddd") -> Saturday | I16: 46060 | J16: {=sum(IF(($P$3:$P$100=I16), $T$3:$T$100, 0))} -> 2230 | L16: Date | M16: Amount | N16: Given To | P16: 46052 | Q16: Donation | R16: Donation | S16: Cash | T16: 10
H17: =TEXT(I17, "dddd") -> Sunday | I17: 46061 | J17: {=sum(IF(($P$3:$P$100=I17), $T$3:$T$100, 0))} -> 1690 | L17: 45774 | M17: 2500 | N17: Rajib vai | P17: 46052 | Q17: Donation | R17: Unknown | S17: Cash | T17: 0
H18: =TEXT(I18, "dddd") -> Monday | I18: 46062 | J18: {=sum(IF(($P$3:$P$100=I18), $T$3:$T$100, 0))} -> 30 | M18: 3000 | N18: Rafi vai | P18: 46051 | Q18: ExtraExpenses | R18: AiSubs | S18: City | T18: 2475
H19: =TEXT(I19, "dddd") -> Tuesday | I19: 46063 | J19: {=sum(IF(($P$3:$P$100=I19), $T$3:$T$100, 0))} -> 930 | L19: 45979 | M19: 2050 | N19: Jahid | P19: 46053 | Q19: HouseholdAccessories | R19: Medicine | S19: Cash | T19: =1000+590 -> 1590 | U19: doc + med for ammu
H20: =TEXT(I20, "dddd") -> Wednesday | I20: 46064 | J20: {=sum(IF(($P$3:$P$100=I20), $T$3:$T$100, 0))} -> 180 | P20: 46054 | Q20: HouseholdAccessories | R20: DailyAccessories | S20: SCB | T20: 220 | U20: toothpest
H21: =TEXT(I21, "dddd") -> Thursday | I21: 46065 | J21: {=sum(IF(($P$3:$P$100=I21), $T$3:$T$100, 0))} -> 0 | P21: 46054 | Q21: Bazar | R21: Fruits | S21: Cash | T21: 250 | U21: dalim
H22: =TEXT(I22, "dddd") -> Friday | I22: 46066 | J22: {=sum(IF(($P$3:$P$100=I22), $T$3:$T$100, 0))} -> 100 | P22: 46054 | Q22: ExtraExpenses | R22: Tea | S22: Cash | T22: 15
H23: =TEXT(I23, "dddd") -> Saturday | I23: 46067 | J23: {=sum(IF(($P$3:$P$100=I23), $T$3:$T$100, 0))} -> 450 | P23: 46055 | Q23: Bazar | R23: Fruits | S23: Cash | T23: 110 | U23: stobary
H24: =TEXT(I24, "dddd") -> Sunday | I24: 46068 | J24: {=sum(IF(($P$3:$P$100=I24), $T$3:$T$100, 0))} -> 320 | L24: LEND TAKEN FROM | N24: =sum(N26:N31) -> 10000 | P24: 46055 | Q24: Donation | R24: Donation | S24: Cash | T24: 20
H25: =TEXT(I25, "dddd") -> Monday | I25: 46069 | J25: {=sum(IF(($P$3:$P$100=I25), $T$3:$T$100, 0))} -> 1000 | L25: Date | M25: Taken From | N25: Amount | P25: 46055 | Q25: Savings | R25: EximBank_2.5 | S25: SCB | T25: 2500
H26: =TEXT(I26, "dddd") -> Tuesday | I26: 46070 | J26: {=sum(IF(($P$3:$P$100=I26), $T$3:$T$100, 0))} -> 2460 | L26: 46075 | M26: Ammu | N26: 10000 | P26: 46056 | Q26: Bazar | R26: DailyBazar | S26: Cash | T26: 2000 | U26: buff
H27: =TEXT(I27, "dddd") -> Wednesday | I27: 46071 | J27: {=sum(IF(($P$3:$P$100=I27), $T$3:$T$100, 0))} -> 965 | P27: 46056 | Q27: HouseholdAccessories | R27: DailyAccessories | S27: SCB | T27: 100 | U27: tishu
H28: =TEXT(I28, "dddd") -> Thursday | I28: 46072 | J28: {=sum(IF(($P$3:$P$100=I28), $T$3:$T$100, 0))} -> 641 | P28: 46056 | Q28: Bazar | R28: Others | S28: SCB | T28: 20
H29: =TEXT(I29, "dddd") -> Friday | I29: 46073 | J29: {=sum(IF(($P$3:$P$100=I29), $T$3:$T$100, 0))} -> 100 | P29: 46056 | Q29: HouseholdAccessories | R29: Medicine | S29: Cash | T29: 65
H30: =TEXT(I30, "dddd") -> Saturday | I30: 46074 | J30: {=sum(IF(($P$3:$P$100=I30), $T$3:$T$100, 0))} -> 2870 | P30: 46056 | Q30: RentAndPaybill | R30: ElectricBill_Dhk | S30: City | T30: 500
H31: =TEXT(I31, "dddd") -> Sunday | I31: 46075 | J31: {=sum(IF(($P$3:$P$100=I31), $T$3:$T$100, 0))} -> 0 | P31: 46059 | Q31: Bazar | R31: Fruits | S31: Cash | T31: 100 | U31: dab
H32: =TEXT(I32, "dddd") -> Monday | I32: 46076 | J32: {=sum(IF(($P$3:$P$100=I32), $T$3:$T$100, 0))} -> 150 | P32: 46059 | Q32: Bazar | R32: Others | S32: Cash | T32: =10+20+30 -> 60
H33: =TEXT(I33, "dddd") -> Tuesday | I33: 46077 | J33: {=sum(IF(($P$3:$P$100=I33), $T$3:$T$100, 0))} -> 420 | L33: Savings | N33: =sum(N35:N40) -> 0 | P33: 46059 | Q33: ExtraExpenses | R33: ExtraExpenses | S33: Cash | T33: =200+10+2160+1000 -> 3370 | U33: dress for suba + khelna
H34: =TEXT(I34, "dddd") -> Wednesday | I34: 46078 | J34: {=sum(IF(($P$3:$P$100=I34), $T$3:$T$100, 0))} -> 113 | L34: Type | M34: Current | N34: Prev | P34: 46060 | Q34: Bazar | R34: AdvGiven | S34: Cash | T34: 2000
H35: =TEXT(I35, "dddd") -> Thursday | I35: 46079 | J35: {=sum(IF(($P$3:$P$100=I35), $T$3:$T$100, 0))} -> 0 | L35: {=INDIRECT("SavingsAcc")} -> EximBank_2.5 | P35: 46060 | Q35: HouseholdAccessories | R35: Medicine | S35: Cash | T35: =70+20 -> 90
J36: {=sum(IF(($P$3:$P$100=I36), $T$3:$T$100, 0))} -> 0 | L36: CityBank_10 | P36: 46060 | Q36: Bazar | R36: Others | S36: Cash | T36: =40+100 -> 140 | U36: nan + momo
L37: BracBank_10 | P37: 46061 | Q37: Bazar | R37: Fruits | S37: Cash | T37: =200+300 -> 500 | U37: boroi + dalim
L38: SBL_root | P38: 46061 | Q38: Bazar | R38: DailyBazar | S38: Cash | T38: =500+100+350 -> 950 | U38: rooh afja + khejur
L39: Exim_root | P39: 46061 | Q39: Donation | R39: Donation | S39: Cash | T39: =20+10+10 -> 40
P40: 46061 | Q40: Bazar | R40: AdvGiven | S40: Cash | T40: 100 | U40: suba
P41: 46061 | Q41: Donation | R41: Unknown | S41: Cash | T41: 100
B42: B U D G E T | P42: 46062 | Q42: Bazar | R42: Others | S42: Cash | T42: 30
P43: 46063 | Q43: Bazar | R43: Others | S43: SCB | T43: 900 | U43: doi + misti
B44: Category | E44: Budget | F44: Subcategory | I44: Budget | J44: Cost | L44: TGC | P44: 46064 | Q44: HouseholdAccessories | R44: Medicine | S44: Cash | T44: =100+80 -> 180 | U44: mumps + cold
B45: RentAndPaybill | E45: =Sum(I45:I50) -> 17070 | F45: {=INDIRECT("Subcategory")} -> HouseRent | I45: 13000 | J45: {=sum(IF(($R$3:$R$100=F45), $T$3:$T$100, 0))} -> 13000 | L45: =sum(J45:J50) -> 16921 | M45: =I45+I48+I50 -> 14880 | P45: 46066 | Q45: Bazar | R45: Others | S45: Cash | T45: 100 | U45: nuts
F46: ElectricBill_Dhk | I46: 1000 | J46: {=sum(IF(($R$3:$R$100=F46), $T$3:$T$100, 0))} -> 1000 | P46: 46067 | Q46: ExtraExpenses | R46: ExtraExpenses | S46: Cash | T46: =150+100+40 -> 290 | U46: hair cut + khelna
F47: ElectricBill_Swk | I47: 350 | J47: {=sum(IF(($R$3:$R$100=F47), $T$3:$T$100, 0))} -> 201 | P47: 46067 | Q47: HouseholdAccessories | R47: Medicine | S47: Cash | T47: =160 -> 160 | U47: fexo + cold syrup
F48: GassBill | I48: 1080 | J48: {=sum(IF(($R$3:$R$100=F48), $T$3:$T$100, 0))} -> 1080 | P48: 46068 | Q48: Bazar | R48: Fruits | S48: Cash | T48: =320 -> 320 | U48: komla
F49: WifiBill | I49: 840 | J49: {=sum(IF(($R$3:$R$100=F49), $T$3:$T$100, 0))} -> 840 | P49: 46069 | Q49: Bazar | R49: AdvGiven | S49: Cash | T49: 1000
F50: ServiceBill | I50: 800 | J50: {=sum(IF(($R$3:$R$100=F50), $T$3:$T$100, 0))} -> 800 | P50: 46070 | Q50: Bazar | R50: Fruits | S50: Cash | T50: =800 -> 800 | U50: khejur
B51: Bazar | E51: =Sum(I51:I54) -> 17000 | F51: DailyBazar | I51: 4500 | J51: {=sum(IF(($R$3:$R$100=F51), $T$3:$T$100, 0))} -> 4350 | L51: =sum(J51:J54) -> 17395 | P51: 46070 | Q51: Bazar | R51: DailyBazar | S51: Cash | T51: =1000+400 -> 1400 | U51: chingri + kacki
F52: Fruits | I52: 2500 | J52: {=sum(IF(($R$3:$R$100=F52), $T$3:$T$100, 0))} -> 2910 | P52: 46070 | Q52: HouseholdAccessories | R52: Medicine | S52: Cash | T52: =260 -> 260 | U52: ammu
F53: AdvGiven | I53: 8000 | J53: {=sum(IF(($R$3:$R$100=F53), $T$3:$T$100, 0))} -> 8220 | P53: 46071 | Q53: RentAndPaybill | R53: WifiBill | S53: bKash | T53: 840
F54: Others | I54: 2000 | J54: {=sum(IF(($R$3:$R$100=F54), $T$3:$T$100, 0))} -> 1915 | P54: 46071 | Q54: ExtraExpenses | R54: Tea | S54: Cash | T54: 15
B55: HouseholdAccessories | E55: =sum(I55:I57) -> 5500 | F55: HouseholdAccessories | I55: 200 | J55: {=sum(IF(($R$3:$R$100=F55), $T$3:$T$100, 0))} -> 0 | L55: =sum(J55:J58) -> 5875 | P55: 46071 | Q55: HouseholdAccessories | R55: Medicine | S55: Cash | T55: 110
F56: DailyAccessories | I56: 300 | J56: {=sum(IF(($R$3:$R$100=F56), $T$3:$T$100, 0))} -> 320 | P56: 46072 | Q56: RentAndPaybill | R56: ElectricBill_Swk | S56: bKash | T56: 201
F57: Medicine | I57: 5000 | J57: {=sum(IF(($R$3:$R$100=F57), $T$3:$T$100, 0))} -> 5525 | P57: 46072 | Q57: Bazar | R57: Others | S57: Cash | T57: 100
B58: MobileInternet | E58: =I58+I59 -> 400 | F58: ForMine | I58: 100 | J58: {=sum(IF(($R$3:$R$100=F58), $T$3:$T$100, 0))} -> 30 | L58: =J58+J59 -> 729 | P58: 46072 | Q58: MobileInternet | R58: ForOthers | S58: bKash | T58: =210+130 -> 340
F59: ForOthers | I59: 300 | J59: {=sum(IF(($R$3:$R$100=F59), $T$3:$T$100, 0))} -> 699 | P59: 46063 | Q59: MobileInternet | R59: ForMine | S59: bKash | T59: 30
B60: ExtraExpenses | E60: =I60+I61+I62+I63+I64 -> 6550 | F60: Tea | I60: 50 | J60: {=sum(IF(($R$3:$R$100=F60), $T$3:$T$100, 0))} -> 45 | L60: =J60+J61+J62+J63+J64 -> 9050 | P60: 46073 | Q60: Donation | R60: Donation | S60: Cash | T60: 100
F61: Travel | I61: 0 | J61: {=sum(IF(($R$3:$R$100=F61), $T$3:$T$100, 0))} -> 20 | P61: 46074 | Q61: ExtraExpenses | R61: ExtraExpenses | S61: Cash | T61: =1400+1400+50 -> 2850 | U61: tshirt+juta
F62: AiSubs | I62: 2500 | J62: {=sum(IF(($R$3:$R$100=F62), $T$3:$T$100, 0))} -> 2475 | P62: 46074 | Q62: Bazar | R62: Others | S62: Cash | T62: 20
F63: BooksOrCourses | I63: 0 | J63: {=sum(IF(($R$3:$R$100=F63), $T$3:$T$100, 0))} -> 0 | P63: 46076 | Q63: HouseholdAccessories | R63: Medicine | S63: Cash | T63: 150
F64: ExtraExpenses | I64: 4000 | J64: {=sum(IF(($R$3:$R$100=F64), $T$3:$T$100, 0))} -> 6510 | P64: 46077 | Q64: Bazar | R64: Fruits | S64: Cash | T64: =420 -> 420
B65: Savings | E65: =sum(I65:I68) -> 2500 | F65: EximBank_2.5 | I65: 2500 | J65: {=sum(IF(($R$3:$R$100=F65), $T$3:$T$100, 0))} -> 2500 | L65: =sum(J65:J68) -> 2500 | P65: 46078 | Q65: ExtraExpenses | R65: Travel | S65: Cash | T65: 20
F66: CityBank_10 | I66: 0 | J66: {=sum(IF(($R$3:$R$100=F66), $T$3:$T$100, 0))} -> 0 | P66: 46078 | Q66: Donation | R66: Donation | S66: Cash | T66: =30 -> 30
F67: BracBank_10 | I67: 0 | J67: {=sum(IF(($R$3:$R$100=F67), $T$3:$T$100, 0))} -> 0 | P67: 46078 | Q67: MobileInternet | R67: ForOthers | S67: bKash | T67: 50
F68: SBL_root | I68: 0 | J68: {=sum(IF(($R$3:$R$100=F68), $T$3:$T$100, 0))} -> 0 | P68: 46078 | Q68: Pay | R68: Unknown | S68: City | T68: 13 | U68: maybe int. tran.
B69: Donation | F69: Exim_root | I69: 200 | J69: {=sum(IF(($R$3:$R$100=F69), $T$3:$T$100, 0))} -> 0
F70: Donation | J70: {=sum(IF(($R$3:$R$100=F70), $T$3:$T$100, 0))} -> 200
B71: Pay | F71: Unknown | J71: {=sum(IF(($R$3:$R$100=F71), $T$3:$T$100, 0))} -> 113
F72: CityService | J72: {=sum(IF(($R$3:$R$100=F72), $T$3:$T$100, 0))} -> 0
F73: SblService
H75: Total | I75: =SUM(I45:I72) -> 49220 | J75: =SUM(J45:J72) -> 52753 | L75: =I75-J75 -> -3533
H76: Non-Cash | I76: =I46+I47+I49+I58+I59+I63+I67+I68+I62+I64+I65+I66 -> 11590 | J76: =J46+J47+J49+J58+J59+J63+J67+J68+J62+J64+J65+J66 -> 14255 | L76: =I76-J76 -> -2665
H77: Cash | I77: =I75-I76 -> 37630 | J77: =J75-J76 -> 38498 | L77: =I77-J77 -> -868
B82: E I D - B U D G E T | I82: =sum(I85:I116) -> 25000 | J82: =sum(J85:J116) -> 5960 | L82: =I82-I82 -> 0
B84: Category | E84: Budget | F84: Subcategory | I84: Budget | J84: Cost | L84: TGC
B85: Shoping -suba | E85: =SUM(I85:I88) -> 5000 | F85: dress | I85: 3000 | J85: =2160+1000 -> 3160 | L85: =sum(I85:I88) - sum(J85:J88) -> 440
F86: juta | I86: 2000 | J86: 1400
B89: shoping -ammu | E89: =SUM(I89:I92) -> 500 | F89: dress-3pc | I89: 500 | L89: =sum(I89:I92) - sum(J89:J92) -> 500
B93: shoping -nodi | E93: =SUM(I93:I96) -> 500 | F93: dress-3pc | I93: 500 | L93: =sum(I93:I96) - sum(J93:J96) -> 500
B97: shoping -abbu | E97: =SUM(I97:I100) -> 3000 | F97: t-shirt | I97: 1000 | J97: 1400 | L97: =sum(I97:I100) - sum(J97:J100) -> 1600
F98: t-shirt Reg 2x | I98: 1000
F99: Lungi | I99: 1000
B101: shoping -me | E101: =SUM(I101:I104) -> 2000 | F101: Juta | I101: 2000 | L101: =sum(I101:I104) - sum(J101:J104) -> 2000
F102: x
B105: travel | E105: =SUM(I105:I108) -> 7000 | F105: Dhk to Swk 3x | I105: 3000 | L105: =sum(I105:I108) - sum(J105:J108) -> 7000
F106: Swk to Dhk 3x | I106: 3000
F107: other cost | I107: 1000
B109: Bazar | E109: =SUM(I109:I112) -> 5000 | F109: bazar | I109: 5000 | L109: =sum(I109:I112) - sum(J109:J112) -> 5000
B113: Others | E113: =SUM(I113:I116) -> 2000 | F113: donation 1 | I113: 1000 | L113: =sum(I113:I116) - sum(J113:J116) -> 2000
F114: Fetra | I114: 1000
F115: Salami
F116: x

Sheet March 26
B2: T r a n s a c t i o n & P a y | H2: DAY | I2: Date | J2: =sum(J4:J39) -> 61489 | L2: FINANCIAL STATUS | N2: =M4+M5+M8+M9+M12 -> 1110 | P2: Date | Q2: Category | R2: Subcategory | S2: Payment Method | T2: Amount | U2: Remarks | W2: R e m i n d M e
B3: Date | C3: Cost | D3: Amount | E3: FROM | F3: TO | J3: Cost | L3: Type | M3: Current Status | N3: Start with | P3: 46079 | Q3: HouseholdAccessories | R3: Medicine | S3: Cash | T3: =125 -> 125 | W3: Date | X3: Task
B4: 46078 | D4: 49500 | E4: Add | F4: SCB | H4: =TEXT(I4, "dddd") -> Thursday | I4: 46079 | J4: {=sum(IF(($P$3:$P$100=I4), $T$3:$T$100, 0))} -> 2750 | L4: {=INDIRECT("Account")} -> Cash | M4: {=N4 - sum(IF(($E$4:$E$49=L4), $D$4:$D$39 + $C$4:$C$39, 0)) + sum(IF(($F$4:$F$49=L4), $D$4:$D$39, 0)) - sum(IF(($S$3:$S$100=L4), $T$3:$T$100, 0))} -> 565 | N4: ='Feb 26'!M4 -> 6540 | P4: 46079 | Q4: Donation | R4: Donation | S4: Cash | T4: 25 | W4: 46099 | X4: Ticket Dhk to Swk
B5: 46079 | D5: 20000 | E5: SCB | F5: City | H5: =TEXT(I5, "dddd") -> Friday | I5: 46080 | J5: {=sum(IF(($P$3:$P$100=I5), $T$3:$T$100, 0))} -> 8020 | L5: SCB | M5: {=N5 - sum(IF(($E$4:$E$49=L5), $D$4:$D$39 + $C$4:$C$39, 0)) + sum(IF(($F$4:$F$49=L5), $D$4:$D$39, 0)) - sum(IF(($S$3:$S$100=L5), $T$3:$T$100, 0))} -> 417 | N5: ='Feb 26'!M5 -> 7 | P5: 46079 | Q5: ExtraExpenses | R5: ExtraExpenses | S5: Cash | T5: 2600 | U5: tshirt | W5: 46107 | X5: Ticket Swk to Dhk
B6: 46079 | D6: 20000 | E6: City | F6: Cash | H6: =TEXT(I6, "dddd") -> Saturday | I6: 46081 | J6: {=sum(IF(($P$3:$P$100=I6), $T$3:$T$100, 0))} -> 2960 | L6: SBL | M6: {=N6 - sum(IF(($E$4:$E$49=L6), $D$4:$D$39 + $C$4:$C$39, 0)) + sum(IF(($F$4:$F$49=L6), $D$4:$D$39, 0)) - sum(IF(($S$3:$S$100=L6), $T$3:$T$100, 0))} -> 9 | N6: ='Feb 26'!M6 -> 9 | P6: 46080 | Q6: Donation | R6: Donation | S6: Cash | T6: 20 | W6: 46085 | X6: Reminder for adv ticket
B7: 46085 | D7: 5000 | E7: SCB | F7: City | H7: =TEXT(I7, "dddd") -> Sunday | I7: 46082 | J7: {=sum(IF(($P$3:$P$100=I7), $T$3:$T$100, 0))} -> 0 | L7: EXIM | M7: {=N7 - sum(IF(($E$4:$E$49=L7), $D$4:$D$39 + $C$4:$C$39, 0)) + sum(IF(($F$4:$F$49=L7), $D$4:$D$39, 0)) - sum(IF(($S$3:$S$100=L7), $T$3:$T$100, 0))} -> 285 | N7: ='Feb 26'!M7 -> 285 | P7: 46080 | Q7: Bazar | R7: AdvGiven | S7: Cash | T7: 8000
B8: 46085 | D8: 5000 | E8: City | F8: Cash | H8: =TEXT(I8, "dddd") -> Monday | I8: 46083 | J8: {=sum(IF(($P$3:$P$100=I8), $T$3:$T$100, 0))} -> 0 | L8: bKash | M8: {=N8 - sum(IF(($E$4:$E$49=L8), $D$4:$D$39 + $C$4:$C$39, 0)) + sum(IF(($F$4:$F$49=L8), $D$4:$D$39, 0)) - sum(IF(($S$3:$S$100=L8), $T$3:$T$100, 0))} -> 7 | N8: ='Feb 26'!M8 -> 66 | P8: 46081 | Q8: HouseholdAccessories | R8: DailyAccessories | S8: Cash | T8: 260 | U8: good night refill
B9: 46091 | C9: 10 | D9: 2040 | E9: LendGiven | F9: bKash | H9: =TEXT(I9, "dddd") -> Tuesday | I9: 46084 | J9: {=sum(IF(($P$3:$P$100=I9), $T$3:$T$100, 0))} -> 0 | L9: Nagad | M9: {=N9 - sum(IF(($E$4:$E$49=L9), $D$4:$D$39 + $C$4:$C$39, 0)) + sum(IF(($F$4:$F$49=L9), $D$4:$D$39, 0)) - sum(IF(($S$3:$S$100=L9), $T$3:$T$100, 0))} -> 2 | N9: ='Feb 26'!M9 -> 2 | P9: 46081 | Q9: Bazar | R9: Others | S9: Cash | T9: 25
B10: 46098 | D10: 15000 | E10: SCB | F10: City | H10: =TEXT(I10, "dddd") -> Wednesday | I10: 46085 | J10: {=sum(IF(($P$3:$P$100=I10), $T$3:$T$100, 0))} -> 15025 | L10: LendTaken | M10: =N10-10000 -> 20000 | N10: ='Feb 26'!M10 -> 30000 | P10: 46081 | Q10: ExtraExpenses | R10: ExtraExpenses | S10: Cash | T10: 200 | U10: sunglass for suba
B11: 46099 | D11: 4000 | E11: City | F11: bKash | H11: =TEXT(I11, "dddd") -> Thursday | I11: 46086 | J11: {=sum(IF(($P$3:$P$100=I11), $T$3:$T$100, 0))} -> 2210 | L11: LendGiven | M11: {=N11 - sum(IF(($E$4:$E$49=L11), $D$4:$D$39 + $C$4:$C$39, 0)) + sum(IF(($F$4:$F$49=L11), $D$4:$D$39, 0)) - sum(IF(($S$3:$S$100=L11), $T$3:$T$100, 0))} -> 5500 | N11: ='Feb 26'!M11 -> 7550 | P11: 46085 | Q11: ExtraExpenses | R11: Tea | S11: Cash | T11: 25
B12: 46099 | D12: 12000 | E12: City | F12: Cash | H12: =TEXT(I12, "dddd") -> Friday | I12: 46087 | J12: {=sum(IF(($P$3:$P$100=I12), $T$3:$T$100, 0))} -> 50 | L12: City | M12: {=N12 - sum(IF(($E$4:$E$49=L12), $D$4:$D$39 + $C$4:$C$39, 0)) + sum(IF(($F$4:$F$49=L12), $D$4:$D$39, 0)) - sum(IF(($S$3:$S$100=L12), $T$3:$T$100, 0))} -> 119 | N12: ='Feb 26'!M12 -> 4106 | P12: 46085 | Q12: RentAndPaybill | R12: HouseRent | S12: Cash | T12: 13000
B13: 46099 | D13: =200+100 -> 300 | E13: Add | F13: Cash | H13: =TEXT(I13, "dddd") -> Saturday | I13: 46088 | J13: {=sum(IF(($P$3:$P$100=I13), $T$3:$T$100, 0))} -> 2500 | N13: ='Feb 26'!M13 | P13: 46085 | Q13: RentAndPaybill | R13: GassBill | S13: Cash | T13: 1080
B14: 46108 | D14: 500 | E14: City | F14: bKash | H14: =TEXT(I14, "dddd") -> Sunday | I14: 46089 | J14: {=sum(IF(($P$3:$P$100=I14), $T$3:$T$100, 0))} -> 1240 | P14: 46085 | Q14: RentAndPaybill | R14: ServiceBill | S14: Cash | T14: 800
B15: 46108 | D15: 50 | E15: Add | F15: bKash | H15: =TEXT(I15, "dddd") -> Monday | I15: 46090 | J15: {=sum(IF(($P$3:$P$100=I15), $T$3:$T$100, 0))} -> 4710 | L15: LEND GIVEN TO | N15: =sum(M17:M22) -> 7550 | P15: 46085 | Q15: Bazar | R15: AdvGiven | S15: Cash | T15: 120
B16: 46103 | D16: 12 | E16: City | F16: Pay | H16: =TEXT(I16, "dddd") -> Tuesday | I16: 46091 | J16: {=sum(IF(($P$3:$P$100=I16), $T$3:$T$100, 0))} -> 500 | L16: Date | M16: Given To | N16: Amount | P16: 46081 | Q16: ExtraExpenses | R16: AiSubs | S16: City | T16: 2475
H17: =TEXT(I17, "dddd") -> Wednesday | I17: 46092 | J17: {=sum(IF(($P$3:$P$100=I17), $T$3:$T$100, 0))} -> 0 | L17: 45774 | M17: 2500 | N17: Rajib vai | P17: 46086 | Q17: ExtraExpenses | R17: Tea | S17: Cash | T17: =50+60+10 -> 120 | U17: meet rafi vai
H18: =TEXT(I18, "dddd") -> Thursday | I18: 46093 | J18: {=sum(IF(($P$3:$P$100=I18), $T$3:$T$100, 0))} -> 85 | M18: 3000 | N18: Rafi vai | P18: 46086 | Q18: ExtraExpenses | R18: ExtraExpenses | S18: SCB | T18: 2090 | U18: shirt for me
H19: =TEXT(I19, "dddd") -> Friday | I19: 46094 | J19: {=sum(IF(($P$3:$P$100=I19), $T$3:$T$100, 0))} -> 40 | L19: 45979 | M19: 2050 | N19: Jahid | P19: 46087 | Q19: Donation | R19: Donation | S19: Cash | T19: 50
H20: =TEXT(I20, "dddd") -> Saturday | I20: 46095 | J20: {=sum(IF(($P$3:$P$100=I20), $T$3:$T$100, 0))} -> 920 | P20: 46089 | Q20: Bazar | R20: Fruits | S20: Cash | T20: =650+140 -> 790 | U20: khejur + komla
H21: =TEXT(I21, "dddd") -> Sunday | I21: 46096 | J21: {=sum(IF(($P$3:$P$100=I21), $T$3:$T$100, 0))} -> 0 | P21: 46089 | Q21: HouseholdAccessories | R21: Medicine | S21: Cash | T21: =140+170+110 -> 420 | U21: fexo+xinc+napa+sargel2+joytrip
H22: =TEXT(I22, "dddd") -> Monday | I22: 46097 | J22: {=sum(IF(($P$3:$P$100=I22), $T$3:$T$100, 0))} -> 500 | P22: 46090 | Q22: ExtraExpenses | R22: Travel | S22: Cash | T22: 90 | U22: office to linkroad
H23: =TEXT(I23, "dddd") -> Tuesday | I23: 46098 | J23: {=sum(IF(($P$3:$P$100=I23), $T$3:$T$100, 0))} -> 600 | P23: 46090 | Q23: ExtraExpenses | R23: Tea | S23: Cash | T23: 80 | U23: meet with rafi vai
H24: =TEXT(I24, "dddd") -> Wednesday | I24: 46099 | J24: {=sum(IF(($P$3:$P$100=I24), $T$3:$T$100, 0))} -> 4775 | L24: LEND TAKEN FROM | N24: =sum(N26:N31) -> 10000 | P24: 46090 | Q24: Donation | R24: Unknown | S24: Cash | T24: 40
H25: =TEXT(I25, "dddd") -> Thursday | I25: 46100 | J25: {=sum(IF(($P$3:$P$100=I25), $T$3:$T$100, 0))} -> 6019 | L25: Date | M25: Taken From | N25: Amount | P25: 46090 | Q25: ExtraExpenses | R25: Travel | S25: SCB | T25: 4500 | U25: dhk to bar adv ticket
H26: =TEXT(I26, "dddd") -> Friday | I26: 46101 | J26: {=sum(IF(($P$3:$P$100=I26), $T$3:$T$100, 0))} -> 4810 | L26: 46075 | M26: ammu | N26: 10000 | P26: 46089 | Q26: MobileInternet | R26: ForMine | S26: bKash | T26: 30
H27: =TEXT(I27, "dddd") -> Saturday | I27: 46102 | J27: {=sum(IF(($P$3:$P$100=I27), $T$3:$T$100, 0))} -> 417 | P27: 46088 | Q27: Savings | R27: EximBank_2.5 | S27: SCB | T27: 2500
H28: =TEXT(I28, "dddd") -> Sunday | I28: 46103 | J28: {=sum(IF(($P$3:$P$100=I28), $T$3:$T$100, 0))} -> 0 | P28: 46091 | Q28: Donation | R28: Donation | S28: Cash | T28: 500 | U28: edi for soinik
H29: =TEXT(I29, "dddd") -> Monday | I29: 46104 | J29: {=sum(IF(($P$3:$P$100=I29), $T$3:$T$100, 0))} -> 225 | P29: 46093 | Q29: HouseholdAccessories | R29: Medicine | S29: Cash | T29: 70
H30: =TEXT(I30, "dddd") -> Tuesday | I30: 46105 | J30: {=sum(IF(($P$3:$P$100=I30), $T$3:$T$100, 0))} -> 0 | P30: 46093 | Q30: Donation | R30: Donation | S30: Cash | T30: =15 -> 15
H31: =TEXT(I31, "dddd") -> Wednesday | I31: 46106 | J31: {=sum(IF(($P$3:$P$100=I31), $T$3:$T$100, 0))} -> 0 | P31: 46094 | Q31: Donation | R31: Donation | S31: Cash | T31: =20+20 -> 40
H32: =TEXT(I32, "dddd") -> Thursday | I32: 46107 | J32: {=sum(IF(($P$3:$P$100=I32), $T$3:$T$100, 0))} -> 208 | P32: 46095 | Q32: Bazar | R32: Fruits | S32: Cash | T32: =530+140 -> 670 | U32: khejur + dalim
H33: =TEXT(I33, "dddd") -> Friday | I33: 46108 | J33: {=sum(IF(($P$3:$P$100=I33), $T$3:$T$100, 0))} -> 2645 | L33: Savings | N33: =sum(M35:M39) -> 37500 | P33: 46095 | Q33: Bazar | R33: Others | S33: Cash | T33: =200+50 -> 250 | U33: halim + jilipi
H34: =TEXT(I34, "dddd") -> Saturday | I34: 46109 | J34: {=sum(IF(($P$3:$P$100=I34), $T$3:$T$100, 0))} -> 280 | L34: Type | M34: Current | N34: Prev | P34: 46097 | Q34: Donation | R34: Donation | S34: Cash | T34: 500 | U34: shofiq mama
H35: =TEXT(I35, "dddd") -> Sunday | I35: 46110 | J35: {=sum(IF(($P$3:$P$100=I35), $T$3:$T$100, 0))} -> 0 | L35: {=INDIRECT("SavingsAcc")} -> EximBank_2.5 | M35: {=N35+sum(IF(($R$3:$R$100=L35), $T$3:$T$100, 0))} -> 37500 | N35: =14*2500 -> 35000 | P35: 46098 | Q35: ExtraExpenses | R35: ExtraExpenses | S35: Cash | T35: 600 | U35: hair
J36: {=sum(IF(($P$3:$P$100=I36), $T$3:$T$100, 0))} -> 0 | L36: CityBank_10 | P36: 46099 | Q36: HouseholdAccessories | R36: Medicine | S36: Cash | T36: 200
L37: BracBank_10 | P37: 46099 | Q37: Bazar | R37: Others | S37: Cash | T37: 175
L38: SBL_root | P38: 46099 | Q38: ExtraExpenses | R38: Travel | S38: bKash | T38: =4500-100 -> 4400
L39: Exim_root | P39: 46100 | Q39: Donation | R39: Donation | S39: Cash | T39: 50
P40: 46100 | Q40: ExtraExpenses | R40: Travel | S40: Cash | T40: =400+200 -> 600 | U40: goriar par to swk and to home
P41: 46100 | Q41: ExtraExpenses | R41: Tea | S41: Cash | T41: =50+50 -> 100
B42: B U D G E T | P42: 46100 | Q42: HouseholdAccessories | R42: DailyAccessories | S42: Cash | T42: 20
P43: 46100 | Q43: ExtraExpenses | R43: BooksOrCourses | S43: Cash | T43: 5000 | U43: given to abbu
B44: Category | E44: Budget | F44: Subcategory | I44: Budget | J44: Cost | L44: TGC | P44: 46101 | Q44: Donation | R44: Donation | S44: Cash | T44: =200+50+200 -> 450 | U44: mosjid+unkonwn+
B45: RentAndPaybill | E45: =Sum(I45:I50) -> 16070 | F45: {=INDIRECT("Subcategory")} -> HouseRent | I45: 13000 | J45: {=sum(IF(($R$3:$R$100=F45), $T$3:$T$100, 0))} -> 13000 | L45: =sum(J45:J50) -> 15945 | M45: =I45+I48+I50 -> 14880 | P45: 46101 | Q45: ExtraExpenses | R45: ExtraExpenses | S45: Cash | T45: 250 | U45: tupi
F46: ElectricBill_Dhk | I46: 0 | J46: {=sum(IF(($R$3:$R$100=F46), $T$3:$T$100, 0))} -> 0 | P46: 46101 | Q46: ExtraExpenses | R46: Travel | S46: Cash | T46: 70
F47: ElectricBill_Swk | I47: 350 | J47: {=sum(IF(($R$3:$R$100=F47), $T$3:$T$100, 0))} -> 225 | P47: 46101 | Q47: ExtraExpenses | R47: BooksOrCourses | S47: Cash | T47: 80 | U47: rosun
F48: GassBill | I48: 1080 | J48: {=sum(IF(($R$3:$R$100=F48), $T$3:$T$100, 0))} -> 1080 | P48: 46101 | Q48: Donation | R48: Donation | S48: Cash | T48: 500 | U48: mosjid
F49: WifiBill | I49: 840 | J49: {=sum(IF(($R$3:$R$100=F49), $T$3:$T$100, 0))} -> 840 | P49: 46101 | Q49: ExtraExpenses | R49: BooksOrCourses | S49: Cash | T49: =(1160+500+500)+(500+100+200)+500 -> 3460 | U49: edi
F50: ServiceBill | I50: 800 | J50: {=sum(IF(($R$3:$R$100=F50), $T$3:$T$100, 0))} -> 800 | P50: 46100 | Q50: MobileInternet | R50: ForMine | S50: bKash | T50: =219+30 -> 249 | U50: add rec 30 on 17-03
B51: Bazar | E51: =Sum(I51:I54) -> 10000 | F51: DailyBazar | I51: 0 | J51: {=sum(IF(($R$3:$R$100=F51), $T$3:$T$100, 0))} -> 0 | L51: =sum(J51:J54) -> 10030 | P51: 46102 | Q51: MobileInternet | R51: ForOthers | S51: bKash | T51: 417 | U51: abbu
F52: Fruits | I52: 1500 | J52: {=sum(IF(($R$3:$R$100=F52), $T$3:$T$100, 0))} -> 1460 | P52: 46104 | Q52: RentAndPaybill | R52: ElectricBill_Swk | S52: bKash | T52: 225
F53: AdvGiven | I53: 8000 | J53: {=sum(IF(($R$3:$R$100=F53), $T$3:$T$100, 0))} -> 8120 | P53: 46108 | Q53: ExtraExpenses | R53: BooksOrCourses | S53: Cash | T53: 1000 | U53: goru
F54: Others | I54: 500 | J54: {=sum(IF(($R$3:$R$100=F54), $T$3:$T$100, 0))} -> 450 | P54: 46108 | Q54: ExtraExpenses | R54: Travel | S54: Cash | T54: =350+100 -> 450 | U54: swk to bar + dhaka
B55: HouseholdAccessories | E55: =sum(I55:I57) -> 1100 | F55: HouseholdAccessories | J55: {=sum(IF(($R$3:$R$100=F55), $T$3:$T$100, 0))} -> 0 | L55: =sum(J55:J58) -> 1724 | P55: 46108 | Q55: ExtraExpenses | R55: Tea | S55: Cash | T55: =170+20+20+10+15 -> 235 | U55: tea, water and others
F56: DailyAccessories | I56: 300 | J56: {=sum(IF(($R$3:$R$100=F56), $T$3:$T$100, 0))} -> 280 | P56: 46108 | Q56: HouseholdAccessories | R56: Medicine | S56: Cash | T56: 70
F57: Medicine | I57: 800 | J57: {=sum(IF(($R$3:$R$100=F57), $T$3:$T$100, 0))} -> 885 | N57: =500+200+1000+1000+6000+2000 -> 10700 | P57: 46108 | Q57: Donation | R57: Donation | S57: Cash | T57: 50
B58: MobileInternet | E58: =I58+I59 -> 700 | F58: ForMine | I58: 300 | J58: {=sum(IF(($R$3:$R$100=F58), $T$3:$T$100, 0))} -> 559 | L58: =J58+J59 -> 1184 | P58: 46109 | Q58: MobileInternet | R58: ForMine | S58: bKash | T58: 280
F59: ForOthers | I59: 400 | J59: {=sum(IF(($R$3:$R$100=F59), $T$3:$T$100, 0))} -> 625 | P59: 46108 | Q59: RentAndPaybill | R59: WifiBill | S59: bKash | T59: 840
B60: ExtraExpenses | E60: =I60+I61+I62+I63+I64 -> 27500 | F60: Tea | I60: 500 | J60: {=sum(IF(($R$3:$R$100=F60), $T$3:$T$100, 0))} -> 560 | L60: =J60+J61+J62+J63+J64 -> 28425 | P60: 46107 | Q60: MobileInternet | R60: ForOthers | S60: bKash | T60: 208
F61: Travel | I61: 10000 | J61: {=sum(IF(($R$3:$R$100=F61), $T$3:$T$100, 0))} -> 10110
F62: AiSubs | I62: 2500 | J62: {=sum(IF(($R$3:$R$100=F62), $T$3:$T$100, 0))} -> 2475
F63: BooksOrCourses | I63: 8500 | J63: {=sum(IF(($R$3:$R$100=F63), $T$3:$T$100, 0))} -> 9540 | M63: Festib
F64: ExtraExpenses | I64: 6000 | J64: {=sum(IF(($R$3:$R$100=F64), $T$3:$T$100, 0))} -> 5740
B65: Savings | E65: =sum(I65:I68) -> 2500 | F65: EximBank_2.5 | I65: 2500 | J65: {=sum(IF(($R$3:$R$100=F65), $T$3:$T$100, 0))} -> 2500 | L65: =sum(J65:J68) -> 2500
F66: CityBank_10 | I66: 0 | J66: {=sum(IF(($R$3:$R$100=F66), $T$3:$T$100, 0))} -> 0
F67: BracBank_10 | I67: 0 | J67: {=sum(IF(($R$3:$R$100=F67), $T$3:$T$100, 0))} -> 0
F68: SBL_root | I68: 0 | J68: {=sum(IF(($R$3:$R$100=F68), $T$3:$T$100, 0))} -> 0
B69: Donation | F69: Exim_root | I69: 2000 | J69: {=sum(IF(($R$3:$R$100=F69), $T$3:$T$100, 0))} -> 0
F70: Donation | I70: 100 | J70: {=sum(IF(($R$3:$R$100=F70), $T$3:$T$100, 0))} -> 2200 | M70: Fetra
B71: Pay | F71: Unknown | J71: {=sum(IF(($R$3:$R$100=F71), $T$3:$T$100, 0))} -> 40
F72: CityService | J72: {=sum(IF(($R$3:$R$100=F72), $T$3:$T$100, 0))} -> 0
F73: SblService
H75: Total | I75: =SUM(I45:I72) -> 59970 | J75: =SUM(J45:J72) -> 61489 | L75: =I75-J75 -> -1519
H76: Non-Cash | I76: =I46+I47+I49+I58+I59+I63+I67+I68+I62+I64+I65+I66 -> 21390 | J76: =J46+J47+J49+J58+J59+J63+J67+J68+J62+J64+J65+J66 -> 22504 | L76: =I76-J76 -> -1114
H77: Cash | I77: =I75-I76 -> 38580 | J77: =J75-J76 -> 38985 | L77: =I77-J77 -> -405
B82: E I D - B U D G E T | I82: =sum(I85:I116) -> 29500 | J82: =sum(J85:J116) -> 10600 | L82: =I82-J82 -> 18900
B84: Category | E84: Budget | F84: Subcategory | I84: Budget | J84: Cost | L84: TGC
B85: Shoping -suba | E85: =SUM(I85:I88) -> 4600 | F85: dress | I85: 3200 | J85: 3200 | L85: =sum(I85:I88) - sum(J85:J88) -> 0
F86: juta | I86: 1400 | J86: 1400
B89: shoping -ammu | E89: =SUM(I89:I92) -> 0 | F89: dress-3pc | L89: =sum(I89:I92) - sum(J89:J92) -> 0
B93: shoping -nodi | E93: =SUM(I93:I96) -> 0 | F93: dress-3pc | L93: =sum(I93:I96) - sum(J93:J96) -> 0
B97: shoping -abbu | E97: =SUM(I97:I100) -> 3800 | F97: t-shirt | I97: 1400 | J97: 1400 | L97: =sum(I97:I100) - sum(J97:J100) -> 900
F98: t-shirt Reg 2x | I98: 1400 | J98: 1500
F99: Lungi | I99: 1000
B101: shoping -me | E101: =SUM(I101:I104) -> 2100 | F101: Juta | L101: =sum(I101:I104) - sum(J101:J104) -> -1000
F102: shirt/panjabi | I102: 1500 | J102: 2100
F103: t-shirt | I103: 600 | J103: 1000
B105: travel | E105: =SUM(I105:I108) -> 10000 | F105: Dhk to Swk 3x | I105: 5000 | L105: =sum(I105:I108) - sum(J105:J108) -> 10000
F106: Swk to Dhk 3x | I106: 5000
F107: other cost
B109: Bazar | E109: =SUM(I109:I112) -> 5000 | F109: bazar | I109: 5000 | L109: =sum(I109:I112) - sum(J109:J112) -> 5000
B113: Others | E113: =SUM(I113:I116) -> 4000 | F113: donation 1 | L113: =sum(I113:I116) - sum(J113:J116) -> 4000
F114: Fetra | I114: 1000
F115: Salami | I115: 1000
F116: others | I116: 2000
B124: L o w e s t - B U D G E T | I124: =SUM(I127:I156) -> 34970 | J124: =SUM(J127:J156) -> 61489
B126: Category | E126: Budget | F126: Subcategory | I126: Budget | J126: Cost | L126: TGC
B127: RentAndPaybill | E127: =Sum(I127:I132) -> 17120 | F127: {=INDIRECT("Subcategory")} -> HouseRent | I127: 13000 | J127: {=sum(IF(($R$3:$R$100=F127), $T$3:$T$100, 0))} -> 13000 | L127: =sum(J127:J132) -> 15945
F128: ElectricBill_Dhk | I128: 1000 | J128: {=sum(IF(($R$3:$R$100=F128), $T$3:$T$100, 0))} -> 0
F129: ElectricBill_Swk | I129: 400 | J129: {=sum(IF(($R$3:$R$100=F129), $T$3:$T$100, 0))} -> 225
...

Sheet Apr 26
B2: T r a n s a c t i o n & P a y | H2: DAY | I2: Date | J2: =sum(J4:J39) -> 35779 | L2: FINANCIAL STATUS | N2: =M4+M5+M8+M9+M12 -> 57831 | P2: Date | Q2: Category | R2: Subcategory | S2: Payment Method | T2: Amount | U2: Remarks | W2: R e m i n d M e
B3: Date | C3: Cost | D3: Amount | E3: FROM | F3: TO | J3: Cost | L3: Type | M3: Current Status | N3: Start with | P3: 46110 | Q3: ExtraExpenses | R3: AiSubs | S3: City | T3: 2475 | W3: Date | X3: Task
B4: 46096 | D4: 49500 | E4: Add | F4: SCB | H4: =TEXT(I4, "dddd") -> Thursday | I4: 46107 | J4: {=sum(IF(($P$3:$P$100=I4), $T$3:$T$100, 0))} -> 0 | L4: {=INDIRECT("Account")} -> Cash | M4: {=N4 - sum(IF(($E$4:$E$49=L4), $D$4:$D$39 + $C$4:$C$39, 0)) + sum(IF(($F$4:$F$49=L4), $D$4:$D$39, 0)) - sum(IF(($S$3:$S$100=L4), $T$3:$T$100, 0))} -> 2060 | N4: ='March 26'!M4 -> 565 | P4: 46110 | Q4: RentAndPaybill | R4: HouseRent | S4: Cash | T4: 13000 | W4: 46099 | X4: Ticket Dhk to Swk
B5: 46109 | D5: 38000 | E5: SCB | F5: City | H5: =TEXT(I5, "dddd") -> Friday | I5: 46108 | J5: {=sum(IF(($P$3:$P$100=I5), $T$3:$T$100, 0))} -> 0 | L5: SCB | M5: {=N5 - sum(IF(($E$4:$E$49=L5), $D$4:$D$39 + $C$4:$C$39, 0)) + sum(IF(($F$4:$F$49=L5), $D$4:$D$39, 0)) - sum(IF(($S$3:$S$100=L5), $T$3:$T$100, 0))} -> 39417 | N5: ='March 26'!M5 -> 417 | P5: 46110 | Q5: RentAndPaybill | R5: GassBill | S5: Cash | T5: 1080 | W5: 46107 | X5: Ticket Swk to Dhk
B6: 46110 | D6: 35000 | E6: City | F6: Cash | H6: =TEXT(I6, "dddd") -> Saturday | I6: 46109 | J6: {=sum(IF(($P$3:$P$100=I6), $T$3:$T$100, 0))} -> 0 | L6: SBL | M6: {=N6 - sum(IF(($E$4:$E$49=L6), $D$4:$D$39 + $C$4:$C$39, 0)) + sum(IF(($F$4:$F$49=L6), $D$4:$D$39, 0)) - sum(IF(($S$3:$S$100=L6), $T$3:$T$100, 0))} -> 50009 | N6: ='March 26'!M6 -> 9 | P6: 46110 | Q6: RentAndPaybill | R6: ServiceBill | S6: Cash | T6: 800 | W6: 46085 | X6: Reminder for adv ticket
B7: 46110 | D7: 10000 | E7: Cash | F7: Pay | H7: =TEXT(I7, "dddd") -> Sunday | I7: 46110 | J7: {=sum(IF(($P$3:$P$100=I7), $T$3:$T$100, 0))} -> 27475 | L7: EXIM | M7: {=N7 - sum(IF(($E$4:$E$49=L7), $D$4:$D$39 + $C$4:$C$39, 0)) + sum(IF(($F$4:$F$49=L7), $D$4:$D$39, 0)) - sum(IF(($S$3:$S$100=L7), $T$3:$T$100, 0))} -> 285 | N7: ='March 26'!M7 -> 285 | P7: 46110 | Q7: Bazar | R7: AdvGiven | S7: Cash | T7: =10000+120 -> 10120
B8: 46108 | D8: 1000 | E8: Add | F8: Cash | H8: =TEXT(I8, "dddd") -> Monday | I8: 46111 | J8: {=sum(IF(($P$3:$P$100=I8), $T$3:$T$100, 0))} -> 0 | L8: bKash | M8: {=N8 - sum(IF(($E$4:$E$49=L8), $D$4:$D$39 + $C$4:$C$39, 0)) + sum(IF(($F$4:$F$49=L8), $D$4:$D$39, 0)) - sum(IF(($S$3:$S$100=L8), $T$3:$T$100, 0))} -> 468 | N8: ='March 26'!M8 -> 7 | P8: 46112 | Q8: ExtraExpenses | R8: Tea | S8: Cash | T8: 30
B9: 46111 | D9: 500 | E9: City | F9: bKash | H9: =TEXT(I9, "dddd") -> Tuesday | I9: 46112 | J9: {=sum(IF(($P$3:$P$100=I9), $T$3:$T$100, 0))} -> 130 | L9: Nagad | M9: {=N9 - sum(IF(($E$4:$E$49=L9), $D$4:$D$39 + $C$4:$C$39, 0)) + sum(IF(($F$4:$F$49=L9), $D$4:$D$39, 0)) - sum(IF(($S$3:$S$100=L9), $T$3:$T$100, 0))} -> 2 | N9: ='March 26'!M9 -> 2 | P9: 46112 | Q9: HouseholdAccessories | R9: Medicine | S9: Cash | T9: 100 | U9: napa + surgel
B10: 46111 | D10: 102000 | E10: Add | F10: SCB | H10: =TEXT(I10, "dddd") -> Wednesday | I10: 46113 | J10: {=sum(IF(($P$3:$P$100=I10), $T$3:$T$100, 0))} -> 0 | L10: LendTaken | M10: =N10-10000 -> 10000 | N10: ='March 26'!M10 -> 20000 | P10: 46114 | Q10: ExtraExpenses | R10: ExtraExpenses | S10: Cash | T10: 120
B11: 46111 | D11: 1000 | E11: SCB | F11: City | H11: =TEXT(I11, "dddd") -> Thursday | I11: 46114 | J11: {=sum(IF(($P$3:$P$100=I11), $T$3:$T$100, 0))} -> 210 | L11: LendGiven | M11: {=N11 - sum(IF(($E$4:$E$49=L11), $D$4:$D$39 + $C$4:$C$39, 0)) + sum(IF(($F$4:$F$49=L11), $D$4:$D$39, 0)) - sum(IF(($S$3:$S$100=L11), $T$3:$T$100, 0))} -> 5500 | N11: ='March 26'!M11 -> 5500 | P11: 46114 | Q11: Bazar | R11: Others | S11: Cash | T11: 90
B12: 46114 | D12: 1000 | E12: SCB | F12: Cash | H12: =TEXT(I12, "dddd") -> Friday | I12: 46115 | J12: {=sum(IF(($P$3:$P$100=I12), $T$3:$T$100, 0))} -> 0 | L12: City | M12: {=N12 - sum(IF(($E$4:$E$49=L12), $D$4:$D$39 + $C$4:$C$39, 0)) + sum(IF(($F$4:$F$49=L12), $D$4:$D$39, 0)) - sum(IF(($S$3:$S$100=L12), $T$3:$T$100, 0))} -> 15884 | N12: ='March 26'!M12 -> 119 | P12: 46116 | Q12: ExtraExpenses | R12: Travel | S12: Cash | T12: 145
B13: 46125 | D13: 1000 | E13: City | F13: Cash | H13: =TEXT(I13, "dddd") -> Saturday | I13: 46116 | J13: {=sum(IF(($P$3:$P$100=I13), $T$3:$T$100, 0))} -> 145 | N13: ='March 26'!M13 | P13: 46117 | Q13: Bazar | R13: Others | S13: Cash | T13: 100
B14: 46130 | D14: 50000 | E14: SCB | F14: SBL | H14: =TEXT(I14, "dddd") -> Sunday | I14: 46117 | J14: {=sum(IF(($P$3:$P$100=I14), $T$3:$T$100, 0))} -> 308 | P14: 46118 | Q14: ExtraExpenses | R14: Travel | S14: Cash | T14: 170
B15: 46130 | D15: 20000 | E15: SCB | F15: City | H15: =TEXT(I15, "dddd") -> Monday | I15: 46118 | J15: {=sum(IF(($P$3:$P$100=I15), $T$3:$T$100, 0))} -> 950 | L15: LEND GIVEN TO | N15: =sum(M17:M22) -> 5500 | P15: 46118 | Q15: ExtraExpenses | R15: ExtraExpenses | S15: Cash | T15: 630 | U15: meet with mama
B16: 46131 | D16: 1000 | E16: City | F16: Cash | H16: =TEXT(I16, "dddd") -> Tuesday | I16: 46119 | J16: {=sum(IF(($P$3:$P$100=I16), $T$3:$T$100, 0))} -> 0 | L16: Date | M16: Given To | N16: Amount | P16: 46118 | Q16: ExtraExpenses | R16: Tea | S16: Cash | T16: 120
B17: 46134 | D17: 1000 | E17: City | F17: bKash | H17: =TEXT(I17, "dddd") -> Wednesday | I17: 46120 | J17: {=sum(IF(($P$3:$P$100=I17), $T$3:$T$100, 0))} -> 0 | L17: 45774 | M17: 2500 | N17: Rajib vai | P17: 46121 | Q17: ExtraExpenses | R17: ExtraExpenses | S17: Cash | T17: 900 | U17: given to ammu to buy an umbrella
B18: 46135 | D18: 2000 | E18: City | F18: Cash | H18: =TEXT(I18, "dddd") -> Thursday | I18: 46121 | J18: {=sum(IF(($P$3:$P$100=I18), $T$3:$T$100, 0))} -> 950 | M18: 3000 | N18: Rafi vai | P18: 46121 | Q18: ExtraExpenses | R18: Tea | S18: Cash | T18: 50
H19: =TEXT(I19, "dddd") -> Friday | I19: 46122 | J19: {=sum(IF(($P$3:$P$100=I19), $T$3:$T$100, 0))} -> 65 | P19: 46122 | Q19: ExtraExpenses | R19: ExtraExpenses | S19: Cash | T19: 65
H20: =TEXT(I20, "dddd") -> Saturday | I20: 46123 | J20: {=sum(IF(($P$3:$P$100=I20), $T$3:$T$100, 0))} -> 0 | P20: 46125 | Q20: ExtraExpenses | R20: Tea | S20: Cash | T20: 45
H21: =TEXT(I21, "dddd") -> Sunday | I21: 46124 | J21: {=sum(IF(($P$3:$P$100=I21), $T$3:$T$100, 0))} -> 0 | P21: 46125 | Q21: HouseholdAccessories | R21: DailyAccessories | S21: Cash | T21: 205
H22: =TEXT(I22, "dddd") -> Monday | I22: 46125 | J22: {=sum(IF(($P$3:$P$100=I22), $T$3:$T$100, 0))} -> 330 | P22: 46125 | Q22: Bazar | R22: Others | S22: Cash | T22: 80
H23: =TEXT(I23, "dddd") -> Tuesday | I23: 46126 | J23: {=sum(IF(($P$3:$P$100=I23), $T$3:$T$100, 0))} -> 2815 | P23: 46126 | Q23: Savings | R23: EximBank_2.5 | S23: SCB | T23: 2500
H24: =TEXT(I24, "dddd") -> Wednesday | I24: 46127 | J24: {=sum(IF(($P$3:$P$100=I24), $T$3:$T$100, 0))} -> 0 | L24: LEND TAKEN FROM | N24: =sum(N26:N31) -> 10000 | P24: 46126 | Q24: HouseholdAccessories | R24: Medicine | S24: Cash | T24: 315
H25: =TEXT(I25, "dddd") -> Thursday | I25: 46128 | J25: {=sum(IF(($P$3:$P$100=I25), $T$3:$T$100, 0))} -> 0 | L25: Date | M25: Taken From | N25: Amount | P25: 46129 | Q25: ExtraExpenses | R25: Travel | S25: Cash | T25: =130+10 -> 140
H26: =TEXT(I26, "dddd") -> Friday | I26: 46129 | J26: {=sum(IF(($P$3:$P$100=I26), $T$3:$T$100, 0))} -> 205 | L26: 46075 | M26: ammu | N26: 10000 | P26: 46129 | Q26: ExtraExpenses | R26: Tea | S26: Cash | T26: 65
H27: =TEXT(I27, "dddd") -> Saturday | I27: 46130 | J27: {=sum(IF(($P$3:$P$100=I27), $T$3:$T$100, 0))} -> 125 | P27: 46117 | Q27: MobileInternet | R27: ForOthers | S27: bKash | T27: 208
H28: =TEXT(I28, "dddd") -> Sunday | I28: 46131 | J28: {=sum(IF(($P$3:$P$100=I28), $T$3:$T$100, 0))} -> 430 | P28: 46118 | Q28: MobileInternet | R28: ForMine | S28: bKash | T28: 30
H29: =TEXT(I29, "dddd") -> Monday | I29: 46132 | J29: {=sum(IF(($P$3:$P$100=I29), $T$3:$T$100, 0))} -> 100 | P29: 46130 | Q29: Bazar | R29: Fruits | S29: Cash | T29: 125 | U29: dab
H30: =TEXT(I30, "dddd") -> Tuesday | I30: 46133 | J30: {=sum(IF(($P$3:$P$100=I30), $T$3:$T$100, 0))} -> 0 | P30: 46131 | Q30: Bazar | R30: Fruits | S30: Cash | T30: 430 | U30: fruits
H31: =TEXT(I31, "dddd") -> Wednesday | I31: 46134 | J31: {=sum(IF(($P$3:$P$100=I31), $T$3:$T$100, 0))} -> 1241 | P31: 46132 | Q31: ExtraExpenses | R31: ExtraExpenses | S31: Cash | T31: 100 | U31: mug
H32: =TEXT(I32, "dddd") -> Thursday | I32: 46135 | J32: {=sum(IF(($P$3:$P$100=I32), $T$3:$T$100, 0))} -> 90 | P32: 46134 | Q32: HouseholdAccessories | R32: HouseholdAccessories | S32: Cash | T32: 210 | U32: rats
H33: =TEXT(I33, "dddd") -> Friday | I33: 46136 | J33: {=sum(IF(($P$3:$P$100=I33), $T$3:$T$100, 0))} -> 0 | L33: Savings | N33: =sum(M35:M39) -> 40000 | P33: 46134 | Q33: Bazar | R33: AdvGiven | S33: Cash | T33: 50 | U33: to suba
H34: =TEXT(I34, "dddd") -> Saturday | I34: 46137 | J34: {=sum(IF(($P$3:$P$100=I34), $T$3:$T$100, 0))} -> 210 | L34: Type | M34: Current | N34: Prev | P34: 46134 | Q34: ExtraExpenses | R34: Tea | S34: Cash | T34: =4*30 -> 120
H35: =TEXT(I35, "dddd") -> Sunday | I35: 46138 | J35: {=sum(IF(($P$3:$P$100=I35), $T$3:$T$100, 0))} -> 0 | L35: {=INDIRECT("SavingsAcc")} -> EximBank_2.5 | M35: {=N35+sum(IF(($R$3:$R$100=L35), $T$3:$T$100, 0))} -> 40000 | N35: ='March 26'!M35 -> 37500 | P35: 46134 | Q35: Donation | R35: Donation | S35: Cash | T35: 10
J36: {=sum(IF(($P$3:$P$100=I36), $T$3:$T$100, 0))} -> 0 | L36: CityBank_10 | M36: {=N36+sum(IF(($R$3:$R$100=L36), $T$3:$T$100, 0))} -> 0 | N36: 0 | P36: 46134 | Q36: RentAndPaybill | R36: ElectricBill_Swk | S36: bKash | T36: 386
L37: BracBank_10 | P37: 46134 | Q37: MobileInternet | R37: ForOthers | S37: bKash | T37: 205 | U37: ammu
L38: SBL_root | P38: 46137 | Q38: MobileInternet | R38: ForOthers | S38: bKash | T38: 180 | U38: abbu
L39: Exim_root | P39: 46137 | Q39: MobileInternet | R39: ForMine | S39: bKash | T39: 30
P40: 46135 | Q40: ExtraExpenses | R40: Tea | S40: Cash | T40: =6*15 -> 90
P41: 46134 | Q41: HouseholdAccessories | R41: DailyAccessories | S41: City | T41: 260
B42: B U D G E T | M42: Payment Remaining
B44: Category | E44: Budget | F44: Subcategory | I44: Budget | J44: Cost | L44: TGC | M44: Days
B45: RentAndPaybill | E45: =Sum(I45:I50) -> 15230 | F45: {=INDIRECT("Subcategory")} -> HouseRent | I45: 13000 | J45: {=sum(IF(($R$3:$R$100=F45), $T$3:$T$100, 0))} -> 13000 | L45: =sum(J45:J50) -> 15266 | M45: =IF(DATE(2026, 4, 10) > TODAY(), DATE(2026, 4, 10) - TODAY(), "Exceed") -> Exceed
F46: ElectricBill_Dhk | I46: 0 | J46: {=sum(IF(($R$3:$R$100=F46), $T$3:$T$100, 0))} -> 0 | M46: =IF(DATE(2026, 4, 15) > TODAY(), DATE(2026, 4, 15) - TODAY(), "Exceed") -> Exceed
F47: ElectricBill_Swk | I47: 350 | J47: {=sum(IF(($R$3:$R$100=F47), $T$3:$T$100, 0))} -> 386 | M47: =IF(DATE(2026, 4, 24) > TODAY(), DATE(2026, 4, 24) - TODAY(), "Exceed") -> Exceed
F48: GassBill | I48: 1080 | J48: {=sum(IF(($R$3:$R$100=F48), $T$3:$T$100, 0))} -> 1080
F49: WifiBill | I49: 0 | J49: {=sum(IF(($R$3:$R$100=F49), $T$3:$T$100, 0))} -> 0 | M49: =IF(DATE(2026, 3, 27) > TODAY(), DATE(2026, 3, 27) - TODAY(), "Exceed") -> Exceed
F50: ServiceBill | I50: 800 | J50: {=sum(IF(($R$3:$R$100=F50), $T$3:$T$100, 0))} -> 800
B51: Bazar | E51: =Sum(I51:I54) -> 11000 | F51: DailyBazar | I51: 0 | J51: {=sum(IF(($R$3:$R$100=F51), $T$3:$T$100, 0))} -> 0 | L51: =sum(J51:J54) -> 10995
F52: Fruits | I52: 500 | J52: {=sum(IF(($R$3:$R$100=F52), $T$3:$T$100, 0))} -> 555
F53: AdvGiven | I53: 10000 | J53: {=sum(IF(($R$3:$R$100=F53), $T$3:$T$100, 0))} -> 10170
F54: Others | I54: 500 | J54: {=sum(IF(($R$3:$R$100=F54), $T$3:$T$100, 0))} -> 270
B55: HouseholdAccessories | E55: =sum(I55:I57) -> 500 | F55: HouseholdAccessories | I55: 0 | J55: {=sum(IF(($R$3:$R$100=F55), $T$3:$T$100, 0))} -> 210 | L55: =sum(J55:J58) -> 1150
F56: DailyAccessories | I56: 200 | J56: {=sum(IF(($R$3:$R$100=F56), $T$3:$T$100, 0))} -> 465
F57: Medicine | I57: 300 | J57: {=sum(IF(($R$3:$R$100=F57), $T$3:$T$100, 0))} -> 415
B58: MobileInternet | E58: =I58+I59 -> 500 | F58: ForMine | I58: 100 | J58: {=sum(IF(($R$3:$R$100=F58), $T$3:$T$100, 0))} -> 60 | L58: =J58+J59 -> 653
F59: ForOthers | I59: 400 | J59: {=sum(IF(($R$3:$R$100=F59), $T$3:$T$100, 0))} -> 593
B60: ExtraExpenses | E60: =I60+I61+I62+I63+I64 -> 2600 | F60: Tea | I60: 100 | J60: {=sum(IF(($R$3:$R$100=F60), $T$3:$T$100, 0))} -> 520 | L60: =J60+J61+J62+J63+J64 -> 5265
F61: Travel | I61: 0 | J61: {=sum(IF(($R$3:$R$100=F61), $T$3:$T$100, 0))} -> 455
F62: AiSubs | I62: 2500 | J62: {=sum(IF(($R$3:$R$100=F62), $T$3:$T$100, 0))} -> 2475 | M62: =IF(DATE(2026, 3, 28) > TODAY(), DATE(2026, 3, 28) - TODAY(), "Exceed") -> Exceed
F63: BooksOrCourses | I63: 0 | J63: {=sum(IF(($R$3:$R$100=F63), $T$3:$T$100, 0))} -> 0
F64: ExtraExpenses | I64: 0 | J64: {=sum(IF(($R$3:$R$100=F64), $T$3:$T$100, 0))} -> 1815
B65: Savings | E65: =sum(I65:I68) -> 2500 | F65: EximBank_2.5 | I65: 2500 | J65: {=sum(IF(($R$3:$R$100=F65), $T$3:$T$100, 0))} -> 2500 | L65: =sum(J65:J68) -> 2500 | M65: =IF(DATE(2026, 4, 20) > TODAY(), DATE(2026, 4, 20) - TODAY(), "Exceed") -> Exceed
F66: CityBank_10 | I66: 0 | J66: {=sum(IF(($R$3:$R$100=F66), $T$3:$T$100, 0))} -> 0
F67: BracBank_10 | I67: 0 | J67: {=sum(IF(($R$3:$R$100=F67), $T$3:$T$100, 0))} -> 0
F68: SBL_root | I68: 0 | J68: {=sum(IF(($R$3:$R$100=F68), $T$3:$T$100, 0))} -> 0
B69: Donation | F69: Exim_root | I69: 1100 | J69: {=sum(IF(($R$3:$R$100=F69), $T$3:$T$100, 0))} -> 0
F70: Donation | J70: {=sum(IF(($R$3:$R$100=F70), $T$3:$T$100, 0))} -> 10
B71: Pay | F71: Unknown | J71: {=sum(IF(($R$3:$R$100=F71), $T$3:$T$100, 0))} -> 0
F72: CityService | J72: {=sum(IF(($R$3:$R$100=F72), $T$3:$T$100, 0))} -> 0
F73: SblService
H75: Total | I75: =SUM(I45:I72) -> 33430 | J75: =SUM(J45:J72) -> 35779 | L75: =I75-J75 -> -2349
H76: Non-Cash | I76: =I46+I47+I49+I58+I59+I63+I67+I68+I62+I64+I65+I66 -> 5850 | J76: =J46+J47+J49+J58+J59+J63+J67+J68+J62+J64+J65+J66 -> 7829 | L76: =I76-J76 -> -1979
H77: Cash | I77: =I75-I76 -> 27580 | J77: =J75-J76 -> 27950 | L77: =I77-J77 -> -370
B81: L o w e s t - B U D G E T | I81: =SUM(I84:I113) -> 34970 | J81: =SUM(J84:J113) -> 35779
B83: Category | E83: Budget | F83: Subcategory | I83: Budget | J83: Cost | L83: TGC
B84: RentAndPaybill | E84: =Sum(I84:I89) -> 17120 | F84: {=INDIRECT("Subcategory")} -> HouseRent | I84: 13000 | J84: {=sum(IF(($R$3:$R$100=F84), $T$3:$T$100, 0))} -> 13000 | L84: =sum(J84:J89) -> 15266
F85: ElectricBill_Dhk | I85: 1000 | J85: {=sum(IF(($R$3:$R$100=F85), $T$3:$T$100, 0))} -> 0
F86: ElectricBill_Swk | I86: 400 | J86: {=sum(IF(($R$3:$R$100=F86), $T$3:$T$100, 0))} -> 386
